Workbook

Sheet Tổng hợp
A1: STT | B1: Danh mục | C1: Trạng thái DNS lần 1 | D1: Trạng thái DNS lần 2 | E1: Trạng thái TPE lần 1 | F1: Trạng thái TPE lần 2 | G1: Tổng số testcase | H1: Số TH kiểm thử đạt | I1: Số TH kiểm thử không đạt | J1: Số TH đang xem xét (PE) | K1: Số TH kiểm chưa test | L1: Tổng số TH đã kiểm thử | M1: Tỉ lệ TH kiểm thử đạt (%P) | N1: Tỉ lệ TH kiểm thử không đạt (%F) | O1: Tỉ lệ TH đã thực hiện (%Cover) | P1: DNS note | Q1: TPE Note
A2: =Row()-ROW($A$1) | B2: DM dịch vụ sửa chữa và chi phí khác | C2: Đã xong | G2: ='1. DM dịch vụ sửa chữa và chi '!K16 | H2: ='1. DM dịch vụ sửa chữa và chi '!K11 | I2: ='1. DM dịch vụ sửa chữa và chi '!K12 | J2: ='1. DM dịch vụ sửa chữa và chi '!K13 | K2: ='1. DM dịch vụ sửa chữa và chi '!K14 | L2: ='1. DM dịch vụ sửa chữa và chi '!K15 | M2: =ROUND(H2/G2 * 100,2) | N2: =ROUND(I2/G2 * 100,2) | O2: =ROUND(L2/G2 * 100,2)
A3: =Row()-ROW($A$1) | B3: Danh mục tiền tệ | C3: Đã xong | G3: ='2. DM tiền tệ'!K16 | H3: ='2. DM tiền tệ'!K11 | I3: ='2. DM tiền tệ'!K12 | J3: ='2. DM tiền tệ'!K13 | K3: ='2. DM tiền tệ'!K14 | L3: ='2. DM tiền tệ'!K16 | M3: =ROUND(H3/G3 * 100,2) | N3: =ROUND(I3/G3 * 100,2) | O3: =ROUND(L3/G3 * 100,2)
A4: =Row()-ROW($A$1) | B4: Danh mục tài khoản | C4: Đã xong | G4: ='3. DM tài khoản'!K11 | H4: ='3. DM tài khoản'!K12 | I4: ='3. DM tài khoản'!K13 | J4: ='3. DM tài khoản'!K14 | K4: ='3. DM tài khoản'!K15 | L4: ='3. DM tài khoản'!K16 | M4: =ROUND(H4/G4 * 100,2) | N4: =ROUND(I4/G4 * 100,2) | O4: =ROUND(L4/G4 * 100,2)
A5: =Row()-ROW($A$1) | B5: Danh mục loại tài khoản | C5: Đã xong | G5: ='4. DM loại tài khoản'!K16 | H5: ='4. DM loại tài khoản'!K12 | I5: ='4. DM loại tài khoản'!K13 | J5: ='4. DM loại tài khoản'!K14 | K5: ='4. DM loại tài khoản'!K15 | L5: ='4. DM loại tài khoản'!K16 | M5: =ROUND(H5/G5 * 100,2) | N5: =ROUND(I5/G5 * 100,2) | O5: =ROUND(L5/G5 * 100,2)
A6: =Row()-ROW($A$1) | B6: Cập nhật nhanh giá dịch vụ | C6: Đã xong | G6: ='5. Cập nhật nhanh giá dịch vụ'!K16 | H6: ='5. Cập nhật nhanh giá dịch vụ'!K11 | I6: ='5. Cập nhật nhanh giá dịch vụ'!K12 | J6: ='5. Cập nhật nhanh giá dịch vụ'!K13 | K6: ='5. Cập nhật nhanh giá dịch vụ'!K14 | L6: ='5. Cập nhật nhanh giá dịch vụ'!K15 | M6: =ROUND(H6/G6 * 100,2) | N6: =ROUND(I6/G6 * 100,2) | O6: =ROUND(L6/G6 * 100,2)
A7: =Row()-ROW($A$1) | B7: DM serial thiết bị làm dịch vụ | C7: Đã xong | G7: ='6. DM serial thiết bị làm dịch '!K16 | H7: ='6. DM serial thiết bị làm dịch '!K11 | I7: ='6. DM serial thiết bị làm dịch '!K12 | J7: ='6. DM serial thiết bị làm dịch '!K13 | K7: ='6. DM serial thiết bị làm dịch '!K14 | L7: ='6. DM serial thiết bị làm dịch '!K15 | M7: =ROUND(H7/G7 * 100,2) | N7: =ROUND(I7/G7 * 100,2) | O7: =ROUND(L7/G7 * 100,2)
A8: =Row()-ROW($A$1) | B8: DM cấp dịch vụ bảo dưỡng | C8: Đã xong | G8: ='7. DM cấp dịch vụ bảo dưỡng'!K16 | H8: ='7. DM cấp dịch vụ bảo dưỡng'!K11 | I8: ='7. DM cấp dịch vụ bảo dưỡng'!K12 | J8: ='7. DM cấp dịch vụ bảo dưỡng'!K13 | K8: ='7. DM cấp dịch vụ bảo dưỡng'!K14 | L8: ='8. DM ghi chú kiểm tra bảo dưỡn'!K15 | M8: =ROUND(H8/G8 * 100,2) | N8: =ROUND(I8/G8 * 100,2) | O8: =ROUND(L8/G8 * 100,2)
A9: =Row()-ROW($A$1) | B9: DM ghi chú kiểm tra bảo dưỡng | C9: Đã xong | G9: ='8. DM ghi chú kiểm tra bảo dưỡn'!K16 | H9: ='8. DM ghi chú kiểm tra bảo dưỡn'!K11 | I9: ='8. DM ghi chú kiểm tra bảo dưỡn'!K12 | J9: ='8. DM ghi chú kiểm tra bảo dưỡn'!K13 | K9: ='8. DM ghi chú kiểm tra bảo dưỡn'!K14 | L9: ='8. DM ghi chú kiểm tra bảo dưỡn'!K15 | M9: =ROUND(H9/G9 * 100,2) | N9: =ROUND(I9/G9 * 100,2) | O9: =ROUND(L9/G9 * 100,2)
A10: =Row()-ROW($A$1) | B10: DM khách hàng | C10: Đang hoàn thiện | G10: ='9. DM khách hàng'!K16 | H10: ='9. DM khách hàng'!K11 | I10: ='9. DM khách hàng'!K12 | J10: ='9. DM khách hàng'!K13 | K10: ='9. DM khách hàng'!K14 | L10: ='9. DM khách hàng'!K15 | M10: =ROUND(H10/G10 * 100,2) | N10: =ROUND(I10/G10 * 100,2) | O10: =ROUND(L10/G10 * 100,2)
A11: =Row()-ROW($A$1) | B11: Danh mục ngân hàng | C11: Đã xong | G11: ='10. Danh mục ngân hàng'!K16 | H11: ='10. Danh mục ngân hàng'!K11 | I11: ='10. Danh mục ngân hàng'!K12 | J11: ='10. Danh mục ngân hàng'!K13 | K11: ='10. Danh mục ngân hàng'!K14 | L11: ='10. Danh mục ngân hàng'!K15 | M11: =ROUND(H11/G11 * 100,2) | N11: =ROUND(I11/G11 * 100,2) | O11: =ROUND(L11/G11 * 100,2)
A12: =Row()-ROW($A$1) | B12: Danh mục tài khoản ngân hàng | C12: Đã xong | G12: ='11. Danh mục tài khoản ngân hàn'!K16 | H12: ='11. Danh mục tài khoản ngân hàn'!K11 | I12: ='11. Danh mục tài khoản ngân hàn'!K12 | J12: ='11. Danh mục tài khoản ngân hàn'!K13 | K12: ='11. Danh mục tài khoản ngân hàn'!K14 | L12: ='11. Danh mục tài khoản ngân hàn'!K15 | M12: =ROUND(H12/G12 * 100,2) | N12: =ROUND(I12/G12 * 100,2) | O12: =ROUND(L12/G12 * 100,2)
A13: =Row()-ROW($A$1) | B13: Danh mục gói bảo dưỡng | C13: Đã xong | G13: ='12.Danh mục gói bảo dưỡng'!K16 | H13: ='12.Danh mục gói bảo dưỡng'!K11 | I13: ='12.Danh mục gói bảo dưỡng'!K12 | J13: ='12.Danh mục gói bảo dưỡng'!K13 | K13: ='12.Danh mục gói bảo dưỡng'!K14 | L13: ='12.Danh mục gói bảo dưỡng'!K15 | M13: =ROUND(H13/G13 * 100,2) | N13: =ROUND(I13/G13 * 100,2) | O13: =ROUND(L13/G13 * 100,2)
A14: =Row()-ROW($A$1) | B14: DM quốc gia | C14: Đã xong | G14: ='13. DM quốc gia'!K16 | H14: ='13. DM quốc gia'!K11 | I14: ='13. DM quốc gia'!K12 | J14: ='13. DM quốc gia'!K13 | K14: ='13. DM quốc gia'!K14 | L14: ='13. DM quốc gia'!K15 | M14: =ROUND(H14/G14 * 100,2) | N14: =ROUND(I14/G14 * 100,2) | O14: =ROUND(L14/G14 * 100,2)
A15: =Row()-ROW($A$1) | B15: DM khu vực | C15: Đã xong | G15: ='14. DM khu vực'!K16 | H15: ='14. DM khu vực'!K11 | I15: ='14. DM khu vực'!K12 | J15: ='14. DM khu vực'!K13 | K15: ='14. DM khu vực'!K14 | L15: ='14. DM khu vực'!K15 | M15: =ROUND(H15/G15 * 100,2) | N15: =ROUND(I15/G15 * 100,2) | O15: =ROUND(L15/G15 * 100,2)
A16: =Row()-ROW($A$1) | B16: DM phường/xã | C16: Đã xong | G16: ='15. DM phườngxã'!K16 | H16: ='15. DM phườngxã'!K11 | I16: ='15. DM phườngxã'!K12 | J16: ='15. DM phườngxã'!K13 | K16: ='15. DM phườngxã'!K14 | L16: ='15. DM phườngxã'!K15 | M16: =ROUND(H16/G16 * 100,2) | N16: =ROUND(I16/G16 * 100,2) | O16: =ROUND(L16/G16 * 100,2)
A17: =Row()-ROW($A$1) | B17: DM Tỉnh/TP | C17: Đã xong | G17: ='16. DM tỉnhTP'!K16 | H17: ='16. DM tỉnhTP'!K11 | I17: ='16. DM tỉnhTP'!K12 | J17: ='16. DM tỉnhTP'!K13 | K17: ='16. DM tỉnhTP'!K14 | L17: ='16. DM tỉnhTP'!K15 | M17: =ROUND(H17/G17 * 100,2) | N17: =ROUND(I17/G17 * 100,2) | O17: =ROUND(L17/G17 * 100,2)
A18: =Row()-ROW($A$1) | B18: DM đường/phố | C18: Đã xong | G18: ='17. DM đườngphố'!K16 | H18: ='17. DM đườngphố'!K11 | I18: ='17. DM đườngphố'!K12 | J18: ='17. DM đườngphố'!K13 | K18: ='17. DM đườngphố'!K14 | L18: ='17. DM đườngphố'!K15 | M18: =ROUND(H18/G18 * 100,2) | N18: =ROUND(I18/G18 * 100,2) | O18: =ROUND(L18/G18 * 100,2)
A19: =Row()-ROW($A$1) | B19: DM quận huyện | C19: Đã xong | G19: ='18. DM quận huyện'!K16 | H19: ='18. DM quận huyện'!K11 | I19: ='18. DM quận huyện'!K12 | J19: ='18. DM quận huyện'!K13 | K19: ='18. DM quận huyện'!K14 | L19: ='18. DM quận huyện'!K15 | M19: =ROUND(H19/G19 * 100,2) | N19: =ROUND(I19/G19 * 100,2) | O19: =ROUND(L19/G19 * 100,2)
A20: =Row()-ROW($A$1) | B20: DM vụ việc | C20: Đã xong | G20: ='19. DM vụ việc '!K16 | H20: ='19. DM vụ việc '!K11 | I20: ='19. DM vụ việc '!K12 | J20: ='19. DM vụ việc '!K13 | K20: ='19. DM vụ việc '!K14 | L20: ='21. DM mã phí'!K15 | M20: =ROUND(H20/G20 * 100,2) | N20: =ROUND(I20/G20 * 100,2) | O20: =ROUND(L20/G20 * 100,2)
A21: =Row()-ROW($A$1) | B21: DM nguồn vốn | C21: Đã xong | G21: ='20. DM nguồn vốn'!K16 | H21: ='20. DM nguồn vốn'!K11 | I21: ='20. DM nguồn vốn'!K12 | J21: ='20. DM nguồn vốn'!K13 | K21: ='20. DM nguồn vốn'!K14 | L21: ='20. DM nguồn vốn'!K15 | M21: =ROUND(H21/G21 * 100,2) | N21: =ROUND(I21/G21 * 100,2) | O21: =ROUND(L21/G21 * 100,2)
A22: 21 | B22: DM mã phí | C22: Đã xong | G22: ='21. DM mã phí'!K16 | H22: ='21. DM mã phí'!K11 | I22: ='21. DM mã phí'!K12 | J22: ='21. DM mã phí'!K13 | K22: ='21. DM mã phí'!K14 | L22: ='21. DM mã phí'!K15 | M22: =ROUND(H22/G22 * 100,2) | N22: =ROUND(I22/G22 * 100,2) | O22: =ROUND(L22/G22 * 100,2)
A23: 22 | B23: DM công việc, lỗi thiết bị | C23: Đã xong | G23: ='22. DM công việc, lỗi thiết bị'!K16 | H23: ='22. DM công việc, lỗi thiết bị'!K11 | I23: ='22. DM công việc, lỗi thiết bị'!K12 | J23: ='22. DM công việc, lỗi thiết bị'!K13 | K23: ='22. DM công việc, lỗi thiết bị'!K14 | L23: ='22. DM công việc, lỗi thiết bị'!K15 | M23: =ROUND(H23/G23 * 100,2) | N23: =ROUND(I23/G23 * 100,2) | O23: =ROUND(L23/G23 * 100,2)
A24: =Row()-ROW($A$1) | B24: Yêu cầu kiểm tra sửa chữa - bảo hành | C24: Đã xong | G24: ='25. YC kiểm tra sửa chữa - BH'!K16 | H24: ='25. YC kiểm tra sửa chữa - BH'!K11 | I24: ='25. YC kiểm tra sửa chữa - BH'!K12 | J24: ='25. YC kiểm tra sửa chữa - BH'!K13 | K24: ='25. YC kiểm tra sửa chữa - BH'!K14 | L24: ='25. YC kiểm tra sửa chữa - BH'!K15 | M24: =ROUND(H24/G24 * 100,2) | N24: =ROUND(I24/G24 * 100,2) | O24: =ROUND(L24/G24 * 100,2)
A25: =Row()-ROW($A$1) | B25: Phiếu xử lý yêu cầu | C25: Đã xong | G25: ='26. Phiếu xử lý yêu cầu'!K16 | H25: ='26. Phiếu xử lý yêu cầu'!K11 | I25: ='26. Phiếu xử lý yêu cầu'!K12 | J25: ='26. Phiếu xử lý yêu cầu'!K13 | K25: ='26. Phiếu xử lý yêu cầu'!K14 | L25: ='26. Phiếu xử lý yêu cầu'!K15 | M25: =ROUND(H25/G25 * 100,2) | N25: =ROUND(I25/G25 * 100,2) | O25: =ROUND(L25/G25 * 100,2)

Sheet 1. DM dịch vụ sửa  chữa và chi 
A1: MÔ TẢ TÍNH NĂNG (đọc trước khi xem testcase)
A2: 1. Mục đích tính năng | B2: Kiểm thử TOÀN BỘ màn hình “Danh mục dịch vụ sửa chữa và chi phí khác” của phân hệ CSKH (vào theo đường dẫn: CSKH → nhóm menu “Danh mục- Dịch vụ” → “Danh mục dịch vụ sửa chữa và chi phí khác”). ► Phạm vi kiểm thử: danh sách, tìm kiếm, bộ lọc, sắp xếp, phân trang, Tạo mới, Sửa, Xem, Khóa, Mở khóa, Xóa, Xuất Excel, phân quyền và toàn bộ ràng buộc nhập liệu. ► Danh mục này khai báo 3 thông số dùng cho nghiệp vụ phía sau: % Tính giá vốn, % VAT và ĐM giảm giá. Đây là nguồn dữ liệu cho Báo giá hãng và Hợp đồng hãng. ► Màn hình dùng CHUNG dữ liệu với màn danh mục chi phí tương ứng bên phần mềm ERP: sửa ở cổng nào thì cổng còn lại cũng thấy ngay.
A3: 2. Đối tượng được tính / hiển thị | B3: ► Danh sách hiển thị toàn bộ dịch vụ sửa chữa và chi phí khác đã khai báo. Dữ liệu thực tế trên cổng dev đang có 526 dòng. ► 2 trạng thái: “Hoạt động” (nhãn xanh) và “Khóa” (nhãn đỏ). ► 2 phân loại: “Có tính doanh thu” (nhãn xanh) và “Chi phí khác” (nhãn đỏ). Phân loại này do ô tích “Dịch vụ có tính doanh thu” trên form quyết định. ► Cột “ĐM giảm giá” hiển thị định mức giảm giá của CÔNG TY ĐANG CHỌN của người đăng nhập. Cùng một dịch vụ, người của công ty A và công ty B có thể thấy hai mức khác nhau — đây là hành vi đúng. Công ty chưa khai báo thì hiển thị “—”. ► 9 cột danh sách: STT | Tên dịch vụ / chi phí | Phân loại | ĐM giảm giá | % Tính giá vốn | % VAT | Trạng thái | Cập nhật | Hành động.
A4: 3. Đối tượng bị ẩn / không tính | B4: ► Các khoản “Chi phí phải trả” và “Chi phí bán hàng” KHÔNG thuộc màn này (vẫn quản lý bên phần mềm ERP), nên không xuất hiện trong danh sách. ► Nút Tạo mới / Sửa / Xóa / Khóa / Mở khóa CHỈ hiện với người có quyền quản lý danh mục. Người chỉ được xem thì chỉ thấy nút Xem và nút Xuất Excel. ► 2 dịch vụ hệ thống là “Chi phí đi lại” và “Chi phí vận chuyển” bị khóa cứng: không sửa, không xóa, không khóa, không mở khóa được. Nút vẫn hiển thị nhưng bị làm mờ. ► Dòng đang ở trạng thái Khóa: nút Sửa và nút Xóa bị làm mờ, phải Mở khóa trước. ► Cửa sổ Tạo mới KHÔNG có ô “Trạng thái” (dịch vụ mới luôn ở trạng thái Hoạt động); ô này chỉ xuất hiện ở cửa sổ Sửa. ► Nút “Lưu & Tiếp tục” chỉ có ở cửa sổ Tạo mới, không có ở cửa sổ Sửa và Xem.
A5: 4. Bộ lọc thời gian áp dụng cho | B5: ► Màn hình KHÔNG có bộ lọc theo khoảng thời gian. ► Cột “Cập nhật” chỉ để hiển thị: dòng trên là ngày giờ sửa gần nhất, dòng dưới là người sửa (dạng MÃ NV- Họ tên). Dịch vụ chưa từng được sửa thì hiển thị người tạo. ► Cột “Cập nhật” có sắp xếp được. ► Khi mới vào màn, danh sách sắp xếp theo ngày tạo giảm dần (dịch vụ mới nhất nằm đầu). ► Hệ thống ghi nhớ bộ lọc đang áp dụng trong 10 phút: rời màn rồi quay lại trong khoảng thời gian đó thì bộ lọc cũ còn nguyên; quá 10 phút thì bộ lọc tự trở về mặc định.
A6: 5. Cấu trúc dữ liệu / cây phân cấp | B6: ► Danh mục PHẲNG, không có cấu trúc cha- con, không gom nhóm. ► Mỗi dòng gồm: Tên dịch vụ / chi phí, Phân loại, % Tính giá vốn, % VAT, Trạng thái, và ĐM giảm giá. ► Riêng ĐM giảm giá được lưu TÁCH RIÊNG THEO TỪNG CÔNG TY: một dịch vụ có thể có nhiều mức giảm giá, mỗi công ty một mức. Người dùng chỉ nhìn thấy và chỉ sửa được mức của công ty mình đang chọn. ► Dịch vụ trong danh mục này được sử dụng ở 2 nơi: Báo giá hãng và Hợp đồng hãng. Đây là căn cứ để hệ thống quyết định một dịch vụ được xóa hẳn hay chỉ được chuyển sang Khóa.
A7: 6. Quy tắc cộng dồn / deduplicate | B7: ► KHÔNG cộng dồn — mỗi dòng là một dịch vụ độc lập, màn hình không có ô tổng. ► Chống trùng: Tên dịch vụ / chi phí phải là DUY NHẤT trong toàn danh mục, không phân biệt dịch vụ đó đang Hoạt động hay đang Khóa. Khi Sửa thì không tính chính dòng đang sửa là trùng. ► Mỗi công ty chỉ có DUY NHẤT một mức ĐM giảm giá cho một dịch vụ, lưu lại nhiều lần cũng không sinh dòng thừa. ► Bỏ trống hoặc nhập 0 ở ĐM giảm giá nghĩa là “không có định mức”: hệ thống gỡ mức giảm giá của CÔNG TY ĐANG CHỌN và KHÔNG đụng tới mức của các công ty khác. ► Xóa hẳn một dịch vụ thì mức giảm giá của MỌI công ty cũng bị xóa theo. Còn Khóa thì giữ nguyên toàn bộ mức giảm giá.
A8: 7. Phân quyền cấp | B8: • Quyền “Quản lý dịch vụ sửa chữa và chi phí khác” — xem danh sách, xem chi tiết, Tạo mới, Sửa, Xóa, Khóa, Mở khóa. • Quyền “Xem dịch vụ sửa chữa và chi phí khác” — CHỈ xem danh sách, xem chi tiết, tìm kiếm và Xuất Excel. • Mục menu “Danh mục dịch vụ sửa chữa và chi phí khác” chỉ hiện khi tài khoản có ít nhất một trong hai quyền trên. Không có quyền nào thì mục menu bị ẩn và vào thẳng đường dẫn cũng bị chặn. • Mọi thao tác làm thay đổi dữ liệu (Tạo mới, Sửa, Xóa, Khóa, Mở khóa) đều yêu cầu quyền “Quản lý dịch vụ sửa chữa và chi phí khác”. • Màn hình KHÔNG phân quyền theo cấp công ty / phòng ban / bộ phận: mọi người có quyền đều nhìn thấy đủ 526 dòng. Công ty đang chọn CHỈ ảnh hưởng tới giá trị cột “ĐM giảm giá”. Quyền được cấp theo vai trò (chức danh), không cấp trực tiếp cho từng nhân viên.
A9: 8. Cách tính các ô thống kê | B9: ► Màn hình KHÔNG có khối thống kê đầu trang. Chỉ có dòng đếm ở chân bảng: ► Ô “Hiển thị a–b / N dịch vụ / chi phí”: a và b là số thứ tự dòng đầu và dòng cuối của trang đang xem; N là TỔNG số dịch vụ khớp bộ lọc (không phải số dòng của trang). ► Các ô phần trăm trên bảng (% Tính giá vốn, % VAT, ĐM giảm giá) hiển thị đúng giá trị đã lưu, tối đa 2 chữ số thập phân, tự bỏ số 0 thừa (80,00 hiển thị thành “80%”). Không có giá trị thì hiển thị “—”. ► File Excel xuất ra luôn ghi phần trăm với đúng 2 chữ số thập phân (ví dụ 80,00) — khác cách rút gọn trên màn hình. Đây là hành vi đúng của hiện trạng, không phải lỗi.
A10: 9. Ghi chú đọc bảng | B10: ► Toàn bộ Tạo mới / Sửa / Xem đều mở trong một cửa sổ nhỏ ngay trên trang, không chuyển sang màn khác. ► Lỗi nhập liệu hiển thị ngay dưới từng ô (viền đỏ + chữ đỏ) kèm thông báo đỏ “Bạn chưa nhập đầy đủ thông tin” ở góc màn hình. Cửa sổ không bị đóng và dữ liệu đã nhập vẫn còn. ► Ở 3 ô phần trăm, DẤU PHẨY được hiểu là DẤU THẬP PHÂN: nhập “12,5” sẽ lưu là 12,5 phần trăm, KHÔNG phải 125. Đây là chủ đích, khác với màn Tiền tệ. ► “% Tính giá vốn” KHÔNG bị chặn trần 100 (chỉ cần từ 0 trở lên) — dữ liệu thật đang có dòng 321%. Riêng “% VAT” và “ĐM giảm giá” bị chặn tối đa 100. ► Nút Xóa không xóa ngay: hệ thống kiểm tra trước xem dịch vụ đã được dùng ở Báo giá hãng hay Hợp đồng hãng chưa. Nếu đã dùng, hộp thoại đổi thành “Xác nhận khóa” và dịch vụ chỉ bị chuyển sang trạng thái Khóa chứ không bị xóa. ► Phân trang mặc định 10 dòng/trang, chọn được 5 / 10 / 20 / 50. ► Các TH ghi “gọi thẳng chức năng, bỏ qua giao diện” là kiểm thử bảo mật, cần công cụ kiểm thử API (Postman hoặc tương đương) — dành cho tester kỹ thuật.
A11: Testcase _ Danh mục dịch vụ sửa chữa và chi phí khác- Cập nhật ngày 12/08/2026 | F11: TEST SUMMARY | I11: Số TH DNS kiểm thử đạt (P): | K11: =COUNTIF(K18:M1001,"Passed") | M11: Số trường hợp TP kiểm thử đạt (P): | P11: =COUNTIF(O18:Q200,"Passed")
I12: Số TH DNS kiểm thử không đạt (F) | K12: =COUNTIF(K18:M1001,"Failed") | M12: Số trường hợp TP kiểm thử không đạt (F) | P12: =COUNTIF(O19:Q201,"Fail")
I13: Số TH DNS kiểm thử đang xem xét (PE) | K13: =COUNTIF(K18:M1001,"Pending") | M13: Số trường hợp TP kiểm thử đang xem xét (PE) | P13: =COUNTIF(O20:Q202,"Pending")
I14: Số TH DNS kiểm thử chưa thực hiện | K14: =COUNTIF(K18:K1001,"Not Executed") | M14: Số trường hợp TP kiểm thử chưa thực hiện | P14: =K16-P15
I15: Tổng số TH DNS kiểm thử | K15: =COUNTIF(K18:K1001,"<>") | M15: Tổng số trường hợp TP kiểm thử | P15: =sum(P11:Q13)
I16: Tổng số testcase | K16: =COUNTIF(I18:I1001,"*")
A17: Module | B17: Nhóm chức năng | C17: TC ID | D17: Chức năng | E17: Priority | F17: Tiền điều kiện | G17: Bước thực hiện | H17: Test Data | I17: Expected Result (chi tiết) | J17: KQ thực tế | K17: DNS check lần 1 | L17: DNS check lần 2 | M17: DNS check lần 3 | N17: Ghi chú | O17: TP check lần 1 | P17: TP check lần 2 | Q17: TP check lần 3
C18: PHÂN QUYỀN VÀ TRUY CẬP
A19: DV sửa chữa & CP khác | B19: Phân quyền & truy cập | C19: TC-ROLE-00 | D19: Không có quyền nào của màn — menu và màn hình bị chặn | E19: P0 | F19: Tài khoản A đăng nhập được nhưng KHÔNG có quyền “Quản lý dịch vụ sửa chữa và chi phí khác” và cũng KHÔNG có quyền “Xem dịch vụ sửa chữa và chi phí khác” | G19: 1. Đăng nhập tài khoản A, vào phân hệ CSKH 2. Mở nhóm menu “Danh mục- Dịch vụ” hoặc theo đường link chứa /customer-care/costs | H19: Tài khoản A: không có quyền nào | I19: - Nhóm “Danh mục- Dịch vụ” KHÔNG có mục “Danh mục dịch vụ sửa chữa và chi phí khác” - Vào thẳng đường dẫn: hệ thống chặn, bảng không hiển thị dòng dữ liệu nào | J19: - Nhóm “Danh mục- Dịch vụ” KHÔNG có mục “Danh mục dịch vụ sửa chữa và chi phí khác” - Vào thẳng đường dẫn: hệ thống chặn, bảng không hiển thị dòng dữ liệu nào | K19: Passed
C20: TC-ROLE-01 | D20: Chỉ có quyền “Xem dịch vụ sửa chữa và chi phí khác” | E20: P0 | F20: Tài khoản B chỉ được cấp quyền “Xem dịch vụ sửa chữa và chi phí khác” | G20: 1. Đăng nhập B, vào màn hình 2. Quan sát thanh công cụ phía trên bảng 3. Quan sát cột Hành động và cột Trạng thái | H20: Tài khoản B: chỉ quyền xem | I20: - Vào được màn hình, bảng hiển thị đủ 526 dòng, bộ lọc dùng bình thường - Thanh công cụ CHỈ có nút “Xuất Excel”, KHÔNG có nút “Tạo mới” - Cột Hành động CHỈ có nút Xem; không có nút Sửa, không có nút Xóa - Cột Trạng thái chỉ có nhãn trạng thái, KHÔNG có nút ổ khóa | J20: - Vào được màn hình, bảng hiển thị đủ 526 dòng, bộ lọc dùng bình thường - Thanh công cụ CHỈ có nút “Xuất Excel”, KHÔNG có nút “Tạo mới” - Cột Hành động CHỈ có nút Xem; không có nút Sửa, không có nút Xóa - Cột Trạng thái chỉ có nhãn trạng thái, KHÔNG có nút ổ khóa | K20: Passed
C21: TC-ROLE-02 | D21: Có quyền “Quản lý dịch vụ sửa chữa và chi phí khác” | E21: P0 | F21: Tài khoản C được cấp quyền “Quản lý dịch vụ sửa chữa và chi phí khác” | G21: 1. Đăng nhập C, vào màn hình 2. Quan sát thanh công cụ, cột Hành động, cột Trạng thái | H21: Tài khoản C: quyền quản lý | I21: - Thanh công cụ có đủ nút “Tạo mới” và “Xuất Excel” - Cột Hành động có đủ 3 nút: Xem, Sửa, Xóa - Cột Trạng thái có nút ổ khóa để Khóa / Mở khóa | J21: - Thanh công cụ có đủ nút “Tạo mới” và “Xuất Excel” - Cột Hành động có đủ 3 nút: Xem, Sửa, Xóa - Cột Trạng thái có nút ổ khóa để Khóa / Mở khóa | K21: Passed
C22: TC-ROLE-03 | D22: Chỉ quyền Xem — bấm nút Xem vẫn mở được chi tiết | E22: P0 | F22: Tài khoản B (chỉ quyền xem); danh sách có ít nhất 1 dịch vụ | G22: 1. Đăng nhập B 2. Bấm nút Xem ở một dòng bất kỳ | H22: Dịch vụ “Dịch vụ đánh bóng xy lanh” | I22: - Cửa sổ “Xem dịch vụ / chi phí” mở ra bình thường - Mọi ô đều mờ, không nhập được; chân cửa sổ chỉ có nút “Đóng” | J22: - Cửa sổ “Xem dịch vụ / chi phí” mở ra bình thường - Mọi ô đều mờ, không nhập được; chân cửa sổ chỉ có nút “Đóng” | K22: Passed
C23: TC-ROLE-04 | D23: Chỉ quyền Xem — gọi thẳng chức năng Tạo mới, bỏ qua giao diện | E23: P0 | F23: Tài khoản B (chỉ quyền xem), đã đăng nhập hợp lệ | G23: 1. Dùng công cụ kiểm thử API gọi thẳng chức năng Tạo mới với dữ liệu hợp lệ 2. Vào lại danh sách kiểm tra | H23: Tên = “TC bypass”, % Tính giá vốn = 10, % VAT = 8 | I23: - Hệ thống từ chối, báo không có quyền - KHÔNG có dịch vụ mới nào được tạo ra | J23: - Hệ thống từ chối, báo không có quyền - KHÔNG có dịch vụ mới nào được tạo ra | K23: Passed
C24: TC-ROLE-05 | D24: Chỉ quyền Xem — gọi thẳng chức năng Sửa, bỏ qua giao diện | E24: P0 | F24: Tài khoản B (chỉ quyền xem); tồn tại dịch vụ X đang Hoạt động | G24: 1. Dùng công cụ kiểm thử API gọi thẳng chức năng Sửa dịch vụ X 2. Mở lại dịch vụ X trên màn hình để đối chiếu | H24: Tài khoản B, dịch vụ X | I24: - Hệ thống từ chối, báo không có quyền - Dịch vụ X giữ nguyên mọi thông tin, cột “Cập nhật” không đổi | J24: - Hệ thống từ chối, báo không có quyền - Dịch vụ X giữ nguyên mọi thông tin, cột “Cập nhật” không đổi | K24: Passed
C25: TC-ROLE-06 | D25: Chỉ quyền Xem — gọi thẳng chức năng Xóa / Khóa / Mở khóa | E25: P0 | F25: Tài khoản B (chỉ quyền xem); dịch vụ X đang Hoạt động | G25: 1. Dùng công cụ kiểm thử API gọi lần lượt 3 chức năng: Xóa, Khóa, Mở khóa cho dịch vụ X | H25: 3 lần gọi, cùng tài khoản B | I25: - CẢ 3 lần đều bị hệ thống từ chối, báo không có quyền - Dịch vụ X vẫn còn và vẫn ở trạng thái Hoạt động | J25: - CẢ 3 lần đều bị hệ thống từ chối, báo không có quyền - Dịch vụ X vẫn còn và vẫn ở trạng thái Hoạt động | K25: Passed
C26: TC-ROLE-07 | D26: Không có quyền nào — gọi thẳng chức năng xem danh sách và xem chi tiết | E26: P0 | F26: Tài khoản A (không có quyền nào của màn), đã đăng nhập hợp lệ | G26: 1. Dùng công cụ kiểm thử API gọi chức năng lấy danh sách 2. Gọi chức năng xem chi tiết một dịch vụ | H26: Tài khoản A | I26: - Cả 2 lần đều bị từ chối, báo không có quyền - Kết quả trả về KHÔNG để lộ bất kỳ thông tin nào của danh mục | J26: - Cả 2 lần đều bị từ chối, báo không có quyền - Kết quả trả về KHÔNG để lộ bất kỳ thông tin nào của danh mục | K26: Passed
C27: TC-ROLE-08 | D27: ĐM giảm giá hiển thị theo công ty đang chọn của người đăng nhập | E27: P0 | F27: Dịch vụ “Dịch vụ đánh bóng xy lanh” đã khai báo ĐM giảm giá: công ty 1 là 5%, công ty 4 là 12%. Tài khoản C thuộc công ty 1, tài khoản D thuộc công ty 4, cả hai đều có quyền quản lý | G27: 1. Đăng nhập C, xem cột “ĐM giảm giá” của dòng đó 2. Đăng nhập D, xem lại đúng dòng đó | H27: C ở công ty 1; D ở công ty 4 | I27: - Tài khoản C thấy “5%” - Tài khoản D thấy “12%” - Cùng một dịch vụ nhưng 2 người thấy 2 giá trị khác nhau — đây là hành vi đúng, không phải lỗi | J27: - Tài khoản C thấy “5%” - Tài khoản D thấy “12%” - Cùng một dịch vụ nhưng 2 người thấy 2 giá trị khác nhau — đây là hành vi đúng, không phải lỗi | K27: Passed
C28: TC-ROLE-09 | D28: Công ty chưa khai báo ĐM giảm giá — hiển thị gạch ngang | E28: P1 | F28: Dịch vụ “Hướng dẫn, bàn giao máy hàn rút tồn” chưa được khai báo ĐM giảm giá cho công ty của người đăng nhập | G28: 1. Đăng nhập, xem cột “ĐM giảm giá” của dòng đó | H28: Chưa khai báo định mức | I28: - Cột “ĐM giảm giá” hiển thị “—” - KHÔNG hiển thị 0% và không để trống | J28: - Cột “ĐM giảm giá” hiển thị “—” - KHÔNG hiển thị 0% và không để trống | K28: Passed
C29: I. HIỂN THỊ TRANG & TRUY CẬP
A30: DV sửa chữa & CP khác | B30: HIỂN THỊ TRANG & TRUY CẬP | C30: TC_01.001 | D30: Truy cập màn hình từ menu | E30: P0 | F30: Tài khoản C có quyền quản lý danh mục | G30: 1. Vào phân hệ CSKH 2. Bấm nhóm menu “Danh mục- Dịch vụ” 3. Bấm “Danh mục dịch vụ sửa chữa và chi phí khác” | H30: Tài khoản C | I30: - Mở đúng màn hình danh mục - Tiêu đề trên thanh trên cùng ghi “Danh mục dịch vụ sửa chữa và chi phí khác” | J30: - Mở đúng màn hình danh mục - Tiêu đề trên thanh trên cùng ghi “Danh mục dịch vụ sửa chữa và chi phí khác” | K30: Passed
C31: TC_01.002 | D31: Bố cục trang khi vào lần đầu | E31: P0 | F31: Tài khoản C vào màn hình lần đầu trong ngày (chưa từng đặt bộ lọc) | G31: 1. Vào màn hình 2. Quan sát bố cục | H31: — | I31: - Trang có 2 khối: panel “Bộ lọc dịch vụ sửa chữa và chi phí khác” ở trên và bảng danh sách ở dưới - Bộ lọc nâng cao đang THU GỌN, chỉ hiện ô tìm nhanh cùng 2 nút “Tìm kiếm” và “Làm mới” - KHÔNG có khối thống kê ở đầu trang | J31: - Trang có 2 khối: panel “Bộ lọc dịch vụ sửa chữa và chi phí khác” ở trên và bảng danh sách ở dưới - Bộ lọc nâng cao đang THU GỌN, chỉ hiện ô tìm nhanh cùng 2 nút “Tìm kiếm” và “Làm mới” - KHÔNG có khối thống kê ở đầu trang | K31: Passed
C32: TC_01.003 | D32: Hiển thị đủ và đúng thứ tự các cột | E32: P0 | F32: Danh sách có ít nhất 1 dịch vụ | G32: 1. Vào danh sách 2. Đọc tiêu đề từng cột từ trái sang phải | H32: — | I32: - Đúng 9 cột theo thứ tự: STT | Tên dịch vụ / chi phí | Phân loại | ĐM giảm giá | % Tính giá vốn | % VAT | Trạng thái | Cập nhật | Hành động - Cột STT và cột Tên đứng yên (dính bên trái) khi cuộn ngang | J32: - Đúng 9 cột theo thứ tự: STT | Tên dịch vụ / chi phí | Phân loại | ĐM giảm giá | % Tính giá vốn | % VAT | Trạng thái | Cập nhật | Hành động - Cột STT và cột Tên đứng yên (dính bên trái) khi cuộn ngang | K32: Passed
C33: TC_01.004 | D33: Biểu tượng sắp xếp chỉ có ở đúng 6 cột | E33: P1 | F33: Đang ở màn danh sách | G33: 1. Quan sát biểu tượng 2 mũi tên trên từng tiêu đề cột | H33: — | I33: - CÓ biểu tượng sắp xếp ở: Tên dịch vụ / chi phí, ĐM giảm giá, % Tính giá vốn, % VAT, Trạng thái, Cập nhật - KHÔNG có ở: STT, Phân loại, Hành động | J33: - CÓ biểu tượng sắp xếp ở: Tên dịch vụ / chi phí, ĐM giảm giá, % Tính giá vốn, % VAT, Trạng thái, Cập nhật - KHÔNG có ở: STT, Phân loại, Hành động | K33: Passed
C34: TC_01.005 | D34: Nhãn Trạng thái Hoạt động / Khóa | E34: P0 | F34: Danh sách có dịch vụ đang Hoạt động và dịch vụ đang Khóa (ví dụ “test01111” đang Khóa) | G34: 1. Quan sát cột Trạng thái của 2 dòng đó | H34: 1 dòng Hoạt động, 1 dòng Khóa | I34: - Dòng Hoạt động: nhãn xanh “Hoạt động” kèm biểu tượng dấu tích - Dòng Khóa: nhãn đỏ “Khóa” kèm biểu tượng ổ khóa | J34: - Dòng Hoạt động: nhãn xanh “Hoạt động” kèm biểu tượng dấu tích - Dòng Khóa: nhãn đỏ “Khóa” kèm biểu tượng ổ khóa | K34: Passed
C35: TC_01.006 | D35: Nhãn Phân loại | E35: P0 | F35: Danh sách có cả dịch vụ có tính doanh thu và khoản chi phí khác | G35: 1. Quan sát cột Phân loại | H35: “Trang test” có tính doanh thu; “test01111” là chi phí khác | I35: - Dịch vụ có tính doanh thu: nhãn xanh “Có tính doanh thu” kèm biểu tượng biểu đồ - Chi phí khác: nhãn đỏ “Chi phí khác” kèm biểu tượng nhãn giá | J35: - Dịch vụ có tính doanh thu: nhãn xanh “Có tính doanh thu” kèm biểu tượng biểu đồ - Chi phí khác: nhãn đỏ “Chi phí khác” kèm biểu tượng nhãn giá | K35: Passed
C36: TC_01.007 | D36: Cột Cập nhật hiển thị thời điểm và người sửa | E36: P1 | F36: Dịch vụ X được nhân viên “10410008- Cao Đình Hòe” sửa lần cuối lúc 16/07/2026 15:12 | G36: 1. Quan sát cột Cập nhật của dòng X | H36: Sửa lần cuối 16/07/2026 15:12 bởi Cao Đình Hòe | I36: - Dòng trên: “16/07/2026 15:12” - Dòng dưới: “bởi 10410008- Cao Đình Hòe” (tên in đậm) | J36: - Dòng trên: “16/07/2026 15:12” - Dòng dưới: “bởi 10410008- Cao Đình Hòe” (tên in đậm) | K36: Passed
C37: TC_01.008 | D37: Dịch vụ chưa từng sửa — cột Cập nhật lấy người tạo | E37: P1 | F37: Dịch vụ Y do “DNS01- DNS Admin” tạo và CHƯA từng được sửa lần nào | G37: 1. Quan sát cột Cập nhật của dòng Y | H37: Chưa từng sửa | I37: - Vẫn hiển thị “bởi DNS01- DNS Admin” (lấy theo người tạo), không được để trống | J37: - Vẫn hiển thị “bởi DNS01- DNS Admin” (lấy theo người tạo), không được để trống | K37: Passed
C38: TC_01.009 | D38: Định dạng phần trăm — tự bỏ số 0 thừa | E38: P1 | F38: Dịch vụ có % Tính giá vốn là 80,00 và % VAT là 8,00 | G38: 1. Quan sát cột “% Tính giá vốn” và “% VAT” | H38: 80,00 và 8,00 | I38: - Hiển thị “80%” và “8%”, KHÔNG hiển thị “80,00%” | J38: - Hiển thị “80%” và “8%”, KHÔNG hiển thị “80,00%” | K38: Passed
C39: TC_01.010 | D39: Giá trị trống hiển thị gạch ngang | E39: P1 | F39: Dịch vụ chưa khai báo ĐM giảm giá | G39: 1. Quan sát cột “ĐM giảm giá” | H39: Chưa khai báo | I39: - Hiển thị “—”, không hiển thị 0% và không để trống | J39: - Hiển thị “—”, không hiển thị 0% và không để trống | K39: Passed
C40: TC_01.011 | D40: Danh sách rỗng khi bộ lọc không khớp | E40: P1 | F40: Danh sách đang có dữ liệu | G40: 1. Nhập “ZZZZZ999” vào ô tìm nhanh 2. Bấm “Tìm kiếm” | H40: Từ khóa: ZZZZZ999 | I40: - Bảng hiển thị dòng chữ “Không có dữ liệu phù hợp bộ lọc.” - Không báo lỗi, không treo trang | J40: - Bảng hiển thị dòng chữ “Không có dữ liệu phù hợp bộ lọc.” - Không báo lỗi, không treo trang | K40: Passed
C41: TC_01.012 | D41: Ghi nhớ bộ lọc trong 10 phút | E41: P2 | F41: Đã lọc Trạng thái = “Khóa”, sau đó chuyển sang màn khác | G41: 1. Quay lại màn danh mục trong vòng 10 phút 2. Mở bộ lọc nâng cao | H41: Quay lại sau 2 phút | I41: - Ô “Trạng thái” vẫn đang chọn “Khóa”, danh sách vẫn lọc theo điều kiện cũ - Danh sách chỉ nạp đúng 1 lần, không bị nháy nạp lại 2 lần | J41: - Ô “Trạng thái” vẫn đang chọn “Khóa”, danh sách vẫn lọc theo điều kiện cũ - Danh sách chỉ nạp đúng 1 lần, không bị nháy nạp lại 2 lần | K41: Passed
C42: TC_01.013 | D42: Bộ lọc hết hạn sau 10 phút | E42: P2 | F42: Đã lọc Trạng thái = “Khóa”, rời màn quá 10 phút | G42: 1. Quay lại màn danh mục sau 10 phút | H42: Quay lại sau 15 phút | I42: - Bộ lọc trở về trắng, danh sách hiển thị lại toàn bộ 526 dòng | J42: - Bộ lọc trở về trắng, danh sách hiển thị lại toàn bộ 526 dòng | K42: Passed
C43: II. BỘ LỌC & TÌM KIẾM
A44: DV sửa chữa & CP khác | B44: BỘ LỌC & TÌM KIẾM | C44: TC_02.001 | D44: Tìm nhanh theo tên dịch vụ | E44: P0 | F44: Tồn tại dịch vụ tên “Dịch vụ đánh bóng xy lanh” | G44: 1. Nhập “đánh bóng” vào ô tìm nhanh 2. Bấm nút “Tìm kiếm” | H44: Từ khóa: đánh bóng | I44: - Danh sách chỉ còn các dịch vụ có tên chứa “đánh bóng” - Danh sách nhảy về trang 1 | J44: - Danh sách chỉ còn các dịch vụ có tên chứa “đánh bóng” - Danh sách nhảy về trang 1 | K44: Passed
C45: TC_02.002 | D45: Ô tìm nhanh KHÔNG tự lọc khi đang gõ | E45: P0 | F45: Đang ở màn danh sách 526 dòng | G45: 1. Gõ “đánh bóng” vào ô tìm nhanh 2. KHÔNG bấm gì thêm, chờ 5 giây 3. Quan sát bảng | H45: Đã gõ nhưng chưa bấm Tìm kiếm | I45: - Bảng GIỮ NGUYÊN 526 dòng, chưa lọc gì - Phải bấm “Tìm kiếm” (hoặc nhấn Enter) thì danh sách mới lọc lại | J45: - Bảng GIỮ NGUYÊN 526 dòng, chưa lọc gì - Phải bấm “Tìm kiếm” (hoặc nhấn Enter) thì danh sách mới lọc lại | K45: Passed
C46: TC_02.003 | D46: Mở và đóng bộ lọc nâng cao | E46: P1 | F46: Bộ lọc đang thu gọn | G46: 1. Bấm “Tìm kiếm nâng cao” 2. Bấm lại nút đó (chữ đã đổi) | H46: — | I46: - Lần 1: hiện 4 ô lọc (Tên dịch vụ / chi phí, Phân loại, Trạng thái, Người cập nhật), nút đổi chữ thành “Ẩn tìm kiếm nâng cao” - Lần 2: 4 ô ẩn đi, nút đổi lại thành “Tìm kiếm nâng cao” | J46: - Lần 1: hiện 4 ô lọc (Tên dịch vụ / chi phí, Phân loại, Trạng thái, Người cập nhật), nút đổi chữ thành “Ẩn tìm kiếm nâng cao” - Lần 2: 4 ô ẩn đi, nút đổi lại thành “Tìm kiếm nâng cao” | K46: Passed
C47: TC_02.004 | D47: Lọc theo ô Tên dịch vụ / chi phí | E47: P0 | F47: Tồn tại dịch vụ có tên chứa “Thiết kế” | G47: 1. Mở bộ lọc nâng cao 2. Nhập “Thiết kế” vào ô Tên dịch vụ / chi phí 3. Bấm “Tìm kiếm” | H47: Tên: Thiết kế | I47: - Danh sách chỉ còn dịch vụ có tên chứa “Thiết kế” | J47: - Danh sách chỉ còn dịch vụ có tên chứa “Thiết kế” | K47: Passed
C48: TC_02.005 | D48: Lọc Phân loại = Dịch vụ có tính doanh thu | E48: P0 | F48: Danh sách có cả 2 phân loại | G48: 1. Mở bộ lọc nâng cao 2. Chọn Phân loại = “Dịch vụ có tính doanh thu” | H48: Phân loại: Có tính doanh thu | I48: - Danh sách CHỈ còn dòng có nhãn “Có tính doanh thu” - Không còn dòng nào có nhãn “Chi phí khác” | J48: - Danh sách CHỈ còn dòng có nhãn “Có tính doanh thu” - Không còn dòng nào có nhãn “Chi phí khác” | K48: Passed
C49: TC_02.006 | D49: Lọc Phân loại = Chi phí khác | E49: P0 | F49: Danh sách có dịch vụ thuộc nhóm Chi phí khác (ví dụ “test01111”) | G49: 1. Chọn Phân loại = “Chi phí khác” 2. Quan sát kết quả | H49: Phân loại: Chi phí khác | I49: - Danh sách CHỈ còn dòng có nhãn “Chi phí khác” - Điểm dễ lỗi: tuyệt đối KHÔNG được trả về toàn bộ danh sách như khi chưa chọn bộ lọc | J49: - Danh sách CHỈ còn dòng có nhãn “Chi phí khác” - Điểm dễ lỗi: tuyệt đối KHÔNG được trả về toàn bộ danh sách như khi chưa chọn bộ lọc | K49: Passed
C50: TC_02.007 | D50: Lọc Trạng thái = Khóa | E50: P0 | F50: Danh sách có dịch vụ đang Khóa (ví dụ “test01111”) | G50: 1. Chọn Trạng thái = “Khóa” | H50: Trạng thái: Khóa | I50: - Danh sách CHỈ còn dòng có nhãn “Khóa” - Điểm dễ lỗi: không được coi lựa chọn này là “chưa chọn gì” rồi trả về cả danh sách | J50: - Danh sách CHỈ còn dòng có nhãn “Khóa” - Điểm dễ lỗi: không được coi lựa chọn này là “chưa chọn gì” rồi trả về cả danh sách | K50: Passed
C51: TC_02.008 | D51: Lọc Trạng thái = Hoạt động | E51: P0 | F51: Danh sách có cả dòng Hoạt động và dòng Khóa | G51: 1. Chọn Trạng thái = “Hoạt động” | H51: Trạng thái: Hoạt động | I51: - Danh sách CHỈ còn dòng có nhãn “Hoạt động” | J51: - Danh sách CHỈ còn dòng có nhãn “Hoạt động” | K51: Passed
C52: TC_02.009 | D52: Lọc theo Người cập nhật | E52: P1 | F52: Nhân viên “10410008- Cao Đình Hòe” đã sửa một số dịch vụ | G52: 1. Chọn Người cập nhật = “10410008- Cao Đình Hòe” | H52: Người cập nhật: Cao Đình Hòe | I52: - Danh sách chỉ còn các dịch vụ do nhân viên đó sửa lần cuối | J52: - Danh sách chỉ còn các dịch vụ do nhân viên đó sửa lần cuối | K52: Passed
C53: TC_02.010 | D53: Lọc Người cập nhật bắt cả dịch vụ chưa từng sửa | E53: P1 | F53: Nhân viên “DNS01- DNS Admin” TẠO dịch vụ Z và Z chưa từng được sửa lần nào | G53: 1. Chọn Người cập nhật = “DNS01- DNS Admin” 2. Tìm dịch vụ Z trong kết quả | H53: Dịch vụ Z chưa từng sửa | I53: - Dịch vụ Z VẪN xuất hiện trong kết quả: dịch vụ chưa từng sửa thì tính theo người tạo | J53: - Dịch vụ Z VẪN xuất hiện trong kết quả: dịch vụ chưa từng sửa thì tính theo người tạo | K53: Passed
C54: TC_02.011 | D54: Kết hợp nhiều điều kiện lọc | E54: P0 | F54: Dữ liệu đa dạng về trạng thái, phân loại và tên | G54: 1. Chọn Trạng thái = Hoạt động 2. Chọn Phân loại = Có tính doanh thu 3. Nhập “Thiết kế” vào ô Tên dịch vụ / chi phí 4. Bấm “Tìm kiếm” | H54: 3 điều kiện cùng lúc | I54: - Kết quả thỏa ĐỒNG THỜI cả 3 điều kiện, không phải thỏa 1 trong 3 | J54: - Kết quả thỏa ĐỒNG THỜI cả 3 điều kiện, không phải thỏa 1 trong 3 | K54: Passed
C55: TC_02.012 | D55: Đổi ô lọc nâng cao là danh sách tự lọc lại | E55: P1 | F55: Đang ở trang 3 của danh sách | G55: 1. Mở bộ lọc nâng cao, chọn Trạng thái = “Khóa” 2. KHÔNG bấm “Tìm kiếm” | H55: Trạng thái: Khóa | I55: - Danh sách tự lọc lại ngay khi chọn, không cần bấm “Tìm kiếm” - Danh sách nhảy về trang 1 | J55: - Danh sách tự lọc lại ngay khi chọn, không cần bấm “Tìm kiếm” - Danh sách nhảy về trang 1 | K55: Passed
C56: TC_02.013 | D56: Nút “Làm mới” xóa lọc và nạp lại danh sách | E56: P0 | F56: Đang lọc Trạng thái = Khóa kèm từ khóa “test”, danh sách chỉ còn vài dòng | G56: 1. Bấm nút “Làm mới” 2. Quan sát các ô lọc và bảng | H56: — | I56: - Ô tìm nhanh và cả 4 ô lọc nâng cao đều trở về trắng - Bảng NẠP LẠI đủ 526 dòng và về trang 1 - Không được chỉ xóa ô lọc mà vẫn giữ nguyên kết quả cũ trên bảng | J56: - Ô tìm nhanh và cả 4 ô lọc nâng cao đều trở về trắng - Bảng NẠP LẠI đủ 526 dòng và về trang 1 - Không được chỉ xóa ô lọc mà vẫn giữ nguyên kết quả cũ trên bảng | K56: Passed
... C59: TC_02.016 | D59: Tìm với toàn khoảng trắng | E59: P2 | F59: Danh sách có dữ liệu | G59: 1. Nhập vài dấu cách vào ô tìm nhanh 2. Bấm “Tìm kiếm” | H59: Từ khóa: chỉ có dấu cách | I59: - Danh sách trả về bình thường như khi không lọc, không báo lỗi | J59: - Danh sách trả về bình thường như khi không lọc, không báo lỗi | K59: Passed
C60: III. DANH SÁCH, SẮP XẾP & PHÂN TRANG
A61: DV sửa chữa & CP khác | B61: DANH SÁCH, SẮP XẾP & PHÂN TRANG | C61: TC_03.001 | D61: Thứ tự mặc định khi vào màn | E61: P0 | F61: Danh sách 526 dòng, có dịch vụ vừa được tạo hôm nay | G61: 1. Vào màn hình lần đầu 2. Quan sát thứ tự các dòng | H61: Chưa bấm sắp xếp cột nào | I61: - Sắp xếp theo ngày tạo giảm dần: dịch vụ mới tạo nhất nằm ở đầu danh sách | J61: - Sắp xếp theo ngày tạo giảm dần: dịch vụ mới tạo nhất nằm ở đầu danh sách | K61: Passed
C62: TC_03.002 | D62: Sắp xếp theo Tên dịch vụ / chi phí | E62: P0 | F62: Danh sách có từ 20 dòng trở lên | G62: 1. Bấm tiêu đề cột “Tên dịch vụ / chi phí” 2. Bấm lần nữa | H62: Sắp xếp theo cột Tên | I62: - Lần 1: sắp tăng dần A → Z - Lần 2: sắp giảm dần Z → A - Biểu tượng mũi tên trên tiêu đề đổi chiều tương ứng | J62: - Lần 1: sắp tăng dần A → Z - Lần 2: sắp giảm dần Z → A - Biểu tượng mũi tên trên tiêu đề đổi chiều tương ứng | K62: Passed
C63: TC_03.003 | D63: Sắp xếp theo ĐM giảm giá | E63: P0 | F63: Có dịch vụ ĐM giảm giá 5%, 32%, 95% và có dịch vụ chưa khai báo | G63: 1. Bấm tiêu đề cột “ĐM giảm giá” 2. Bấm lần nữa | H63: Sắp xếp theo cột ĐM giảm giá | I63: - Sắp đúng theo giá trị số của công ty đang chọn: 5 → 32 → 95 - Các dòng chưa khai báo gom về một đầu danh sách, không gây lỗi | J63: - Sắp đúng theo giá trị số của công ty đang chọn: 5 → 32 → 95 - Các dòng chưa khai báo gom về một đầu danh sách, không gây lỗi | K63: Passed
C64: TC_03.004 | D64: Sắp xếp theo % Tính giá vốn | E64: P1 | F64: Có dịch vụ 0%, 1%, 60%, 80% và 321% | G64: 1. Bấm tiêu đề cột “% Tính giá vốn” để sắp tăng dần | H64: Sắp xếp theo cột % Tính giá vốn | I64: - Thứ tự đúng: 0 → 1 → 60 → 80 → 321 - Điểm dễ lỗi: 321 phải đứng SAU 80 (so sánh theo số, không phải theo chữ) | J64: - Thứ tự đúng: 0 → 1 → 60 → 80 → 321 - Điểm dễ lỗi: 321 phải đứng SAU 80 (so sánh theo số, không phải theo chữ) | K64: Passed
C65: TC_03.005 | D65: Sắp xếp theo % VAT | E65: P1 | F65: Có dịch vụ VAT 0%, 8%, 21% và 100% | G65: 1. Bấm tiêu đề cột “% VAT” | H65: Sắp xếp theo cột % VAT | I65: - Thứ tự tăng dần đúng theo giá trị số | J65: - Thứ tự tăng dần đúng theo giá trị số | K65: Passed
C66: TC_03.006 | D66: Sắp xếp theo Trạng thái | E66: P1 | F66: Có cả dòng Hoạt động và dòng Khóa | G66: 1. Bấm tiêu đề cột “Trạng thái” | H66: Sắp xếp theo cột Trạng thái | I66: - Các dòng cùng trạng thái được gom lại với nhau, không báo lỗi | J66: - Các dòng cùng trạng thái được gom lại với nhau, không báo lỗi | K66: Passed
C67: TC_03.007 | D67: Sắp xếp theo Cập nhật | E67: P1 | F67: Có dòng vừa sửa gần đây và dòng sửa đã lâu | G67: 1. Bấm tiêu đề cột “Cập nhật” 2 lần | H67: Sắp xếp theo cột Cập nhật | I67: - Sắp đúng theo thời điểm cập nhật ở cả 2 chiều | J67: - Sắp đúng theo thời điểm cập nhật ở cả 2 chiều | K67: Passed
C68: TC_03.008 | D68: Thứ tự sắp xếp giữ nguyên khi chuyển trang | E68: P1 | F68: Đang sắp xếp theo Tên tăng dần | G68: 1. Bấm sang trang 2 2. Quan sát thứ tự và biểu tượng trên tiêu đề cột | H68: Đang sắp theo Tên, sang trang 2 | I68: - Trang 2 tiếp nối đúng thứ tự A → Z của trang 1 - Biểu tượng sắp xếp trên cột Tên vẫn giữ nguyên | J68: - Trang 2 tiếp nối đúng thứ tự A → Z của trang 1 - Biểu tượng sắp xếp trên cột Tên vẫn giữ nguyên | K68: Passed
C69: TC_03.009 | D69: Bấm sắp xếp thì quay về trang 1 | E69: P2 | F69: Đang ở trang 3 | G69: 1. Bấm tiêu đề cột “Tên dịch vụ / chi phí” | H69: Đang ở trang 3 | I69: - Danh sách nhảy về trang 1 với thứ tự mới | J69: - Danh sách nhảy về trang 1 với thứ tự mới | K69: Passed
C70: TC_03.010 | D70: Phân trang mặc định 10 dòng | E70: P0 | F70: Danh sách có 526 dòng | G70: 1. Vào màn hình 2. Đọc dòng đếm ở chân bảng | H70: 526 dòng | I70: - Bảng hiện đúng 10 dòng - Chân bảng ghi “Hiển thị 1–10 / 526 dịch vụ / chi phí” - Có 53 trang | J70: - Bảng hiện đúng 10 dòng - Chân bảng ghi “Hiển thị 1–10 / 526 dịch vụ / chi phí” - Có 53 trang | K70: Passed
C71: TC_03.011 | D71: Chuyển trang | E71: P0 | F71: Danh sách 526 dòng, 10 dòng mỗi trang | G71: 1. Bấm sang trang 2 2. Bấm sang trang 3 3. Bấm nút về trang cuối | H71: Trang 2, 3 và trang cuối | I71: - Mỗi trang hiện đúng 10 dòng với dữ liệu KHÁC nhau, dòng đếm đổi thành 11–20 rồi 21–30 - Trang cuối hiển thị 6 dòng - Bộ lọc đang áp dụng KHÔNG bị xóa khi chuyển trang | J71: - Mỗi trang hiện đúng 10 dòng với dữ liệu KHÁC nhau, dòng đếm đổi thành 11–20 rồi 21–30 - Trang cuối hiển thị 6 dòng - Bộ lọc đang áp dụng KHÔNG bị xóa khi chuyển trang | K71: Passed
C72: TC_03.012 | D72: Đổi số dòng mỗi trang | E72: P0 | F72: Danh sách 526 dòng | G72: 1. Chọn “Số dòng/trang” = 50 2. Quan sát bảng và số trang | H72: 50 dòng mỗi trang | I72: - Bảng hiện 50 dòng, chân bảng ghi “Hiển thị 1–50 / 526”, tổng số trang còn 11 - Danh sách nhảy về trang 1 | J72: - Bảng hiện 50 dòng, chân bảng ghi “Hiển thị 1–50 / 526”, tổng số trang còn 11 - Danh sách nhảy về trang 1 | K72: Passed
C73: TC_03.013 | D73: Danh sách lựa chọn số dòng mỗi trang | E73: P2 | F73: Đang ở màn danh sách | G73: 1. Mở ô chọn “Số dòng/trang” | H73: — | I73: - Có đúng 4 lựa chọn: 5, 10, 20, 50; đang chọn sẵn 10 | J73: - Có đúng 4 lựa chọn: 5, 10, 20, 50; đang chọn sẵn 10 | K73: Passed
... C76: TC_03.016 | D76: Đổi số dòng mỗi trang | E76: P0 | F76: Danh sách 526 dòng | G76: 1. Chọn “Số dòng/trang” = 100 2. Quan sát bảng và số trang | H76: 100 dòng mỗi trang | I76: - Bảng hiện 100 dòng, chân bảng ghi “Hiển thị 1–100 / 526”, tổng số trang còn 11 - Danh sách nhảy về trang 1 | J76: - Bảng hiện 100 dòng, chân bảng ghi “Hiển thị 1–100 / 526”, tổng số trang còn 11 - Danh sách nhảy về trang 1 | K76: Passed
C77: IV. TẠO MỚI / SỬA / XEM
A78: DV sửa chữa & CP khác | B78: TẠO MỚI / SỬA / XEM | C78: TC_04.001 | D78: Mở cửa sổ Tạo mới | E78: P0 | F78: Tài khoản C có quyền quản lý | G78: 1. Bấm nút “Tạo mới” 2. Quan sát cửa sổ mở ra | H78: — | I78: - Cửa sổ tiêu đề “Thêm dịch vụ / chi phí” mở ra ngay trên trang - Có 4 ô nhập: Tên dịch vụ / chi phí (bắt buộc), % Tính giá vốn (bắt buộc), % VAT (bắt buộc), ĐM giảm giá (%) - Có ô tích “Dịch vụ có tính doanh thu” ĐANG ĐƯỢC TÍCH SẴN - KHÔNG có ô “Trạng thái” - Chân cửa sổ có 3 nút: “Lưu”, “Lưu & Tiếp tục”, “Đóng” | J78: - Cửa sổ tiêu đề “Thêm dịch vụ / chi phí” mở ra ngay trên trang - Có 4 ô nhập: Tên dịch vụ / chi phí (bắt buộc), % Tính giá vốn (bắt buộc), % VAT (bắt buộc), ĐM giảm giá (%) - Có ô tích “Dịch vụ có tính doanh thu” ĐANG ĐƯỢC TÍCH SẴN - KHÔNG có ô “Trạng thái” - Chân cửa sổ có 3 nút: “Lưu”, “Lưu & Tiếp tục”, “Đóng” | K78: Passed
C79: TC_04.002 | D79: Giá trị điền sẵn khi mở cửa sổ Tạo mới | E79: P0 | F79: Vừa bấm “Tạo mới” | G79: 1. Quan sát giá trị từng ô | H79: — | I79: - Tên, % Tính giá vốn, % VAT và ĐM giảm giá đều TRỐNG (chỉ có chữ gợi ý mờ) - Ô “Dịch vụ có tính doanh thu” ĐÃ ĐƯỢC TÍCH - Chưa có ô nào báo lỗi đỏ | J79: - Tên, % Tính giá vốn, % VAT và ĐM giảm giá đều TRỐNG (chỉ có chữ gợi ý mờ) - Ô “Dịch vụ có tính doanh thu” ĐÃ ĐƯỢC TÍCH - Chưa có ô nào báo lỗi đỏ | K79: Passed
C80: TC_04.003 | D80: Tạo mới dịch vụ hợp lệ đầy đủ | E80: P0 | F80: Tài khoản C có quyền quản lý; chưa tồn tại dịch vụ tên “TC Dịch vụ kiểm thử 01” | G80: 1. Bấm “Tạo mới” 2. Nhập Tên = “TC Dịch vụ kiểm thử 01” 3. % Tính giá vốn = 70 4. % VAT = 8 5. ĐM giảm giá = 5 6. Giữ tích “Dịch vụ có tính doanh thu” 7. Bấm “Lưu” | H80: Tên: TC Dịch vụ kiểm thử 01; giá vốn 70; VAT 8; giảm giá 5 | I80: - Thông báo xanh “Thêm mới thành công” - Cửa sổ đóng lại, danh sách nạp lại, dịch vụ mới nằm ĐẦU danh sách - Dòng mới: Phân loại “Có tính doanh thu”, ĐM giảm giá 5%, % Tính giá vốn 70%, % VAT 8%, Trạng thái “Hoạt động”, cột Cập nhật ghi hôm nay bởi chính tài khoản C | J80: - Thông báo xanh “Thêm mới thành công” - Cửa sổ đóng lại, danh sách nạp lại, dịch vụ mới nằm ĐẦU danh sách - Dòng mới: Phân loại “Có tính doanh thu”, ĐM giảm giá 5%, % Tính giá vốn 70%, % VAT 8%, Trạng thái “Hoạt động”, cột Cập nhật ghi hôm nay bởi chính tài khoản C | K80: Passed
C81: TC_04.004 | D81: Tạo mới bỏ trống ĐM giảm giá | E81: P0 | F81: Chưa tồn tại dịch vụ tên “TC Dịch vụ kiểm thử 02” | G81: 1. Tạo mới, nhập Tên, % Tính giá vốn = 50, % VAT = 10 2. ĐỂ TRỐNG ô ĐM giảm giá 3. Bấm “Lưu” | H81: ĐM giảm giá: để trống | I81: - Lưu thành công, KHÔNG báo lỗi ở ô ĐM giảm giá - Cột “ĐM giảm giá” của dòng mới hiển thị “—” | J81: - Lưu thành công, KHÔNG báo lỗi ở ô ĐM giảm giá - Cột “ĐM giảm giá” của dòng mới hiển thị “—” | K81: Passed
C82: TC_04.005 | D82: Tạo mới bỏ tích “Dịch vụ có tính doanh thu” | E82: P0 | F82: Chưa tồn tại dịch vụ tên “TC Chi phí khác 01” | G82: 1. Tạo mới, nhập Tên = “TC Chi phí khác 01”, % Tính giá vốn = 0, % VAT = 0 2. BỎ TÍCH ô “Dịch vụ có tính doanh thu” 3. Bấm “Lưu” | H82: Bỏ tích ô có tính doanh thu | I82: - Lưu thành công - Dòng mới hiển thị nhãn đỏ “Chi phí khác” ở cột Phân loại | J82: - Lưu thành công - Dòng mới hiển thị nhãn đỏ “Chi phí khác” ở cột Phân loại | K82: Passed
C83: TC_04.006 | D83: Trạng thái sau khi tạo luôn là Hoạt động | E83: P0 | F83: Vừa tạo mới một dịch vụ | G83: 1. Xem cột Trạng thái của dòng vừa tạo | H83: — | I83: - Trạng thái là “Hoạt động”; người dùng không chọn được trạng thái lúc tạo mới | J83: - Trạng thái là “Hoạt động”; người dùng không chọn được trạng thái lúc tạo mới | K83: Passed
C84: TC_04.007 | D84: Nút “Lưu & Tiếp tục” giữ cửa sổ mở | E84: P0 | F84: Đang mở cửa sổ Tạo mới | G84: 1. Nhập đủ thông tin hợp lệ cho dịch vụ “TC Liên tục 01” 2. Bấm “Lưu & Tiếp tục” 3. Quan sát cửa sổ | H84: — | I84: - Thông báo “Thêm mới thành công” - Cửa sổ VẪN MỞ, tiêu đề vẫn là “Thêm dịch vụ / chi phí” - Mọi ô đã được xóa trắng, ô tích trở về trạng thái tích sẵn, nhập tiếp được ngay | J84: - Thông báo “Thêm mới thành công” - Cửa sổ VẪN MỞ, tiêu đề vẫn là “Thêm dịch vụ / chi phí” - Mọi ô đã được xóa trắng, ô tích trở về trạng thái tích sẵn, nhập tiếp được ngay | K84: Passed
C85: TC_04.008 | D85: Bấm Lưu 2 lần liên tiếp không tạo 2 dịch vụ | E85: P0 | F85: Đang mở cửa sổ Tạo mới với dữ liệu hợp lệ | G85: 1. Bấm “Lưu” rồi bấm ngay lần thứ 2 thật nhanh 2. Đếm số dòng trùng tên trong danh sách | H85: Bấm nhanh 2 lần | I85: - Chỉ tạo ĐÚNG 1 dịch vụ; lần bấm thứ 2 không có tác dụng | J85: - Chỉ tạo ĐÚNG 1 dịch vụ; lần bấm thứ 2 không có tác dụng | K85: Passed
C86: TC_04.009 | D86: Mở cửa sổ Sửa — dữ liệu nạp đúng | E86: P0 | F86: Tồn tại dịch vụ “Dịch vụ đánh bóng xy lanh”: giá vốn 60%, VAT 8%, ĐM giảm giá 5%, có tính doanh thu, đang Hoạt động | G86: 1. Bấm nút Sửa (biểu tượng bút chì) ở dòng đó 2. Đối chiếu từng ô với dữ liệu trên bảng | H86: Dịch vụ đánh bóng xy lanh | I86: - Cửa sổ tiêu đề “Sửa dịch vụ / chi phí” - Trên tiêu đề có dòng “Cập nhật: 16/07/2026 15:12” và “Bởi: 10410008- Cao Đình Hòe” - Tên, % Tính giá vốn = 60, % VAT = 8, ĐM giảm giá = 5, Trạng thái = “Hoạt động”, ô tích ĐÃ TÍCH | J86: - Cửa sổ tiêu đề “Sửa dịch vụ / chi phí” - Trên tiêu đề có dòng “Cập nhật: 16/07/2026 15:12” và “Bởi: 10410008- Cao Đình Hòe” - Tên, % Tính giá vốn = 60, % VAT = 8, ĐM giảm giá = 5, Trạng thái = “Hoạt động”, ô tích ĐÃ TÍCH | K86: Passed
C87: TC_04.010 | D87: Cửa sổ Sửa CÓ ô Trạng thái | E87: P0 | F87: Đang mở cửa sổ Sửa | G87: 1. Quan sát khu vực bên phải ô ĐM giảm giá và chân cửa sổ | H87: — | I87: - CÓ ô chọn “Trạng thái” với 2 lựa chọn “Hoạt động” và “Khóa” - Chân cửa sổ chỉ có “Lưu” và “Đóng”, KHÔNG có “Lưu & Tiếp tục” | J87: - CÓ ô chọn “Trạng thái” với 2 lựa chọn “Hoạt động” và “Khóa” - Chân cửa sổ chỉ có “Lưu” và “Đóng”, KHÔNG có “Lưu & Tiếp tục” | K87: Passed
C88: TC_04.011 | D88: Sửa và lưu thành công | E88: P0 | F88: Dịch vụ “TC Dịch vụ kiểm thử 01” đang Hoạt động | G88: 1. Bấm Sửa 2. Đổi Tên thành “TC Dịch vụ kiểm thử 01- đã sửa” 3. Đổi % VAT = 10 4. Bấm “Lưu” | H88: Đổi tên và đổi VAT thành 10 | I88: - Thông báo “Cập nhật thành công”, cửa sổ đóng lại - Dòng trên bảng đổi tên và % VAT thành 10% - Cột “Cập nhật” đổi sang thời điểm hiện tại và tên người đang đăng nhập | J88: - Thông báo “Cập nhật thành công”, cửa sổ đóng lại - Dòng trên bảng đổi tên và % VAT thành 10% - Cột “Cập nhật” đổi sang thời điểm hiện tại và tên người đang đăng nhập | K88: Passed
C89: TC_04.012 | D89: Sửa để bỏ trống ĐM giảm giá | E89: P0 | F89: Dịch vụ X đang có ĐM giảm giá 5% cho công ty đang chọn | G89: 1. Bấm Sửa X 2. XÓA TRẮNG ô “ĐM giảm giá” 3. Bấm “Lưu” 4. Xem lại trên bảng | H89: Xóa trắng ĐM giảm giá | I89: - Lưu thành công - Cột “ĐM giảm giá” của X đổi thành “—” - Mức giảm giá của các công ty KHÁC không bị ảnh hưởng | J89: - Lưu thành công - Cột “ĐM giảm giá” của X đổi thành “—” - Mức giảm giá của các công ty KHÁC không bị ảnh hưởng | K89: Passed
C90: TC_04.013 | D90: Sửa nhập ĐM giảm giá = 0 | E90: P1 | F90: Dịch vụ X đang có ĐM giảm giá 5% | G90: 1. Sửa X, nhập ĐM giảm giá = 0 2. Bấm “Lưu” | H90: ĐM giảm giá: 0 | I90: - Lưu thành công - Cột “ĐM giảm giá” hiển thị “—”, KHÔNG hiển thị 0% (nhập 0 được hiểu là không có định mức) | J90: - Lưu thành công - Cột “ĐM giảm giá” hiển thị “—”, KHÔNG hiển thị 0% (nhập 0 được hiểu là không có định mức) | K90: Passed
... C99: TC_04.022 | D99: Dịch vụ hệ thống “Chi phí vận chuyển” bị chặn mọi thao tác | E99: P0 | F99: Tồn tại dòng tên đúng “Chi phí vận chuyển” | G99: 1. Rê chuột lên nút Sửa và nút Xóa của dòng đó 2. Rê chuột lên nút ổ khóa | H99: Dịch vụ hệ thống | I99: - Cả 3 nút Sửa, Xóa và ổ khóa đều MỜ - Chú thích lần lượt: “Chi phí này không được phép sửa”, “Chi phí này không được phép xóa”, “Chi phí này không được phép khóa” | J99: - Cả 3 nút Sửa, Xóa và ổ khóa đều MỜ - Chú thích lần lượt: “Chi phí này không được phép sửa”, “Chi phí này không được phép xóa”, “Chi phí này không được phép khóa” | K99: Passed
C100: V. KHÓA / MỞ KHÓA
A101: DV sửa chữa & CP khác | B101: KHÓA / MỞ KHÓA | C101: TC_05.001 | D101: Vị trí nút Khóa / Mở khóa | E101: P0 | F101: Tài khoản C có quyền quản lý | G101: 1. Quan sát cột “Trạng thái” của từng dòng | H101: — | I101: - Nút ổ khóa không nằm NGAY TRONG cột Trạng thái, bên phải nhãn trạng thái (phỉa nằm ở cột Hành động) - Dòng Hoạt động: biểu tượng ổ khóa đóng; dòng Khóa: biểu tượng ổ khóa mở (khong còn nút ổ khóa) | J101: Thay đổi luồng: Đưa button Khóa về cột Hành động | K101: Failed
C102: TC_05.002 | D102: Khóa một dịch vụ đang Hoạt động | E102: P0 | F102: Dịch vụ “TC Dịch vụ kiểm thử 02” đang Hoạt động | G102: 1. Bấm nút ổ khóa ở dòng đó 2. Quan sát hộp thoại 3. Bấm “Khóa” | H102: Khóa dịch vụ TC Dịch vụ kiểm thử 02 | I102: - Hộp thoại tiêu đề “Xác nhận khóa”, nội dung “Bạn có chắc muốn khóa 'TC Dịch vụ kiểm thử 02'?”, có 2 nút “Hủy” và “Khóa” - Sau khi xác nhận: thông báo “Khóa thành công”, danh sách nạp lại, nhãn đổi thành “Khóa” - Nút Sửa và nút Xóa của dòng đó disable đi | J102: - Hộp thoại tiêu đề “Xác nhận khóa”, nội dung “Bạn có chắc muốn khóa 'TC Dịch vụ kiểm thử 02'?”, có 2 nút “Hủy” và “Khóa” - Sau khi xác nhận: thông báo “Khóa thành công”, danh sách nạp lại, nhãn đổi thành “Khóa” - Nút Sửa và nút Xóa của dòng đó disable đi | K102: Passed
C103: TC_05.003 | D103: Bấm Hủy ở hộp xác nhận khóa | E103: P0 | F103: Dịch vụ X đang Hoạt động | G103: 1. Bấm nút ổ khóa 2. Bấm “Hủy” | H103: — | I103: - Hộp thoại đóng lại, trạng thái của X giữ nguyên “Hoạt động” | J103: - Hộp thoại đóng lại, trạng thái của X giữ nguyên “Hoạt động” | K103: Passed
C104: TC_05.004 | D104: Mở khóa một dịch vụ đang Khóa | E104: P0 | F104: Dịch vụ “TC Dịch vụ kiểm thử 02” đang Khóa | G104: 1. Bấm nút ổ khóa (biểu tượng mở) ở dòng đó 2. Quan sát hộp thoại 3. Bấm “Mở khóa” | H104: Mở khóa dịch vụ đang Khóa | I104: - Hộp thoại tiêu đề “Xác nhận mở khóa”, nút xác nhận ghi “Mở khóa” - Thông báo “Mở khóa thành công”, nhãn đổi lại thành “Hoạt động” - Nút Sửa và nút Xóa của dòng đó sáng trở lại | J104: - Hộp thoại tiêu đề “Xác nhận mở khóa”, nút xác nhận ghi “Mở khóa” - Thông báo “Mở khóa thành công”, nhãn đổi lại thành “Hoạt động” - Nút Sửa và nút Xóa của dòng đó sáng trở lại | K104: Passed
C105: TC_05.005 | D105: Mở khóa giữ nguyên ĐM giảm giá cũ | E105: P0 | F105: Dịch vụ X có ĐM giảm giá 12% rồi bị Khóa | G105: 1. Mở khóa X 2. Xem cột “ĐM giảm giá” | H105: Trước khi khóa: 12% | I105: - Sau khi mở khóa, ĐM giảm giá vẫn là 12% - Thao tác khóa và mở khóa chỉ đổi trạng thái, không làm mất định mức đã khai báo | J105: - Sau khi mở khóa, ĐM giảm giá vẫn là 12% - Thao tác khóa và mở khóa chỉ đổi trạng thái, không làm mất định mức đã khai báo | K105: Passed
C106: TC_05.006 | D106: Khóa rồi mở khóa không làm đổi thông tin khác | E106: P1 | F106: Dịch vụ X: giá vốn 70%, VAT 8%, có tính doanh thu | G106: 1. Khóa X 2. Mở khóa X 3. Đối chiếu lại các cột | H106: — | I106: - % Tính giá vốn, % VAT và Phân loại giữ nguyên - Chỉ cột “Cập nhật” đổi sang người và thời điểm mới nhất | J106: - % Tính giá vốn, % VAT và Phân loại giữ nguyên - Chỉ cột “Cập nhật” đổi sang người và thời điểm mới nhất | K106: Passed
C107: TC_05.007 | D107: Dịch vụ hệ thống không khóa được | E107: P0 | F107: Dòng “Chi phí đi lại” đang Hoạt động | G107: 1. Rê chuột lên nút ổ khóa của dòng đó 2. Dùng công cụ kiểm thử API gọi thẳng chức năng Khóa cho dòng này | H107: Dịch vụ hệ thống | I107: - Nút ổ khóa MỜ, chú thích “Chi phí này không được phép khóa” - Gọi thẳng chức năng Khóa cũng bị từ chối, trạng thái không đổi | J107: - Nút ổ khóa MỜ, chú thích “Chi phí này không được phép khóa” - Gọi thẳng chức năng Khóa cũng bị từ chối, trạng thái không đổi | K107: Passed
C108: TC_05.008 | D108: Khóa một dịch vụ vốn đã Khóa | E108: P1 | F108: Dịch vụ X đang ở trạng thái Khóa | G108: 1. Dùng công cụ kiểm thử API gọi thẳng chức năng Khóa cho X | H108: X đang Khóa sẵn | I108: - Hệ thống báo “Chi phí đang bị khóa” và không thực hiện gì thêm | J108: - Hệ thống báo “Chi phí đang bị khóa” và không thực hiện gì thêm | K108: Passed
C109: TC_05.009 | D109: Mở khóa một dịch vụ vốn đang Hoạt động | E109: P1 | F109: Dịch vụ X đang Hoạt động | G109: 1. Dùng công cụ kiểm thử API gọi thẳng chức năng Mở khóa cho X | H109: X đang Hoạt động sẵn | I109: - Hệ thống báo “Chi phí đang hoạt động” và không thực hiện gì thêm | J109: - Hệ thống báo “Chi phí đang hoạt động” và không thực hiện gì thêm | K109: Passed
C110: TC_05.010 | D110: Người chỉ có quyền Xem không thấy nút ổ khóa | E110: P0 | F110: Tài khoản B chỉ có quyền xem | G110: 1. Đăng nhập B, quan sát cột Trạng thái | H110: Tài khoản B | I110: - Cột Trạng thái CHỈ có nhãn trạng thái, không hiển thị nút ổ khóa | J110: - Cột Trạng thái CHỈ có nhãn trạng thái, không hiển thị nút ổ khóa | K110: Passed
C111: VI. XÓA (XÓA HẲN HOẶC CHUYỂN SANG KHÓA)
A112: DV sửa chữa & CP khác | B112: XÓA (XÓA HẲN HOẶC CHUYỂN SANG KHÓA) | C112: TC_06.001 | D112: Xóa dịch vụ chưa phát sinh chứng từ | E112: P0 | F112: Dịch vụ “TC Dịch vụ kiểm thử 01” đang Hoạt động và CHƯA được dùng ở Báo giá hãng hay Hợp đồng hãng nào | G112: 1. Bấm nút Xóa (biểu tượng thùng rác) ở dòng đó 2. Quan sát hộp thoại 3. Bấm “Xóa” | H112: Dịch vụ chưa dùng ở đâu | I112: - Hộp thoại tiêu đề “Xác nhận xóa”, nội dung “Bạn có chắc muốn xóa 'TC Dịch vụ kiểm thử 01'?”, nút xác nhận ghi “Xóa” - Thông báo “Xóa thành công”, dịch vụ BIẾN MẤT khỏi danh sách - ĐM giảm giá của dịch vụ đó ở MỌI công ty cũng bị xóa theo | J112: - Hộp thoại tiêu đề “Xác nhận xóa”, nội dung “Bạn có chắc muốn xóa 'TC Dịch vụ kiểm thử 01'?”, nút xác nhận ghi “Xóa” - Thông báo “Xóa thành công”, dịch vụ BIẾN MẤT khỏi danh sách - ĐM giảm giá của dịch vụ đó ở MỌI công ty cũng bị xóa theo | K112: Passed
...

Sheet 2. DM tiền tệ
A1: MÔ TẢ TÍNH NĂNG (đọc trước khi xem testcase)
A2: 1. Mục đích tính năng | B2: Quản lý tập trung danh sách các loại tiền tệ và tỷ giá quy đổi ra Đồng Việt Nam, dùng chung cho toàn hệ thống (báo giá, hợp đồng, đề nghị thu tiền, đề nghị chi tiền, công nợ, phiếu kế toán…). Màn hình nằm ở phân hệ Tài chính → nhóm menu Danh mục → Danh mục tiền tệ. Đây là màn được chuyển từ hệ thống cũ sang. Hai cổng dùng CHUNG một danh sách tiền tệ, nên sửa ở cổng mới thì cổng cũ cũng thấy ngay và ngược lại.
A3: 2. Đối tượng được tính / hiển thị | B3: - Toàn bộ tiền tệ trong danh mục, KHÔNG phân theo công ty / phòng ban — ai có quyền vào màn thì thấy đủ như nhau. - Hiển thị cả tiền tệ ở trạng thái Hoạt động và trạng thái Khóa (mặc định không lọc trạng thái). - Mỗi dòng gồm 7 cột: STT, Mã tiền tệ, Tên tiền tệ (kèm dòng phụ "Tên gọi khác" nếu có), Tỷ giá (VNĐ), Cập nhật, Trạng thái, Hành động. - Cột Tên tiền tệ chỉ hiện dòng phụ "Tên gọi khác" khi tiền tệ đó có nhập tên gọi khác; không nhập thì không hiện dòng phụ (không hiện dòng trống).
A4: 3. Đối tượng bị ẩn / không tính | B4: - Không có tiền tệ nào bị ẩn khỏi danh sách: màn này không có khái niệm xóa mềm / lưu trữ. - Tiền tệ ở trạng thái Khóa VẪN hiện trong danh sách của màn này, chỉ bị chặn không cho chọn mới ở các màn nghiệp vụ khác. - Khi lọc theo Trạng thái = Hoạt động thì các tiền tệ đang Khóa bị loại khỏi kết quả và ngược lại.
A5: 4. Bộ lọc thời gian áp dụng cho | B5: Không áp dụng. Màn hình không có bộ lọc theo khoảng thời gian. Cột Cập nhật chỉ để xem và để sắp xếp, không phải điều kiện lọc.
A6: 5. Cấu trúc dữ liệu / cây phân cấp | B6: Danh sách phẳng, không phân cấp cha- con. Mã tiền tệ là giá trị không được trùng trong toàn danh mục. Tỷ giá luôn được hiểu là: 1 đơn vị tiền tệ đó bằng bao nhiêu Đồng Việt Nam.
A7: 6. Quy tắc cộng dồn / deduplicate | B7: Không cộng dồn. Mỗi tiền tệ là một dòng độc lập. Quy tắc chống trùng: Mã tiền tệ là duy nhất. Thêm mới hoặc sửa sang một mã đã có sẽ bị chặn với thông báo "Mã tiền tệ đã tồn tại" ngay dưới ô Mã tiền tệ. Tên tiền tệ và Tên gọi khác KHÔNG bắt buộc duy nhất — được phép trùng.
A8: 7. Phân quyền cấp | B8: Hai quyền dành riêng cho màn này: - "Xem danh mục tiền tệ": vào được màn hình, xem danh sách, mở xem chi tiết, xuất Excel. - "Quản lý danh mục tiền tệ": thêm mới, sửa, khóa, mở khóa, xóa. Người có quyền này cũng vào và xem được màn hình. Không có quyền nào trong hai quyền trên thì không vào được màn hình. Danh mục KHÔNG phân quyền theo công ty / phòng ban / bộ phận.
A9: 8. Cách tính các ô thống kê | B9: - Dòng "Hiển thị a- b / N" dưới bảng: a là số thứ tự dòng đầu của trang đang xem, b là dòng cuối, N là tổng số tiền tệ khớp bộ lọc hiện tại (không phải tổng toàn danh mục). - Cột STT được đánh theo trang: trang 2 với cỡ trang 10 thì bắt đầu từ 11. - Cột Tỷ giá (VNĐ) hiển thị theo định dạng Việt Nam: dấu chấm ngăn cách hàng nghìn, dấu phẩy ngăn phần thập phân, luôn 2 chữ số thập phân. Ví dụ 26.520,00.
A10: 9. Ghi chú đọc bảng | B10: - Ô nhập Tỷ giá dùng dấu phẩy làm dấu thập phân theo chuẩn Việt Nam; tối đa 999.999,99. Nhập vượt trần sẽ bị chặn kèm thông báo. - Tỷ giá được hệ thống TỰ ĐỘNG cập nhật lại hằng ngày lúc 03:00 sáng theo tỷ giá bán của Vietcombank, khớp theo Mã tiền tệ (riêng VNĐ được bỏ qua). Vì vậy tỷ giá sửa tay hôm nay có thể khác vào sáng hôm sau — đây là hành vi đúng, không phải lỗi. Khi kiểm thử tỷ giá, hãy đối chiếu trong cùng một ngày. - Nút Xóa bị mờ (không bấm được) với tiền tệ đang được dùng ở chứng từ khác. Trạng thái mờ này xuất hiện chậm hơn bảng khoảng vài trăm mili giây — vừa mở màn mà nút còn sáng là bình thường, bấm vào vẫn bị hệ thống chặn lại. - Nút Khóa / Mở khóa nằm NGAY TRONG cột Trạng thái, không nằm ở cột Hành động. - Bộ lọc được hệ thống ghi nhớ trong 10 phút: rời màn rồi quay lại trong 10 phút thì bộ lọc cũ vẫn còn. Khi kiểm thử bộ lọc, nhớ bấm Làm mới trước mỗi kịch bản. - Nút Xuất Excel luôn hiện với mọi người vào được màn.
A11: Testcase _ Danh mục tiền tệ- Cập nhật ngày 13/08/2026 | F11: TEST SUMMARY | I11: Số TH DNS kiểm thử đạt (P): | K11: =COUNTIF(K18:M1001,"Passed") | M11: Số trường hợp TP kiểm thử đạt (P): | P11: =COUNTIF(O18:Q200,"Passed")
I12: Số TH DNS kiểm thử không đạt (F) | K12: =COUNTIF(K18:M1001,"Failed") | M12: Số trường hợp TP kiểm thử không đạt (F) | P12: =COUNTIF(O19:Q201,"Fail")
I13: Số TH DNS kiểm thử đang xem xét (PE) | K13: =COUNTIF(K18:M1001,"Pending") | M13: Số trường hợp TP kiểm thử đang xem xét (PE) | P13: =COUNTIF(O20:Q202,"Pending")
I14: Số TH DNS kiểm thử chưa thực hiện | K14: =COUNTIF(K18:K1001,"Not Executed") | M14: Số trường hợp TP kiểm thử chưa thực hiện | P14: =K16-P15
I15: Tổng số TH DNS kiểm thử | K15: =COUNTIF(K18:K1001,"<>") | M15: Tổng số trường hợp TP kiểm thử | P15: =sum(P11:Q13)
I16: Tổng số testcase | K16: =COUNTIF(I18:I1003,"*")
A17: Module | B17: Nhóm chức năng | C17: TC ID | D17: Chức năng | E17: Priority | F17: Tiền điều kiện | G17: Bước thực hiện | H17: Test Data | I17: Expected Result (chi tiết) | J17: KQ thực tế | K17: DNS check lần 1 | L17: DNS check lần 2 | M17: DNS check lần 3 | N17: Ghi chú | O17: TP check lần 1 | P17: TP check lần 2 | Q17: TP check lần 3
C18: Phân quyền & truy cập
A19: Danh mục tiền tệ | B19: Phân quyền & truy cập | C19: TC-ROLE-01 | D19: Vào màn hình khi chỉ có quyền Xem | E19: P0 | F19: Có sẵn 2 tài khoản: tài khoản A chỉ được cấp quyền "Xem danh mục tiền tệ"; tài khoản B được cấp quyền "Quản lý danh mục tiền tệ". Danh mục đang có 11 tiền tệ, trong đó VNĐ và USD đang được dùng ở chứng từ khác, tiền tệ "TST" mới tạo chưa dùng ở đâu. | G19: 1. Đăng nhập bằng tài khoản A 2. Vào phân hệ Tài chính → Danh mục → Danh mục tiền tệ hoặc theo đường dẫn chứa /finance/currencies | H19: Tài khoản A (chỉ có quyền Xem danh mục tiền tệ) | I19: - Vào được màn hình, bảng hiển thị đủ 11 tiền tệ - KHÔNG có nút Tạo mới - Trên mỗi dòng chỉ có nút Xem (hình con mắt); KHÔNG có nút Sửa, nút Xóa - Trong cột Trạng thái KHÔNG có nút Khóa / Mở khóa - Vẫn có nút Xuất Excel | J19: - Vào được màn hình, bảng hiển thị đủ 11 tiền tệ - KHÔNG có nút Tạo mới - Trên mỗi dòng chỉ có nút Xem (hình con mắt); KHÔNG có nút Sửa, nút Xóa - Trong cột Trạng thái KHÔNG có nút Khóa / Mở khóa - Vẫn có nút Xuất Excel | K19: Passed
C20: TC-ROLE-02 | D20: Vào màn hình khi có quyền Quản lý | E20: P0 | F20: Có sẵn 2 tài khoản: tài khoản A chỉ được cấp quyền "Xem danh mục tiền tệ"; tài khoản B được cấp quyền "Quản lý danh mục tiền tệ". Danh mục đang có 11 tiền tệ, trong đó VNĐ và USD đang được dùng ở chứng từ khác, tiền tệ "TST" mới tạo chưa dùng ở đâu. | G20: 1. Đăng nhập bằng tài khoản B 2. Vào Danh mục tiền tệ | H20: Tài khoản B (có quyền Quản lý danh mục tiền tệ) | I20: - Vào được màn hình - Có nút Tạo mới và nút Xuất Excel - Mỗi dòng có đủ 3 nút: Xem, Sửa, Xóa - Cột Trạng thái có nút Khóa (với dòng đang Hoạt động) hoặc Mở khóa (với dòng đang Khóa) | J20: - Vào được màn hình - Có nút Tạo mới và nút Xuất Excel - Mỗi dòng có đủ 3 nút: Xem, Sửa, Xóa - Cột Trạng thái có nút Khóa (với dòng đang Hoạt động) hoặc Mở khóa (với dòng đang Khóa) | K20: Passed
C21: TC-ROLE-03 | D21: Chặn vào màn hình khi không có quyền nào | E21: P0 | F21: Tài khoản C không được cấp cả hai quyền "Xem danh mục tiền tệ" và "Quản lý danh mục tiền tệ". | G21: 1. Đăng nhập bằng tài khoản C 2. Mở phân hệ Tài chính, tìm mục Danh mục tiền tệ 3. Dán thẳng đường dẫn của màn Danh mục tiền tệ vào thanh địa chỉ | H21: Tài khoản C (không có quyền nào của màn này) | I21: - Mục menu Danh mục tiền tệ KHÔNG hiện trong phân hệ Tài chính - Dán thẳng đường dẫn thì hệ thống chuyển sang trang báo không tìm thấy, KHÔNG hiện dữ liệu tiền tệ nào Không được để lộ dù chỉ một phần bảng dữ liệu rồi mới chuyển trang | J21: - Mục menu Danh mục tiền tệ KHÔNG hiện trong phân hệ Tài chính - Dán thẳng đường dẫn thì hệ thống chuyển sang trang báo không tìm thấy, KHÔNG hiện dữ liệu tiền tệ nào Không được để lộ dù chỉ một phần bảng dữ liệu rồi mới chuyển trang | K21: Passed
C22: TC-ROLE-04 | D22: Chặn Thêm mới khi bỏ qua giao diện | E22: P0 | F22: Có sẵn 2 tài khoản: tài khoản A chỉ được cấp quyền "Xem danh mục tiền tệ"; tài khoản B được cấp quyền "Quản lý danh mục tiền tệ". Danh mục đang có 11 tiền tệ, trong đó VNĐ và USD đang được dùng ở chứng từ khác, tiền tệ "TST" mới tạo chưa dùng ở đâu. Chuẩn bị công cụ kiểm thử API và mã đăng nhập của tài khoản A. | G22: 1. Đăng nhập bằng tài khoản A, lấy mã đăng nhập 2. Dùng công cụ kiểm thử API gọi thẳng chức năng Thêm tiền tệ, bỏ qua giao diện 3. Mở lại màn Danh mục tiền tệ kiểm tra | H22: Mã tiền tệ: ZZZ; Tên tiền tệ: Tiền thử; Tỷ giá: 1,00 | I22: - Hệ thống từ chối, báo không có quyền - Danh sách vẫn 11 tiền tệ, không xuất hiện ZZZ Đây là nhóm dành cho tester kỹ thuật; nếu bản ghi được tạo là lỗ hổng phân quyền nghiêm trọng | J22: - Hệ thống từ chối, báo không có quyền - Danh sách vẫn 11 tiền tệ, không xuất hiện ZZZ Đây là nhóm dành cho tester kỹ thuật; nếu bản ghi được tạo là lỗ hổng phân quyền nghiêm trọng | K22: Passed
C23: TC-ROLE-05 | D23: Chặn Sửa khi bỏ qua giao diện | E23: P0 | F23: Có sẵn 2 tài khoản: tài khoản A chỉ được cấp quyền "Xem danh mục tiền tệ"; tài khoản B được cấp quyền "Quản lý danh mục tiền tệ". Danh mục đang có 11 tiền tệ, trong đó VNĐ và USD đang được dùng ở chứng từ khác, tiền tệ "TST" mới tạo chưa dùng ở đâu. | G23: 1. Đăng nhập bằng tài khoản A 2. Dùng công cụ kiểm thử API gọi thẳng chức năng Sửa tiền tệ USD, bỏ qua giao diện 3. Mở lại màn Danh mục tiền tệ, xem dòng USD | H23: Sửa Tên tiền tệ USD thành "Bị sửa trộm" | I23: - Hệ thống từ chối, báo không có quyền - Dòng USD giữ nguyên tên cũ và tỷ giá cũ | J23: - Hệ thống từ chối, báo không có quyền - Dòng USD giữ nguyên tên cũ và tỷ giá cũ | K23: Passed
C24: TC-ROLE-06 | D24: Chặn Xóa khi bỏ qua giao diện | E24: P0 | F24: Có sẵn 2 tài khoản: tài khoản A chỉ được cấp quyền "Xem danh mục tiền tệ"; tài khoản B được cấp quyền "Quản lý danh mục tiền tệ". Danh mục đang có 11 tiền tệ, trong đó VNĐ và USD đang được dùng ở chứng từ khác, tiền tệ "TST" mới tạo chưa dùng ở đâu. | G24: 1. Đăng nhập bằng tài khoản A 2. Dùng công cụ kiểm thử API gọi thẳng chức năng Xóa tiền tệ "TST", bỏ qua giao diện 3. Mở lại màn Danh mục tiền tệ | H24: Tiền tệ TST (chưa dùng ở đâu nên về nghiệp vụ là xóa được) | I24: - Hệ thống từ chối, báo không có quyền - Tiền tệ TST vẫn còn trong danh sách Bản ghi "xóa được" là phép thử nặng nhất: nếu quyền hở thì dữ liệu mất thật | J24: - Hệ thống từ chối, báo không có quyền - Tiền tệ TST vẫn còn trong danh sách Bản ghi "xóa được" là phép thử nặng nhất: nếu quyền hở thì dữ liệu mất thật | K24: Passed
C25: TC-ROLE-07 | D25: Chặn Khóa / Mở khóa khi bỏ qua giao diện | E25: P1 | F25: Có sẵn 2 tài khoản: tài khoản A chỉ được cấp quyền "Xem danh mục tiền tệ"; tài khoản B được cấp quyền "Quản lý danh mục tiền tệ". Danh mục đang có 11 tiền tệ, trong đó VNĐ và USD đang được dùng ở chứng từ khác, tiền tệ "TST" mới tạo chưa dùng ở đâu. | G25: 1. Đăng nhập bằng tài khoản A 2. Dùng công cụ kiểm thử API gọi thẳng chức năng Khóa tiền tệ USD, bỏ qua giao diện 3. Mở lại màn Danh mục tiền tệ | H25: Tiền tệ USD đang ở trạng thái Hoạt động | I25: - Hệ thống từ chối, báo không có quyền - USD vẫn ở trạng thái Hoạt động | J25: - Hệ thống từ chối, báo không có quyền - USD vẫn ở trạng thái Hoạt động | K25: Passed
C26: TC-ROLE-08 | D26: Người có quyền Quản lý làm được trọn vòng đời | E26: P1 | F26: Có sẵn 2 tài khoản: tài khoản A chỉ được cấp quyền "Xem danh mục tiền tệ"; tài khoản B được cấp quyền "Quản lý danh mục tiền tệ". Danh mục đang có 11 tiền tệ, trong đó VNĐ và USD đang được dùng ở chứng từ khác, tiền tệ "TST" mới tạo chưa dùng ở đâu. | G26: 1. Đăng nhập bằng tài khoản B 2. Tạo mới 1 tiền tệ 3. Sửa tiền tệ vừa tạo 4. Khóa rồi Mở khóa tiền tệ đó 5. Xóa tiền tệ đó | H26: Mã: TC1; Tên: Tiền kiểm thử; Tỷ giá: 1.000,00 | I26: - Cả 5 thao tác đều thực hiện được, mỗi thao tác có thông báo thành công tương ứng - Sau bước 5, tiền tệ TC1 không còn trong danh sách | J26: - Cả 5 thao tác đều thực hiện được, mỗi thao tác có thông báo thành công tương ứng - Sau bước 5, tiền tệ TC1 không còn trong danh sách | K26: Passed
C27: I. HIỂN THỊ TRANG & TRUY CẬP
A28: Danh mục tiền tệ | B28: HIỂN THỊ TRANG & TRUY CẬP | C28: TC_01.001 | D28: Mở màn hình lần đầu | E28: P0 | F28: Danh mục có 11 tiền tệ, trong đó 9 tiền tệ Hoạt động và 2 tiền tệ đang Khóa; có ít nhất 1 tiền tệ đã nhập Tên gọi khác (USD- Đô la Mỹ) và 1 tiền tệ bỏ trống Tên gọi khác. | G28: 1. Vào phân hệ Tài chính → Danh mục → Danh mục tiền tệ 2. Quan sát toàn màn hình | H28: — | I28: - Tiêu đề trang và tiêu đề bảng đều là "Danh mục tiền tệ" - Khối lọc phía trên có tiêu đề "Bộ lọc danh mục tiền tệ", mặc định ở dạng thu gọn (chỉ hiện ô tìm nhanh) - Bảng hiển thị đủ 7 cột theo đúng thứ tự: STT, Mã tiền tệ, Tên tiền tệ, Tỷ giá (VNĐ), Cập nhật, Trạng thái, Hành động - Dưới bảng có nút Tạo mới và nút Xuất Excel | J28: - Tiêu đề trang và tiêu đề bảng đều là "Danh mục tiền tệ" - Khối lọc phía trên có tiêu đề "Bộ lọc danh mục tiền tệ", mặc định ở dạng thu gọn (chỉ hiện ô tìm nhanh) - Bảng hiển thị đủ 7 cột theo đúng thứ tự: STT, Mã tiền tệ, Tên tiền tệ, Tỷ giá (VNĐ), Cập nhật, Trạng thái, Hành động - Dưới bảng có nút Tạo mới và nút Xuất Excel | K28: Passed
C29: TC_01.002 | D29: Kiểm tra hiển thị danh sách tiền tệ | E29: P0 | F29: Có 11 tiền tệ theo data test | G29: 1. Đăng nhập bằng tài khoản có quyền quản lý danh mục tiền tệ 2. Vào tài chính- > Danh mục- > Danh mục tiền tệ 3. Quan sát danh sách | H29: - | I29: - Hiển thị đủ 11 tiền tệ - Hiển thị cả tên Hoạt động và Khóa - Các cột hiển thị đúng thứ tự: STT, Mã tiền tệ, Tỷ giá (VNĐ), Cập nhật, Trạng thái, Hành động | J29: - Hiển thị đủ 11 tiền tệ - Hiển thị cả tên Hoạt động và Khóa - Các cột hiển thị đúng thứ tự: STT, Mã tiền tệ, Tỷ giá (VNĐ), Cập nhật, Trạng thái, Hành động | K29: Passed
C30: TC_01.003 | D30: Cột Tên tiền tệ hiện dòng phụ Tên gọi khác | E30: P1 | F30: USD có Tên gọi khác = Đô la mỹ; TST không có tên gọi khác | G30: 1. Mở màn hình 2. Nhìn dòng USD 3. Nhìn dòng TST không có tên gọi khác | H30: — | I30: - Dòng USD hiện tên tiền tệ ở dòng trên, dòng dưới hiện "Tên gọi khác: Đô la Mỹ" - TST chỉ hiển thị Tên tiền tệ, không hiển thị dòng Tện gọi khác trống | J30: - Dòng USD hiện tên tiền tệ ở dòng trên, dòng dưới hiện "Tên gọi khác: Đô la Mỹ" - TST chỉ hiển thị Tên tiền tệ, không hiển thị dòng Tện gọi khác trống | K30: Passed
C31: TC_01.004 | D31: Định dạng số của cột Tỷ giá (VNĐ) | E31: P0 | F31: Danh mục có các tỷ giá khác nhau | G31: 1. Mở Danh mục tiền tệ. 2. Kiểm tra cột Tỷ giá (VNĐ | H31: — | I31: - Tỷ giá hiển thị dạng 26.520,00 — dấu chấm ngăn hàng nghìn, dấu phẩy ngăn phần thập phân, luôn có đúng 2 chữ số thập phân Không được hiện dạng 26520 hay 26,520.00 | J31: - Tỷ giá hiển thị dạng 26.520,00 — dấu chấm ngăn hàng nghìn, dấu phẩy ngăn phần thập phân, luôn có đúng 2 chữ số thập phân Không được hiện dạng 26520 hay 26,520.00 | K31: Passed
C32: TC_01.005 | D32: Cột Trạng thái hiển thị đúng nhãn | E32: P0 | F32: Danh mục có 11 tiền tệ, trong đó 9 tiền tệ Hoạt động và 2 tiền tệ đang Khóa; có ít nhất 1 tiền tệ đã nhập Tên gọi khác (USD- Đô la Mỹ) và 1 tiền tệ bỏ trống Tên gọi khác. | G32: 1. Mở màn hình 2. Đối chiếu cột Trạng thái | H32: — | I32: Tỷ giá hiển thị theo định dạng Việt Nam. Ví dụ: 26.520,00. Có dấu chấm ngăn cách hàng nghìn và dấu phẩy ngăn phần thập phân, luôn có 2 chữ số thập phân | J32: Tỷ giá hiển thị theo định dạng Việt Nam. Ví dụ: 26.520,00. Có dấu chấm ngăn cách hàng nghìn và dấu phẩy ngăn phần thập phân, luôn có 2 chữ số thập phân | K32: Passed
C33: TC_01.006 | D33: Vị trí nút Khóa / Mở khóa | E33: P1 | F33: Danh mục có 11 tiền tệ, trong đó 9 tiền tệ Hoạt động và 2 tiền tệ đang Khóa; có ít nhất 1 tiền tệ đã nhập Tên gọi khác (USD- Đô la Mỹ) và 1 tiền tệ bỏ trống Tên gọi khác. | G33: 1. Mở màn hình 2. Nhìn cột Trạng thái và cột Hành động | H33: — | I33: - Nút Khóa (hình ổ khóa đóng) hoặc Mở khóa (hình ổ khóa mở) nằm ngay bên phải nhãn trạng thái, TRONG cột Trạng thái - Cột Hành động chỉ có 3 nút: Xem, Sửa, Xóa | J33: - Nút Khóa (hình ổ khóa đóng) hoặc Mở khóa (hình ổ khóa mở) nằm ngay bên phải nhãn trạng thái, TRONG cột Trạng thái - Cột Hành động chỉ có 3 nút: Xem, Sửa, Xóa | K33: Passed
C34: TC_01.007 | D34: Cột Cập nhật khi chưa có ngày cập nhật | E34: P2 | F34: Danh mục có 11 tiền tệ, trong đó 9 tiền tệ Hoạt động và 2 tiền tệ đang Khóa; có ít nhất 1 tiền tệ đã nhập Tên gọi khác (USD- Đô la Mỹ) và 1 tiền tệ bỏ trống Tên gọi khác. | G34: 1. Mở màn hình 2. Nhìn cột Cập nhật của mọi dòng | H34: — | I34: - Dòng có ngày cập nhật hiện đúng ngày giờ - Dòng chưa có ngày cập nhật hiện dấu gạch ngang, không để ô trắng trơn | J34: - Dòng có ngày cập nhật hiện đúng ngày giờ - Dòng chưa có ngày cập nhật hiện dấu gạch ngang, không để ô trắng trơn | K34: Passed
C35: TC_01.008 | D35: Bảng trống khi bộ lọc không khớp gì | E35: P1 | F35: Danh mục có 11 tiền tệ, trong đó 9 tiền tệ Hoạt động và 2 tiền tệ đang Khóa; có ít nhất 1 tiền tệ đã nhập Tên gọi khác (USD- Đô la Mỹ) và 1 tiền tệ bỏ trống Tên gọi khác. | G35: 1. Gõ vào ô tìm nhanh chuỗi "khongtontai123" 2. Bấm Tìm kiếm | H35: khongtontai123 | I35: - Bảng hiện dòng chữ "Không có dữ liệu phù hợp bộ lọc." - Dòng Hiển thị dưới bảng cho tổng là 0 - Nút Tạo mới và Xuất Excel vẫn còn | J35: - Bảng hiện dòng chữ "Không có dữ liệu phù hợp bộ lọc." - Dòng Hiển thị dưới bảng cho tổng là 0 - Nút Tạo mới và Xuất Excel vẫn còn | K35: Passed
C36: TC_01.009 | D36: Vào màn hình khi danh mục rỗng | E36: P2 | F36: Môi trường kiểm thử riêng, danh mục tiền tệ không có bản ghi nào. | G36: 1. Mở màn Danh mục tiền tệ | H36: — | I36: - Màn hình mở bình thường, không báo lỗi - Bảng hiện thông báo không có dữ liệu, tổng là 0 | J36: - Màn hình mở bình thường, không báo lỗi - Bảng hiện thông báo không có dữ liệu, tổng là 0 | K36: Passed
C37: II. BỘ LỌC & TÌM KIẾM
A38: Danh mục tiền tệ | B38: BỘ LỌC & TÌM KIẾM | C38: TC_02.001 | D38: Tìm nhanh theo Mã tiền tệ | E38: P0 | F38: Có USD trong danh sách | G38: 1. Gõ "USD" vào ô tìm nhanh 2. Bấm Tìm kiếm | H38: USD | I38: - Kết quả chỉ còn dòng có mã USD - Tổng dưới bảng đổi theo số dòng khớp | J38: - Kết quả chỉ còn dòng có mã USD - Tổng dưới bảng đổi theo số dòng khớp | K38: Passed
C39: TC_02.002 | D39: Tìm nhanh theo Tên tiền tệ | E39: P0 | F39: Có tiền tệ "Đô la Mỹ" | G39: 1. Gõ "Đô la" vào ô tìm nhanh 2. Bấm Tìm kiếm | H39: Đô la | I39: - Hiển thị các tiền tệ có chuỗi Đô la trong Tên tiền tệ hoặc Tên gọi khác | J39: - Hiển thị các tiền tệ có chuỗi Đô la trong Tên tiền tệ hoặc Tên gọi khác | K39: Passed
C40: TC_02.003 | D40: Tìm nhanh theo Tên gọi khác | E40: P0 | F40: USD có tên gọi khác = Đô la Mỹ | G40: 1. Gõ đúng phần Tên gọi khác của một tiền tệ (ví dụ "Đô la Mỹ") 2. Bấm Tìm kiếm | H40: Đô la Mỹ | I40: - Hiên thị USD dù chuỗi tìm kiếm nằm ở Tên gọi khác | J40: - Hiên thị USD dù chuỗi tìm kiếm nằm ở Tên gọi khác | K40: Passed
C41: TC_02.004 | D41: Tìm nhanh khớp một phần chuỗi | E41: P1 | F41: Chỉ nhập 1 vài phần của chuỗi | G41: 1. Gõ "US" (chỉ 2 ký tự đầu của USD) 2. Bấm Tìm kiếm | H41: US | I41: - USD vẫn nằm trong kết quả Không được yêu cầu gõ đúng nguyên mã mới ra kết quả | J41: - USD vẫn nằm trong kết quả Không được yêu cầu gõ đúng nguyên mã mới ra kết quả | K41: Passed
C42: TC_02.005 | D42: Tìm nhanh không phân biệt hoa thường | E42: P1 | G42: 1. Gõ "usd" bằng chữ thường 2. Bấm Tìm kiếm | H42: usd | I42: - Kết quả giống hệt khi gõ "USD" | J42: - Kết quả giống hệt khi gõ "USD" | K42: Passed
C43: TC_02.006 | D43: Gõ ô tìm nhanh mà chưa bấm Tìm kiếm | E43: P1 | G43: 1. Gõ "USD" vào ô tìm nhanh 2. KHÔNG bấm gì, chờ 5 giây 3. Quan sát bảng | H43: USD | I43: - Bảng vẫn giữ nguyên 11 dòng, chưa lọc Ô tìm nhanh chỉ có tác dụng sau khi bấm nút Tìm kiếm hoặc nhấn Enter | J43: - Bảng vẫn giữ nguyên 11 dòng, chưa lọc Ô tìm nhanh chỉ có tác dụng sau khi bấm nút Tìm kiếm hoặc nhấn Enter | K43: Passed
C44: TC_02.007 | D44: Lọc theo Trạng thái = Hoạt động | E44: P0 | F44: Có 9 tiền tệ hoạt động, 2 tiền tệ Khóa | G44: 1. Bấm mở bộ lọc nâng cao 2. Chọn Trạng thái = Hoạt động 3. Bấm Tìm kiếm | H44: Trạng thái: Hoạt động | I44: - Kết quả chỉ còn 9 dòng, tất cả đều mang nhãn Hoạt động - Không dòng nào mang nhãn Khóa | J44: - Kết quả chỉ còn 9 dòng, tất cả đều mang nhãn Hoạt động - Không dòng nào mang nhãn Khóa | K44: Passed
C45: TC_02.008 | D45: Lọc theo Trạng thái = Khóa | E45: P0 | F45: Có 9 tiền tệ hoạt động, 2 tiền tệ Khóa | G45: 1. Mở bộ lọc nâng cao 2. Chọn Trạng thái = Khóa 3. Bấm Tìm kiếm | H45: Trạng thái: Khóa | I45: - Kết quả chỉ còn 2 dòng, đều mang nhãn Khóa | J45: - Kết quả chỉ còn 2 dòng, đều mang nhãn Khóa | K45: Passed
C46: TC_02.009 | D46: Bỏ chọn Trạng thái bằng dấu x | E46: P1 | G46: 1. Chọn Trạng thái = Khóa, bấm Tìm kiếm 2. Bấm dấu x trên ô Trạng thái để bỏ chọn 3. Bấm Tìm kiếm | H46: Trạng thái: (bỏ trống) | I46: - Danh sách quay lại đủ 11 dòng Ô Trạng thái không có lựa chọn "Tất cả"; bỏ lọc bằng cách bấm dấu x | J46: - Danh sách quay lại đủ 11 dòng Ô Trạng thái không có lựa chọn "Tất cả"; bỏ lọc bằng cách bấm dấu x | K46: Passed
C47: TC_02.010 | D47: Kết hợp tìm nhanh và lọc Trạng thái | E47: P0 | F47: Có tiền tệ phù hợp với cả 2 điều kiện | G47: 1. Gõ "D" vào ô tìm nhanh 2. Chọn Trạng thái = Hoạt động 3. Bấm Tìm kiếm | H47: Từ khóa: D; Trạng thái: Hoạt động | I47: - Kết quả phải thỏa đồng thời điều kiện tìm kiếm và Trạng thái = Hoạt động. Không hiển thị tiền tệ Khóa. | J47: - Kết quả phải thỏa đồng thời điều kiện tìm kiếm và Trạng thái = Hoạt động. Không hiển thị tiền tệ Khóa. | K47: Passed
C48: TC_02.011 | D48: Nút Làm mới xóa hết điều kiện và nạp lại | E48: P0 | F48: Đang có điều kiện tìm kiếm/lọc | G48: 1. Nhập USD. 2. Chọn Trạng thái = Hoạt động. 3. Bấm Tìm kiếm. 4. Bấm Làm mới | H48: — | I48: - Ô Tìm nhanh được xóa. - Trạng thái được xóa. - Danh sách hiển thị lại toàn bộ 11 tiền tệ | J48: - Ô Tìm nhanh được xóa. - Trạng thái được xóa. - Danh sách hiển thị lại toàn bộ 11 tiền tệ | K48: Passed
C49: TC_02.012 | D49: Bộ lọc được nhớ khi quay lại màn trong 10 phút | E49: P1 | F49: Đang cso điều kiện tìm kiếm/lọc | G49: 1. Chọn Trạng thái = Khóa, bấm Tìm kiếm 2. Sang màn khác 3. Trong vòng 10 phút quay lại Danh mục tiền tệ | H49: Trạng thái: Khóa | I49: - Ô Trạng thái vẫn đang là Khóa và danh sách vẫn đang lọc theo Khóa - Trạng thái đóng/mở của khối lọc nâng cao cũng được giữ nguyên | J49: - Ô Trạng thái vẫn đang là Khóa và danh sách vẫn đang lọc theo Khóa - Trạng thái đóng/mở của khối lọc nâng cao cũng được giữ nguyên | K49: Passed
C50: TC_02.013 | D50: Bộ lọc hết hạn nhớ sau 10 phút | E50: P2 | F50: Đang cso điều kiện tìm kiếm/lọc | G50: 1. Chọn Trạng thái = Khóa, bấm Tìm kiếm 2. Sang màn khác và chờ quá 10 phút 3. Quay lại Danh mục tiền tệ | H50: Trạng thái: Khóa | I50: - Bộ lọc trở về trống, danh sách hiện đủ 11 dòng | J50: - Bộ lọc trở về trống, danh sách hiện đủ 11 dòng | K50: Passed
C51: TC_02.014 | D51: Lọc xong tự về trang 1 | E51: P1 | G51: 1. Chuyển sang trang 2 2. Chọn Trạng thái = Hoạt động 3. Bấm Tìm kiếm | H51: — | I51: - Kết quả hiển thị từ trang 1 Không được giữ nguyên trang 2 rồi báo bảng trống | J51: - Kết quả hiển thị từ trang 1 Không được giữ nguyên trang 2 rồi báo bảng trống | K51: Passed
C52: TC_02.015 | D52: Tìm nhanh với chuỗi có khoảng trắng thừa | E52: P2 | G52: 1. Gõ " USD " (có khoảng trắng đầu và cuối) 2. Bấm Tìm kiếm | H52: USD | I52: - Vẫn tìm ra USD, không báo không có dữ liệu (auto trim dữ liệu đầu cuối) | J52: - Vẫn tìm ra USD, không báo không có dữ liệu (auto trim dữ liệu đầu cuối) | K52: Passed
C53: TC_02.016 | D53: Tìm nhanh với ký tự đặc biệt | E53: P2 | G53: 1. Gõ chuỗi "%'" vào ô tìm nhanh 2. Bấm Tìm kiếm | H53: %' | I53: - Màn hình không lỗi, không trắng trang - Hiện kết quả rỗng hoặc kết quả khớp đúng nghĩa đen của chuỗi đó | J53: - Màn hình không lỗi, không trắng trang - Hiện kết quả rỗng hoặc kết quả khớp đúng nghĩa đen của chuỗi đó | K53: Passed
C54: III. DANH SÁCH, SẮP XẾP & PHÂN TRANG
A55: Danh mục tiền tệ | B55: DANH SÁCH, SẮP XẾP & PHÂN TRANG | C55: TC_03.001 | D55: Sắp xếp theo Mã tiền tệ tăng dần | E55: P0 | F55: Đăng nhập bằng tài khoản có quyền 'Quản lý danh mục tiền tệ'. Đang ở màn hình Danh mục tiền tệ có danh sách bản ghi (ít nhất 2 bản ghi). | G55: 1. Bấm tiêu đề cột Mã tiền tệ 1 lần 2. Quan sát thứ tự các dòng | H55: — | I55: - Danh sách xếp theo mã từ A đến Z - Mũi tên trên tiêu đề cột chỉ chiều tăng dần | J55: - Danh sách xếp theo mã từ A đến Z - Mũi tên trên tiêu đề cột chỉ chiều tăng dần | K55: Passed
C56: TC_03.002 | D56: Sắp xếp theo Mã tiền tệ giảm dần | E56: P0 | F56: Đăng nhập bằng tài khoản có quyền 'Quản lý danh mục tiền tệ'. Đang ở màn hình Danh mục tiền tệ có danh sách bản ghi (ít nhất 2 bản ghi). | G56: 1. Bấm tiêu đề cột Mã tiền tệ 2 lần 2. Quan sát | H56: — | I56: - Danh sách xếp ngược từ Z về A, mũi tên đổi chiều | J56: - Danh sách xếp ngược từ Z về A, mũi tên đổi chiều | K56: Passed
C57: TC_03.003 | D57: Sắp xếp theo Tên tiền tệ | E57: P1 | F57: Đăng nhập bằng tài khoản có quyền 'Quản lý danh mục tiền tệ'. Đang ở màn hình Danh mục tiền tệ có danh sách bản ghi (ít nhất 2 bản ghi). | G57: 1. Bấm tiêu đề cột Tên tiền tệ 2. Quan sát | H57: — | I57: - Danh sách xếp theo Tên tiền tệ, thứ tự thật sự thay đổi | J57: - Danh sách xếp theo Tên tiền tệ, thứ tự thật sự thay đổi | K57: Passed
C58: TC_03.004 | D58: Sắp xếp theo Tỷ giá | E58: P0 | F58: Đăng nhập bằng tài khoản có quyền 'Quản lý danh mục tiền tệ'. Đang ở màn hình Danh mục tiền tệ có danh sách bản ghi (ít nhất 2 bản ghi). | G58: 1. Bấm tiêu đề cột Tỷ giá (VNĐ) 2. Quan sát | H58: — | I58: - Danh sách xếp theo giá trị SỐ của tỷ giá, không phải theo chuỗi - Nếu xếp theo chuỗi thì 9.000,00 sẽ đứng sau 26.520,00 — đó là lỗi | J58: - Danh sách xếp theo giá trị SỐ của tỷ giá, không phải theo chuỗi - Nếu xếp theo chuỗi thì 9.000,00 sẽ đứng sau 26.520,00 — đó là lỗi | K58: Passed
C59: TC_03.005 | D59: Sắp xếp theo Cập nhật | E59: P1 | F59: Đăng nhập bằng tài khoản có quyền 'Quản lý danh mục tiền tệ'. Đang ở màn hình Danh mục tiền tệ có danh sách bản ghi (ít nhất 2 bản ghi). | G59: 1. Bấm tiêu đề cột Cập nhật 2. Quan sát | H59: — | I59: - Danh sách xếp theo ngày giờ cập nhật, thứ tự thật sự thay đổi | J59: - Danh sách xếp theo ngày giờ cập nhật, thứ tự thật sự thay đổi | K59: Passed
C60: TC_03.006 | D60: Sắp xếp theo Trạng thái | E60: P2 | F60: Đăng nhập bằng tài khoản có quyền 'Quản lý danh mục tiền tệ'. Đang ở màn hình Danh mục tiền tệ có danh sách bản ghi (ít nhất 2 bản ghi). | G60: 1. Bấm tiêu đề cột Trạng thái 2. Quan sát | H60: — | I60: - Các dòng cùng trạng thái được gom lại liền nhau | J60: - Các dòng cùng trạng thái được gom lại liền nhau | K60: Passed
C61: TC_03.007 | D61: Cột STT và cột Hành động không sắp xếp được | E61: P2 | F61: Đăng nhập bằng tài khoản có quyền 'Quản lý danh mục tiền tệ'. Đang ở màn hình Danh mục tiền tệ có danh sách bản ghi (ít nhất 2 bản ghi). | G61: 1. Bấm tiêu đề cột STT 2. Bấm tiêu đề cột Hành động | H61: — | I61: - Hai cột này không có mũi tên sắp xếp, bấm vào không đổi thứ tự và không lỗi | J61: - Hai cột này không có mũi tên sắp xếp, bấm vào không đổi thứ tự và không lỗi | K61: Passed
C62: TC_03.008 | D62: Sắp xếp giữ nguyên khi chuyển trang | E62: P1 | F62: Đăng nhập bằng tài khoản có quyền 'Quản lý danh mục tiền tệ'. Đang ở màn hình Danh mục tiền tệ. Tổng số bản ghi lớn hơn cỡ trang mặc định (VD: Có 11 bản ghi, cỡ trang đang đặt là 10) | G62: 1. Sắp xếp theo Tỷ giá giảm dần 2. Chuyển sang trang 2 | H62: — | I62: - Trang 2 tiếp nối đúng thứ tự đã sắp, không quay về thứ tự mặc định | J62: - Trang 2 tiếp nối đúng thứ tự đã sắp, không quay về thứ tự mặc định | K62: Passed
C63: TC_03.009 | D63: Chuyển trang bằng nút số trang | E63: P0 | F63: Đăng nhập bằng tài khoản có quyền 'Quản lý danh mục tiền tệ'. Đang ở màn hình Danh mục tiền tệ. Tổng số bản ghi lớn hơn cỡ trang mặc định (VD: Có 11 bản ghi, cỡ trang đang đặt là 10) | G63: 1. Bấm số trang 2 | H63: — | I63: - Bảng hiện dòng thứ 11 - Cột STT bắt đầu từ 11 - Dòng Hiển thị dưới bảng cập nhật đúng khoảng đang xem | J63: - Bảng hiện dòng thứ 11 - Cột STT bắt đầu từ 11 - Dòng Hiển thị dưới bảng cập nhật đúng khoảng đang xem | K63: Passed
C64: TC_03.010 | D64: Đổi cỡ trang | E64: P0 | F64: Đăng nhập bằng tài khoản có quyền 'Quản lý danh mục tiền tệ'. Đang ở trang 1 (với TC 010) hoặc trang 2 (với TC 011) của màn hình Danh mục tiền tệ. | G64: 1. Đổi cỡ trang từ 10 sang 50 2. Quan sát | H64: Cỡ trang: 50 | I64: - Toàn bộ 11 dòng hiện trên 1 trang - Danh sách chỉ nạp lại đúng MỘT lần, không nhấp nháy tải hai lượt | J64: - Toàn bộ 11 dòng hiện trên 1 trang - Danh sách chỉ nạp lại đúng MỘT lần, không nhấp nháy tải hai lượt | K64: Passed
C65: TC_03.011 | D65: Đổi cỡ trang khi đang ở trang cuối | E65: P1 | F65: Đăng nhập bằng tài khoản có quyền 'Quản lý danh mục tiền tệ'. Đang ở trang 1 (với TC 010) hoặc trang 2 (với TC 011) của màn hình Danh mục tiền tệ. | G65: 1. Đổi cỡ trang sang 50 | H65: Cỡ trang: 50 | I65: - Bảng hiện đủ dữ liệu từ trang 1, không hiện bảng trống - Giữ nguyên số trang 2 sau khi tăng cỡ trang sẽ ra bảng rỗng | J65: - Bảng hiện đủ dữ liệu từ trang 1, không hiện bảng trống - Giữ nguyên số trang 2 sau khi tăng cỡ trang sẽ ra bảng rỗng | K65: Passed
C66: TC_03.012 | D66: Đổi cỡ trang khi đang ở trang cuối | E66: P1 | F66: Đăng nhập bằng tài khoản có quyền 'Quản lý danh mục tiền tệ'. Đang ở trang 1 (với TC 010) hoặc trang 2 (với TC 011) của màn hình Danh mục tiền tệ. | G66: 1. Đổi cỡ trang sang 100 | H66: Cỡ trang: 100 | I66: - Bảng hiện đủ dữ liệu từ trang 1, không hiện bảng trống - Giữ nguyên số trang 2 sau khi tăng cỡ trang sẽ ra bảng rỗng | J66: - Bảng hiện đủ dữ liệu từ trang 1, không hiện bảng trống - Giữ nguyên số trang 2 sau khi tăng cỡ trang sẽ ra bảng rỗng | K66: Passed
C67: TC_03.013 | D67: Vào màn hình chỉ gọi dữ liệu một lần | E67: P1 | F67: Đăng nhập bằng tài khoản có quyền 'Quản lý danh mục tiền tệ'. Đang ở màn hình khác (chưa vào Danh mục tiền tệ) | G67: 1. Mở màn Danh mục tiền tệ từ menu 2. Quan sát hiệu ứng tải của bảng | H67: — | I67: - Bảng chỉ tải MỘT lượt rồi đứng yên - Bảng chớp tải hai lần liên tiếp khi vừa vào màn | J67: - Bảng chỉ tải MỘT lượt rồi đứng yên - Bảng chớp tải hai lần liên tiếp khi vừa vào màn | K67: Passed
C68: IV. THÊM / SỬA / XEM TIỀN TỆ
A69: Danh mục tiền tệ | B69: THÊM / SỬA / XEM TIỀN TỆ | C69: TC_04.001 | D69: Mở cửa sổ Thêm tiền tệ | E69: P0 | F69: Tài khoản có quyền Quản lý | G69: 1. Bấm nút Tạo mới | H69: — | I69: - Mở cửa sổ tiêu đề "Thêm tiền tệ" - Có 5 ô: Mã tiền tệ (bắt buộc), Trạng thái, Tên tiền tệ (bắt buộc), Tên gọi khác, Tỷ giá (VNĐ) (bắt buộc) - Ba ô bắt buộc có dấu sao đỏ bên cạnh nhãn - Cuối cửa sổ có 3 nút: Lưu, Lưu & Tiếp tục, Đóng | J69: - Mở cửa sổ tiêu đề "Thêm tiền tệ" - Có 5 ô: Mã tiền tệ (bắt buộc), Trạng thái, Tên tiền tệ (bắt buộc), Tên gọi khác, Tỷ giá (VNĐ) (bắt buộc) - Ba ô bắt buộc có dấu sao đỏ bên cạnh nhãn - Cuối cửa sổ có 3 nút: Lưu, Lưu & Tiếp tục, Đóng | K69: Passed
C70: TC_04.002 | D70: Thêm mới đầy đủ thông tin | E70: P0 | F70: Tài khoản có quyền Quản lý | G70: 1. Bấm Tạo mới 2. Nhập Mã tiền tệ, Tên tiền tệ, Tên gọi khác, Tỷ giá 3. Chọn Trạng thái = Hoạt động 4. Bấm Lưu | H70: Mã: TST; Tên: Tiền kiểm thử; Tên gọi khác: Đồng thử; Tỷ giá: 1.234,56; Trạng thái: Hoạt động | I70: - Hiện thông báo "Thêm mới thành công" - Cửa sổ đóng lại, danh sách nạp lại và có dòng TST - Cột Tỷ giá của dòng mới hiện 1.234,56 - Cột Tên tiền tệ hiện "Tiền kiểm thử" và dòng phụ "Tên gọi khác: Đồng thử" | J70: - Hiện thông báo "Thêm mới thành công" - Cửa sổ đóng lại, danh sách nạp lại và có dòng TST - Cột Tỷ giá của dòng mới hiện 1.234,56 - Cột Tên tiền tệ hiện "Tiền kiểm thử" và dòng phụ "Tên gọi khác: Đồng thử" | K70: Passed
C71: TC_04.003 | D71: Thêm mới chỉ nhập các ô bắt buộc | E71: P0 | F71: Tài khoản có quyền Quản lý | G71: 1. Bấm Tạo mới 2. Chỉ nhập Mã tiền tệ, Tên tiền tệ, Tỷ giá 3. Bấm Lưu | H71: Mã: TS2; Tên: Tiền thử 2; Tỷ giá: 100,00 | I71: - Lưu thành công - Dòng mới không có dòng phụ Tên gọi khác - Trạng thái mặc định là Hoạt động | J71: - Lưu thành công - Dòng mới không có dòng phụ Tên gọi khác - Trạng thái mặc định là Hoạt động | K71: Passed
C72: TC_04.004 | D72: Nút Lưu & Tiếp tục giữ cửa sổ để nhập tiếp | E72: P1 | F72: Tài khoản có quyền Quản lý | G72: 1. Bấm Tạo mới 2. Nhập đủ thông tin 3. Bấm Lưu & Tiếp tục | H72: Mã: TS3; Tên: Tiền thử 3; Tỷ giá: 50,00 | I72: - Hiện thông báo thêm mới thành công - Cửa sổ VẪN mở và các ô đã được xóa trắng để nhập bản ghi tiếp theo - Tiêu đề vẫn là "Thêm tiền tệ" | J72: - Hiện thông báo thêm mới thành công - Cửa sổ VẪN mở và các ô đã được xóa trắng để nhập bản ghi tiếp theo - Tiêu đề vẫn là "Thêm tiền tệ" | K72: Passed
C73: TC_04.005 | D73: Cửa sổ Sửa không có nút Lưu & Tiếp tục | E73: P1 | F73: Tài khoản có quyền Quản lý | G73: 1. Bấm nút Sửa trên dòng USD 2. Nhìn cụm nút cuối cửa sổ | H73: — | I73: - Chỉ có 2 nút: Lưu và Đóng Nút Lưu & Tiếp tục chỉ dành cho thêm mới | J73: - Chỉ có 2 nút: Lưu và Đóng Nút Lưu & Tiếp tục chỉ dành cho thêm mới | K73: Passed
C74: TC_04.006 | D74: Mở cửa sổ Sửa nạp đúng dữ liệu cũ | E74: P0 | F74: Tài khoản có quyền Quản lý | G74: 1. Bấm nút Sửa trên dòng USD | H74: — | I74: - Tiêu đề cửa sổ là "Sửa tiền tệ" - Các ô điền sẵn đúng dữ liệu đang có của USD: mã, tên, tên gọi khác, tỷ giá, trạng thái - Cạnh tiêu đề có hiện thông tin lần cập nhật gần nhất | J74: - Tiêu đề cửa sổ là "Sửa tiền tệ" - Các ô điền sẵn đúng dữ liệu đang có của USD: mã, tên, tên gọi khác, tỷ giá, trạng thái - Cạnh tiêu đề có hiện thông tin lần cập nhật gần nhất | K74: Passed
C75: TC_04.007 | D75: Sửa Tên tiền tệ | E75: P0 | F75: Tài khoản có quyền Quản lý | G75: 1. Bấm Sửa dòng TST 2. Đổi Tên tiền tệ 3. Bấm Lưu | H75: Tên tiền tệ: Tiền kiểm thử (đã sửa) | I75: - Hiện thông báo "Cập nhật thành công" - Danh sách hiện tên mới, cột Cập nhật đổi sang thời điểm vừa sửa | J75: - Hiện thông báo "Cập nhật thành công" - Danh sách hiện tên mới, cột Cập nhật đổi sang thời điểm vừa sửa | K75: Passed
C76: TC_04.008 | D76: Sửa Tỷ giá | E76: P0 | F76: Tài khoản có quyền Quản lý | G76: 1. Bấm Sửa dòng TST 2. Đổi Tỷ giá 3. Bấm Lưu | H76: Tỷ giá: 9.876,54 | I76: - Cập nhật thành công - Cột Tỷ giá hiện 9.876,54 | J76: - Cập nhật thành công - Cột Tỷ giá hiện 9.876,54 | K76: Passed
C77: TC_04.009 | D77: Trùng Mã tiền tệ | E77: P0 | F77: Đã có USD | G77: 1. Bấm tạo mới 2. Nhập mã tiền tệ = USD 3. Nhập các thông tin còn lại 4. Bấm Lưu | I77: - Không cho lưu - Hiển thị thông báo "Mã tiền tệ đã tồn tại" ngay dưới mã tiền tệ | J77: - Không cho lưu - Hiển thị thông báo "Mã tiền tệ đã tồn tại" ngay dưới mã tiền tệ | K77: Passed
C78: TC_04.010 | D78: Khóa tiền tệ | E78: P0 | F78: Có tiền tệ Hoạt động không được sử dụng ở nghiệp vụ khác | G78: 1. Tìm tiền tệ JPY 2. Bấm Khóa tại cột Trạng thái 3. Xác nhận nếu có popup | I78: - JPY chuyển trạng thái Khóa - Nút Khóa chuyển thành Mở khóa | J78: - JPY chuyển trạng thái Khóa - Nút Khóa chuyển thành Mở khóa | K78: Passed
C79: TC_04.011 | D79: Sửa Mã tiền tệ sang mã chưa tồn tại | E79: P1 | F79: Tài khoản có quyền Quản lý | G79: 1. Bấm Sửa dòng TST 2. Đổi Mã tiền tệ thành TSX 3. Bấm Lưu | H79: Mã tiền tệ: TSX | I79: - Cập nhật thành công, danh sách hiện mã TSX | J79: - Cập nhật thành công, danh sách hiện mã TSX | K79: Passed
C80: TC_04.012 | D80: Xóa trắng Tên gọi khác đang có | E80: P1 | F80: Tài khoản có quyền Quản lý | G80: 1. Bấm Sửa dòng có Tên gọi khác 2. Xóa trắng ô Tên gọi khác 3. Bấm Lưu | H80: Tên gọi khác: (để trống) | I80: - Cập nhật thành công - Dòng đó không còn dòng phụ Tên gọi khác trong danh sách | J80: - Cập nhật thành công - Dòng đó không còn dòng phụ Tên gọi khác trong danh sách | K80: Passed
C81: TC_04.013 | D81: Nút Xem mở ở chế độ chỉ đọc | E81: P0 | F81: Tài khoản có quyền Quản lý | G81: 1. Bấm nút Xem (hình con mắt) trên dòng USD | H81: — | I81: - Tiêu đề cửa sổ là "Xem tiền tệ" - Mọi ô đều mờ, không gõ được, không chọn được - KHÔNG có nút Lưu; chỉ có nút Đóng | J81: - Tiêu đề cửa sổ là "Xem tiền tệ" - Mọi ô đều mờ, không gõ được, không chọn được - KHÔNG có nút Lưu; chỉ có nút Đóng | K81: Passed
C82: TC_04.014 | D82: Người chỉ có quyền Xem vẫn mở được cửa sổ Xem | E82: P1 | F82: Đăng nhập bằng tài khoản chỉ có quyền "Xem danh mục tiền tệ". | G82: 1. Bấm nút Xem trên một dòng bất kỳ | H82: — | I82: - Cửa sổ Xem tiền tệ mở bình thường, hiện đủ thông tin, không có nút Lưu | J82: - Cửa sổ Xem tiền tệ mở bình thường, hiện đủ thông tin, không có nút Lưu | K82: Passed
C83: TC_04.015 | D83: Bấm Đóng khi chưa sửa gì | E83: P1 | F83: Đăng nhập bằng tài khoản chỉ có quyền "Xem danh mục tiền tệ". | G83: 1. Bấm Sửa một dòng 2. Không thay đổi gì 3. Bấm Đóng | H83: — | I83: - Cửa sổ đóng ngay, KHÔNG hỏi lại - Danh sách giữ nguyên | J83: - Cửa sổ đóng ngay, KHÔNG hỏi lại - Danh sách giữ nguyên | K83: Passed
C84: TC_04.016 | D84: Cảnh báo khi đóng lúc đang sửa dở | E84: P0 | F84: Đăng nhập bằng tài khoản chỉ có quyền "Xem danh mục tiền tệ". | G84: 1. Bấm Sửa một dòng 2. Sửa Tên tiền tệ nhưng chưa bấm Lưu 3. Bấm Đóng | H84: Tên tiền tệ: sửa dở dang | I84: - Hệ thống cảnh báo dữ liệu chưa được lưu và hỏi xác nhận trước khi đóng - Chọn ở lại thì cửa sổ vẫn mở và giữ nguyên nội dung đang gõ - Chọn thoát thì cửa sổ đóng và dữ liệu cũ không bị đổi | J84: - Hệ thống cảnh báo dữ liệu chưa được lưu và hỏi xác nhận trước khi đóng - Chọn ở lại thì cửa sổ vẫn mở và giữ nguyên nội dung đang gõ - Chọn thoát thì cửa sổ đóng và dữ liệu cũ không bị đổi | K84: Passed
C85: TC_04.017 | D85: Đóng cửa sổ bằng dấu X góc phải | E85: P1 | F85: Đăng nhập bằng tài khoản chỉ có quyền "Xem danh mục tiền tệ". | G85: 1. Bấm Tạo mới 2. Nhập vài ô 3. Bấm dấu X ở góc trên bên phải cửa sổ | H85: Mã: ABC | I85: - Hành xử giống nút Đóng: có cảnh báo chưa lưu | J85: - Hành xử giống nút Đóng: có cảnh báo chưa lưu | K85: Passed
C86: TC_04.018 | D86: Chống bấm Lưu nhiều lần liên tiếp | E86: P1 | F86: Đăng nhập bằng tài khoản chỉ có quyền "Xem danh mục tiền tệ". | G86: 1. Bấm Tạo mới, nhập đủ thông tin 2. Bấm Lưu liên tiếp 3 lần thật nhanh | H86: Mã: TS9; Tên: Tiền thử 9; Tỷ giá: 10,00 | I86: - Chỉ tạo ra ĐÚNG 1 bản ghi TS9 - Nút Lưu bị vô hiệu trong lúc đang xử lý | J86: - Chỉ tạo ra ĐÚNG 1 bản ghi TS9 - Nút Lưu bị vô hiệu trong lúc đang xử lý | K86: Passed
C87: TC_04.019 | D87: Thêm mới rồi kiểm tra ở cổng cũ | E87: P2 | F87: Đăng nhập bằng tài khoản chỉ có quyền "Xem danh mục tiền tệ". | G87: 1. Thêm mới tiền tệ TST ở màn này 2. Mở màn Danh mục tiền tệ ở cổng cũ | H87: Mã: TST | I87: - Tiền tệ TST cũng hiện ở cổng cũ với đúng mã, tên, tỷ giá Hai cổng dùng chung một danh mục — sai lệch giữa hai bên là lỗi | J87: - Tiền tệ TST cũng hiện ở cổng cũ với đúng mã, tên, tỷ giá Hai cổng dùng chung một danh mục — sai lệch giữa hai bên là lỗi | K87: Passed
C88: V. KHÓA & MỞ KHÓA
A89: Danh mục tiền tệ | B89: KHÓA & MỞ KHÓA | C89: TC_05.001 | D89: Khóa một tiền tệ đang Hoạt động | E89: P0 | F89: Đăng nhập TK "Quản lý". Có 1 tiền tệ đang ở trạng thái Hoạt động (VD: TST) | G89: 1. Bấm nút Khóa (hình ổ khóa) ở cột Trạng thái của dòng TST 2. Đọc nội dung hộp xác nhận 3. Bấm Khóa | H89: Tiền tệ: TST | I89: - Hộp xác nhận có tiêu đề "Xác nhận khóa" và câu hỏi nêu đúng tên tiền tệ - Sau khi xác nhận: thông báo "Khóa thành công" - Dòng TST đổi nhãn sang Khóa, nút trong cột Trạng thái đổi thành hình ổ khóa mở | J89: - Hộp xác nhận có tiêu đề "Xác nhận khóa" và câu hỏi nêu đúng tên tiền tệ - Sau khi xác nhận: thông báo "Khóa thành công" - Dòng TST đổi nhãn sang Khóa, nút trong cột Trạng thái đổi thành hình ổ khóa mở | K89: Passed
C90: TC_05.002 | D90: Mở khóa một tiền tệ đang Khóa | E90: P0 | F90: Đăng nhập TK "Quản lý". Có 1 tiền tệ đang ở trạng thái Hoạt động (VD: TST) | G90: 1. Bấm nút Mở khóa ở cột Trạng thái dòng TST 2. Bấm Mở khóa trong hộp xác nhận | H90: Tiền tệ: TST | I90: - Hộp xác nhận có tiêu đề "Xác nhận mở khóa" - Thông báo "Mở khóa thành công" - Dòng TST quay lại nhãn Hoạt động | J90: - Hộp xác nhận có tiêu đề "Xác nhận mở khóa" - Thông báo "Mở khóa thành công" - Dòng TST quay lại nhãn Hoạt động | K90: Passed
C91: TC_05.003 | D91: Hủy hộp xác nhận khóa | E91: P1 | F91: Đăng nhập TK "Quản lý". Có 1 tiền tệ đang ở trạng thái Hoạt động (VD: TST) | G91: 1. Bấm nút Khóa trên dòng TST 2. Bấm Hủy | H91: Tiền tệ: TST | I91: - Hộp đóng lại, trạng thái TST KHÔNG đổi - Không có thông báo thành công nào | J91: - Hộp đóng lại, trạng thái TST KHÔNG đổi - Không có thông báo thành công nào | K91: Passed
C92: TC_05.004 | D92: Khóa tiền tệ đang được dùng ở chứng từ khác | E92: P1 | F92: Đăng nhập TK "Quản lý". Có 1 tiền tệ đang được dùng ở nhiều chứng từ (VD: USD). | G92: 1. Bấm nút Khóa trên dòng USD 2. Xác nhận | H92: Tiền tệ: USD | I92: - Khóa được bình thường (khóa chỉ ngăn dùng MỚI, không ảnh hưởng chứng từ đã lập) Khác với Xóa — Xóa mới bị chặn khi đang được dùng | J92: - Khóa được bình thường (khóa chỉ ngăn dùng MỚI, không ảnh hưởng chứng từ đã lập) Khác với Xóa — Xóa mới bị chặn khi đang được dùng | K92: Passed
C93: TC_05.005 | D93: Tiền tệ đã khóa không còn được chọn ở màn nghiệp vụ | E93: P0 | F93: Đăng nhập TK "Quản lý". Có 1 tiền tệ đang được dùng ở nhiều chứng từ (VD: TST) | G93: 1. Mở một màn có chọn tiền tệ (ví dụ lập báo giá) 2. Mở danh sách chọn tiền tệ | H93: Tiền tệ: TST | I93: - TST KHÔNG có trong danh sách chọn | J93: - TST KHÔNG có trong danh sách chọn | K93: Passed
C94: TC_05.006 | D94: Chứng từ cũ vẫn hiện đúng tiền tệ đã bị khóa | E94: P0 | F94: Có sẵn 1 báo giá cũ đã lập dùng tiền tệ USD. USD hiện đang ở trạng thái Khóa. | G94: 1. Khóa tiền tệ USD 2. Mở lại báo giá cũ ở chế độ Sửa | H94: Tiền tệ: USD (đang Khóa) | I94: - Ô tiền tệ của báo giá vẫn hiện đúng "USD", không bị trống, không tự nhảy sang tiền tệ khác - Lưu lại báo giá không làm mất giá trị tiền tệ Đây là quy tắc chung toàn hệ thống: danh mục bị khóa vẫn phải hiện ở bản ghi đang dùng nó | J94: - Ô tiền tệ của báo giá vẫn hiện đúng "USD", không bị trống, không tự nhảy sang tiền tệ khác - Lưu lại báo giá không làm mất giá trị tiền tệ Đây là quy tắc chung toàn hệ thống: danh mục bị khóa vẫn phải hiện ở bản ghi đang dùng nó | K94: Passed
C95: TC_05.007 | D95: Người chỉ có quyền Xem không thấy nút Khóa | E95: P0 | F95: Đăng nhập TK chỉ có quyền "Xem danh mục tiền tệ" | G95: 1. Mở màn hình 2. Nhìn cột Trạng thái | H95: — | I95: - Cột Trạng thái chỉ có nhãn trạng thái, không có nút Khóa / Mở khóa | J95: - Cột Trạng thái chỉ có nhãn trạng thái, không có nút Khóa / Mở khóa | K95: Passed
C96: TC_05.008 | D96: Khóa rồi lọc lại theo trạng thái | E96: P1 | F96: Đăng nhập TK "Quản lý". Có 1 tiền tệ đang ở trạng thái Hoạt động (VD: TST) | G96: 1. Khóa tiền tệ TST 2. Lọc Trạng thái = Hoạt động 3. Lọc lại Trạng thái = Khóa | H96: Tiền tệ: TST | I96: - Ở bước 2 không có TST trong kết quả - Ở bước 3 có TST trong kết quả | J96: - Ở bước 2 không có TST trong kết quả - Ở bước 3 có TST trong kết quả | K96: Passed
C97: VI. XÓA
A98: Danh mục tiền tệ | B98: XÓA | C98: TC_06.001 | D98: Xóa tiền tệ chưa dùng ở đâu | E98: P0 | F98: Đăng nhập TK "Quản lý". Có 1 tiền tệ chưa được dùng ở bất kỳ đâu (VD: TST). | G98: 1. Bấm nút Xóa trên dòng TST 2. Đọc hộp xác nhận 3. Bấm Xóa | H98: Tiền tệ: TST | I98: - Hộp xác nhận tiêu đề "Xác nhận xóa", câu hỏi nêu đúng tên tiền tệ - Thông báo "Xóa thành công" - Dòng TST biến mất, tổng dưới bảng giảm 1 | J98: - Hộp xác nhận tiêu đề "Xác nhận xóa", câu hỏi nêu đúng tên tiền tệ - Thông báo "Xóa thành công" - Dòng TST biến mất, tổng dưới bảng giảm 1 | K98: Passed
C99: TC_06.002 | D99: Hủy hộp xác nhận xóa | E99: P0 | F99: Đăng nhập TK "Quản lý". Có 1 tiền tệ chưa được dùng ở đâu (VD: TST). | G99: 1. Bấm nút Xóa trên dòng TST 2. Bấm Hủy | H99: Tiền tệ: TST | I99: - Hộp đóng, dòng TST vẫn còn nguyên | J99: - Hộp đóng, dòng TST vẫn còn nguyên | K99: Passed
C100: TC_06.003 | D100: Nút Xóa bị vô hiệu với tiền tệ đang được dùng | E100: P0 | F100: Đăng nhập TK "Quản lý". Có 1 tiền tệ đang được dùng ở chứng từ (VD: USD) | G100: 1. Mở màn hình, chờ bảng hiện xong khoảng 2 giây 2. Rê chuột vào nút Xóa của dòng USD | H100: Tiền tệ: USD | I100: - Nút Xóa bị mờ, không bấm được - Rê chuột hiện chú thích cho biết tiền tệ đang được sử dụng Trạng thái mờ xuất hiện chậm hơn bảng vài trăm mili giây — đó là thiết kế, không phải lỗi | J100: - Nút Xóa bị mờ, không bấm được - Rê chuột hiện chú thích cho biết tiền tệ đang được sử dụng Trạng thái mờ xuất hiện chậm hơn bảng vài trăm mili giây — đó là thiết kế, không phải lỗi | K100: Passed
...

Sheet 3. DM tài khoản
A1: MÔ TẢ TÍNH NĂNG (đọc trước khi xem testcase)
A2: 1. Mục đích tính năng | B2: Quản lý hệ thống tài khoản kế toán 3 bậc dùng chung cho toàn hệ thống (hạch toán chứng từ, sổ sách, báo cáo tài chính, theo dõi công nợ). Màn hình nằm ở phân hệ Tài chính → nhóm menu Danh mục → Danh mục tài khoản. Đây là màn được chuyển từ hệ thống cũ sang, hai cổng dùng CHUNG một danh mục tài khoản.
A3: 2. Đối tượng được tính / hiển thị | B3: - Toàn bộ tài khoản trong danh mục, KHÔNG phân theo công ty / phòng ban — ai có quyền vào màn thì thấy đủ như nhau. - Hiển thị cả tài khoản Hoạt động và tài khoản đang Khóa. - Mỗi dòng gồm 11 cột: STT, Cấp 1, Cấp 2, Cấp 3, Tên tài khoản, Loại tài khoản, Theo dõi công nợ, Ngày tạo, Cập nhật, Trạng thái, Hành động. - Số tài khoản được đặt vào đúng cột Cấp 1 / Cấp 2 / Cấp 3 theo bậc của nó, ba cột còn lại để trống — nhờ vậy nhìn vào bảng là thấy ngay cây tài khoản thụt lề theo bậc. - Cột Theo dõi công nợ chỉ hiện dấu đánh dấu ở những tài khoản có bật, tài khoản không bật thì để trống.
A4: 3. Đối tượng bị ẩn / không tính | B4: - Không có tài khoản nào bị ẩn khỏi màn này. - Tài khoản đang Khóa VẪN hiện ở đây nhưng KHÔNG còn được chọn khi hạch toán chứng từ mới. - Trong danh sách chọn Tài khoản mẹ ở màn thêm/sửa: chỉ hiện các tài khoản đúng bậc liền trên bậc đang chọn (bậc 2 chỉ chọn được mẹ bậc 1, bậc 3 chỉ chọn được mẹ bậc 2).
A5: 4. Bộ lọc thời gian áp dụng cho | B5: Không áp dụng. Màn hình không có ô lọc theo khoảng thời gian. Hai cột Ngày tạo và Cập nhật chỉ để xem, không phải điều kiện lọc.
A6: 5. Cấu trúc dữ liệu / cây phân cấp | B6: Cây 3 bậc, gắn kết theo SỐ tài khoản chứ không theo tên: - Bậc 1: số tài khoản 3 chữ số, KHÔNG có tài khoản mẹ. Ví dụ 131. - Bậc 2: có tài khoản mẹ là một tài khoản bậc 1. Ví dụ 1311 (mẹ là 131). - Bậc 3: có tài khoản mẹ là một tài khoản bậc2. Ví dụ 13111 (mẹ là 1311). Ba quy tắc bắt buộc của cây: a) Tài khoản mẹ phải đúng bậc liền trên. b) Số tài khoản con phải BẮT ĐẦU BẰNG số tài khoản mẹ. c) Tài khoản đang có tài khoản con thì KHÔNG được đổi Bậc và KHÔNG được đổi Số tài khoản.
A7: 6. Quy tắc cộng dồn / deduplicate | B7: Không cộng dồn. Mỗi tài khoản là một dòng độc lập. Chống trùng: Số tài khoản là duy nhất trong toàn danh mục; trùng sẽ báo "Số tài khoản đã tồn tại". Tên tài khoản KHÔNG bắt buộc duy nhất — được phép trùng.
A8: 7. Phân quyền cấp | B8: Hai quyền dành riêng cho màn này: - "Xem danh mục tài khoản": vào màn hình, xem danh sách, mở xem chi tiết, xem lịch sử chỉnh sửa, in danh sách, xuất Excel. - "Quản lý danh mục tài khoản": thêm mới, sửa, khóa, mở khóa, xóa, nhập từ Excel. Không có quyền nào trong hai quyền trên thì không vào được màn hình. Danh mục KHÔNG phân quyền theo công ty / phòng ban / bộ phận. Ngoài quyền, còn một ràng buộc riêng: các thao tác Khóa, Mở khóa và Xóa chỉ dành cho CHÍNH NGƯỜI ĐÃ TẠO tài khoản đó. Người khác dù có quyền Quản lý cũng không thao tác được.
A9: 8. Cách tính các ô thống kê | B9: - Dòng "Hiển thị a- b / N" dưới bảng: a là dòng đầu của trang đang xem, b là dòng cuối, N là tổng số tài khoản khớp bộ lọc hiện tại. - Cột STT đánh theo trang: trang 2 với cỡ trang 10 thì bắt đầu từ 11. - Bản in danh sách lấy đúng tập dữ liệu đang lọc, không phải toàn bộ danh mục. - Bảng nhập từ Excel: số dòng hợp lệ và số dòng lỗi được đếm riêng.
A10: 9. Ghi chú đọc bảng | B10: - Số tài khoản chỉ được nhập CHỮ SỐ, từ 3 đến 15 chữ số. Chữ cái, dấu chấm, dấu gạch đều bị chặn. - Cột Cấp 1 / Cấp 2 / Cấp 3 KHÔNG phải ba số khác nhau — chỉ là một số tài khoản được đặt vào đúng cột theo bậc. Đọc nhầm thành ba giá trị là sai. - Nút Khóa / Mở khóa nằm NGAY TRONG cột Trạng thái, không nằm ở cột Hành động. - Tài khoản đang ở trạng thái Khóa thì nút Sửa bị vô hiệu; muốn sửa phải Mở khóa trước. - Người không phải người tạo sẽ thấy nút Khóa / Mở khóa / Xóa bị mờ, dù có quyền Quản lý. Đây là thiết kế, không phải lỗi. - Bộ lọc được hệ thống ghi nhớ trong 10 phút. Kiểm thử bộ lọc nên bấm Làm mới trước mỗi kịch bản. - Thêm mới và Sửa mở ra TRANG RIÊNG, không phải cửa sổ nhỏ như các danh mục khác. - Mọi thay đổi đều xem lại được qua nút Lịch sử chỉnh sửa trên từng dòng.
A11: Testcase _ Danh mục tài khoản- Cập nhật ngày 14/08/2026 | F11: TEST SUMMARY | I11: Số TH DNS kiểm thử đạt (P): | K11: =COUNTIF(K18:M997,"Passed") | M11: Số trường hợp TP kiểm thử đạt (P): | P11: =COUNTIF(O18:Q200,"Passed")
I12: Số TH DNS kiểm thử không đạt (F) | K12: =COUNTIF(K18:M997,"Failed") | M12: Số trường hợp TP kiểm thử không đạt (F) | P12: =COUNTIF(O19:Q201,"Fail")
I13: Số TH DNS kiểm thử đang xem xét (PE) | K13: =COUNTIF(K18:M997,"Pending") | M13: Số trường hợp TP kiểm thử đang xem xét (PE) | P13: =COUNTIF(O20:Q202,"Pending")
I14: Số TH DNS kiểm thử chưa thực hiện | K14: =COUNTIF(K18:K997,"Not Executed") | M14: Số trường hợp TP kiểm thử chưa thực hiện | P14: =K16-P15
I15: Tổng số TH DNS đã kiểm thử | K15: =sum(K11:K14) | M15: Tổng số trường hợp TP kiểm thử | P15: =sum(P11:Q13)
I16: Tổng số testcase | K16: =COUNTIF(I18:I1017,"*")
A17: Module | B17: Nhóm chức năng | C17: TC ID | D17: Chức năng | E17: Priority | F17: Tiền điều kiện | G17: Bước thực hiện | H17: Test Data | I17: Expected Result (chi tiết) | J17: KQ thực tế | K17: DNS check lần 1 | L17: DNS check lần 2 | M17: DNS check lần 3 | N17: Ghi chú | O17: TP check lần 1 | P17: TP check lần 2 | Q17: TP check lần 3
C18: Phân quyền & truy cập
A19: Danh mục tài khoản | B19: Phân quyền & truy cập | C19: TC-ROLE-01 | D19: Vào màn hình khi chỉ có quyền Xem | E19: P0 | F19: Đăng nhập User A (chỉ có quyền Xem). | G19: 1. Đăng nhập bằng tài khoản A 2. Vào phân hệ Tài chính → Danh mục → Danh mục tài khoản | H19: Tài khoản A | I19: - Vào được màn hình, bảng hiển thị dữ liệu - KHÔNG có nút Tạo mới, KHÔNG có nút Import Excel - Trên mỗi dòng chỉ còn nút Lịch sử chỉnh sửa; KHÔNG có nút Sửa, nút Xóa - Cột Trạng thái không có nút Khóa / Mở khóa - Vẫn có nút In danh sách và nút Xuất Excel | K19: Passed
C20: TC-ROLE-02 | D20: Vào màn hình khi có quyền Quản lý | E20: P0 | F20: Đăng nhập User B (quyền Quản lý). | G20: 1. Đăng nhập bằng tài khoản B 2. Vào Danh mục tài khoản | H20: Tài khoản B | I20: - Có đủ 4 nút dưới bảng: Tạo mới, In danh sách, Xuất Excel, Import Excel - Mỗi dòng có đủ 3 nút: Sửa, Lịch sử chỉnh sửa, Xóa - Cột Trạng thái có nút Khóa hoặc Mở khóa | K20: Passed
C21: TC-ROLE-03 | D21: Chặn vào màn hình khi không có quyền nào | E21: P0 | F21: Đăng nhập User D (không có quyền). | G21: 1. Đăng nhập bằng tài khoản D 2. Tìm mục Danh mục tài khoản trong phân hệ Tài chính 3. Dán thẳng đường dẫn màn hình vào thanh địa chỉ | H21: Tài khoản D | I21: - Mục menu KHÔNG hiện - Dán thẳng đường dẫn thì hệ thống chuyển sang trang báo không tìm thấy, không lộ dữ liệu | K21: Passed
C22: TC-ROLE-04 | D22: Chặn vào trang Thêm mới khi chỉ có quyền Xem | E22: P0 | F22: Đăng nhập User A. | G22: 1. Đăng nhập bằng tài khoản A 2. Dán thẳng đường dẫn trang Thêm tài khoản vào thanh địa chỉ | H22: Tài khoản A | I22: - Hệ thống không cho vào trang thêm mới, chuyển sang trang báo không tìm thấy hoặc quay về danh sách kèm thông báo không có quyền | K22: Passed
C23: TC-ROLE-05 | D23: Chặn Thêm mới khi bỏ qua giao diện | E23: P0 | F23: Đăng nhập User A. | G23: 1. Đăng nhập bằng tài khoản A, lấy mã đăng nhập 2. Dùng công cụ kiểm thử API gọi thẳng chức năng Thêm tài khoản, bỏ qua giao diện 3. Mở lại màn hình kiểm tra | H23: Số tài khoản: 998; Tên: Tài khoản thử; Bậc 1 | I23: - Hệ thống từ chối, báo không có quyền - Không xuất hiện tài khoản 998 | K23: Passed
C24: TC-ROLE-06 | D24: Chặn Sửa khi bỏ qua giao diện | E24: P0 | F24: Đăng nhập User A. | G24: 1. Đăng nhập bằng tài khoản A 2. Dùng công cụ kiểm thử API gọi thẳng chức năng Sửa tài khoản 999 3. Mở lại màn hình | H24: Đổi tên thành "Bị sửa trộm" | I24: - Hệ thống từ chối, báo không có quyền - Tên cũ giữ nguyên | K24: Passed
C25: TC-ROLE-07 | D25: Chặn Xóa khi bỏ qua giao diện | E25: P0 | F25: Đăng nhập User A. | G25: 1. Đăng nhập bằng tài khoản A 2. Dùng công cụ kiểm thử API gọi thẳng chức năng Xóa tài khoản 999 3. Mở lại màn hình | H25: Tài khoản 999 (về nghiệp vụ là xóa được) | I25: - Hệ thống từ chối, báo không có quyền - Tài khoản 999 vẫn còn | K25: Passed
C26: TC-ROLE-08 | D26: Chặn Xóa của người có quyền nhưng không phải người tạo | E26: P0 | F26: Đăng nhập User C (không tạo tài khoản 999). | G26: 1. Đăng nhập bằng tài khoản C (có quyền Quản lý, KHÔNG phải người tạo 999) 2. Dùng công cụ kiểm thử API gọi thẳng chức năng Xóa tài khoản 999 3. Mở lại màn hình | H26: Tài khoản C xóa tài khoản 999 của người khác | I26: - Hệ thống từ chối - Tài khoản 999 vẫn còn Đây là ràng buộc riêng của màn này: chỉ chính người tạo mới được xóa | K26: Passed
C27: TC-ROLE-09 | D27: Chặn Khóa của người có quyền nhưng không phải người tạo | E27: P0 | F27: Đăng nhập User C (không tạo tài khoản 999). | G27: 1. Đăng nhập bằng tài khoản C 2. Mở màn hình, rê chuột vào nút Khóa của dòng 999 3. Dùng công cụ kiểm thử API gọi thẳng chức năng Khóa tài khoản 999 | H27: Tài khoản C | I27: - Trên giao diện nút Khóa bị mờ - Gọi thẳng cũng bị từ chối, trạng thái tài khoản 999 không đổi | K27: Passed
C28: TC-ROLE-10 | D28: Chặn Import Excel khi bỏ qua giao diện | E28: P1 | F28: Đăng nhập User A. | G28: 1. Đăng nhập bằng tài khoản A 2. Dùng công cụ kiểm thử API gọi thẳng chức năng Nhập tài khoản từ Excel 3. Mở lại màn hình | H28: File Excel 3 dòng hợp lệ | I28: - Hệ thống từ chối, báo không có quyền - Danh sách không tăng thêm dòng nào | K28: Passed
C29: TC-ROLE-11 | D29: Người chỉ có quyền Xem vẫn in và xuất Excel được | E29: P1 | F29: Đăng nhập User A. | G29: 1. Đăng nhập bằng tài khoản A 2. Bấm In danh sách 3. Bấm Xuất Excel | H29: Tài khoản A | I29: - Cả hai chức năng đều dùng được bình thường | K29: Passed
C30: TC-ROLE-12 | D30: Kiểm tra mở chức năng Cấu hình cột hiển thị | E30: P1 | F30: Người dùng có quyền truy cập màn Danh mục tài khoản | G30: 1. Vào màn Danh mục tài khoản. 2. Bấm Cấu hình cột hiển thị. | H30: - | I30: Popup Cấu hình cột hiển thị được mở. Hiển thị đầy đủ các cột được phép cấu hình theo nghiệp vụ. | K30: Passed
C31: TC-ROLE-13 | D31: Kiểm tra trạng thái mặc định của các cột | F31: Đã mở popup Cấu hình cột hiển thị | G31: 1. Quan sát danh sách các cột trong popup. | H31: - | I31: Các cột mặc định được chọn đúng theo cấu hình mặc định của màn Danh mục tài khoản. Các cột không mặc định được bỏ chọn. | K31: Passed
C32: I. HIỂN THỊ TRANG & TRUY CẬP
A33: Danh mục tài khoản | B33: HIỂN THỊ TRANG & TRUY CẬP | C33: TC_01.001 | D33: Mở màn hình lần đầu | E33: P0 | F33: Đăng nhập TK "Quản lý". Đang ở màn hình khác. | G33: 1. Vào phân hệ Tài chính → Danh mục → Danh mục tài khoản 2. Quan sát toàn màn hình | I33: - Tiêu đề trang và tiêu đề bảng đều là "Danh mục tài khoản" - Khối lọc có tiêu đề "Bộ lọc danh mục tài khoản", mặc định thu gọn - Bảng có đủ 11 cột đúng thứ tự: STT, Cấp 1, Cấp 2, Cấp 3, Tên tài khoản, Loại tài khoản, Theo dõi công nợ, Ngày tạo, Cập nhật, Trạng thái, Hành động - Dưới bảng có 4 nút: Tạo mới, In danh sách, Xuất Excel, Import Excel | J33: - Tiêu đề trang và tiêu đề bảng đều là "Danh mục tài khoản" - Khối lọc có tiêu đề "Bộ lọc danh mục tài khoản", mặc định thu gọn - Bảng có đủ 11 cột đúng thứ tự: STT, Cấp 1, Cấp 2, Cấp 3, Tên tài khoản, Loại tài khoản, Theo dõi công nợ, Ngày tạo, Cập nhật, Trạng thái, Hành động - Dưới bảng có 4 nút: Tạo mới, In danh sách, Xuất Excel, Import Excel | K33: Passed
C34: TC_01.002 | D34: Số tài khoản nằm đúng cột theo bậc | E34: P0 | F34: Đăng nhập TK "Quản lý". Đang ở màn Danh mục. | G34: 1. Mở màn hình 2. Tìm ba dòng 131, 1311, 13111 và nhìn 3 cột Cấp | I34: - Dòng 131 chỉ điền cột Cấp 1, hai cột Cấp 2 và Cấp 3 để trống - Dòng 1311 chỉ điền cột Cấp 2 - Dòng 13111 chỉ điền cột Cấp 3 Nhìn ngang là thấy cây thụt lề theo bậc; số chỉ xuất hiện MỘT lần trên mỗi dòng | J34: - Dòng 131 chỉ điền cột Cấp 1, hai cột Cấp 2 và Cấp 3 để trống - Dòng 1311 chỉ điền cột Cấp 2 - Dòng 13111 chỉ điền cột Cấp 3 Nhìn ngang là thấy cây thụt lề theo bậc; số chỉ xuất hiện MỘT lần trên mỗi dòng | K34: Passed
C35: TC_01.003 | D35: Cột Theo dõi công nợ | E35: P1 | F35: Đăng nhập TK "Quản lý". Đang ở màn Danh mục. | G35: 1. Mở màn hình 2. So sánh dòng có bật và dòng không bật theo dõi công nợ | I35: - Dòng có bật hiện dấu đánh dấu, rê chuột hiện chú thích "Có theo dõi công nợ" - Dòng không bật để trống, không hiện dấu gạch hay chữ "Không" | J35: - Dòng có bật hiện dấu đánh dấu, rê chuột hiện chú thích "Có theo dõi công nợ" - Dòng không bật để trống, không hiện dấu gạch hay chữ "Không" | K35: Passed
C36: TC_01.004 | D36: Cột Loại tài khoản hiện tên loại | E36: P0 | F36: Đăng nhập TK "Quản lý". Đang ở màn Danh mục. | G36: 1. Mở màn hình 2. Nhìn cột Loại tài khoản | I36: - Hiện TÊN loại tài khoản bằng tiếng Việt (ví dụ "Tài khoản tài sản"), không hiện con số - Tài khoản chưa gán loại thì để trống, không lỗi | J36: - Hiện TÊN loại tài khoản bằng tiếng Việt (ví dụ "Tài khoản tài sản"), không hiện con số - Tài khoản chưa gán loại thì để trống, không lỗi | K36: Passed
C37: TC_01.005 | D37: Cột Ngày tạo và Cập nhật | E37: P1 | F37: Đăng nhập TK "Quản lý". Đang ở màn Danh mục. | G37: 1. Mở màn hình 2. Nhìn hai cột Ngày tạo và Cập nhật | I37: - Ngày tạo hiện thời điểm tạo kèm tên người tạo - Cập nhật hiện thời điểm sửa gần nhất kèm tên người cập nhật | J37: - Ngày tạo hiện thời điểm tạo kèm tên người tạo - Cập nhật hiện thời điểm sửa gần nhất kèm tên người cập nhật | K37: Passed
C38: TC_01.006 | D38: Cột Trạng thái hiển thị đúng nhãn | E38: P0 | F38: Đăng nhập TK "Quản lý". Đang ở màn Danh mục. | G38: 1. Mở màn hình 2. Đối chiếu cột Trạng thái | I38: - Tài khoản đang dùng hiện nhãn "Hoạt động" - Tài khoản bị khóa hiện nhãn "Khóa" | J38: - Tài khoản đang dùng hiện nhãn "Hoạt động" - Tài khoản bị khóa hiện nhãn "Khóa" | K38: Passed
C39: TC_01.007 | D39: Vị trí nút Khóa / Mở khóa | E39: P1 | F39: Đăng nhập TK "Quản lý". Đang ở màn Danh mục. | G39: 1. Mở màn hình 2. Nhìn cột Trạng thái và cột Hành động | I39: - Nút Khóa / Mở khóa nằm cạnh nhãn trạng thái, TRONG cột Trạng thái - Cột Hành động có 3 nút: Sửa, Lịch sử chỉnh sửa, Xóa Màn này KHÁC các danh mục khác: KHÔNG có nút Xem riêng, muốn xem chi tiết thì mở trang Sửa | J39: - Nút Khóa / Mở khóa nằm cạnh nhãn trạng thái, TRONG cột Trạng thái - Cột Hành động có 3 nút: Sửa, Lịch sử chỉnh sửa, Xóa Màn này KHÁC các danh mục khác: KHÔNG có nút Xem riêng, muốn xem chi tiết thì mở trang Sửa | K39: Passed
C40: TC_01.008 | D40: Tên tài khoản dài được xuống dòng | E40: P2 | F40: Đăng nhập TK "Quản lý". Đang ở màn Danh mục. | G40: 1. Tìm dòng có Tên tài khoản dài (ví dụ "Phải thu của khách hàng ngắn hạn") | I40: - Tên được xuống dòng trong ô, hiện đầy đủ, không cắt cụt, không tràn bảng | J40: - Tên được xuống dòng trong ô, hiện đầy đủ, không cắt cụt, không tràn bảng | K40: Passed
C41: TC_01.009 | D41: Bảng trống khi bộ lọc không khớp gì | E41: P1 | F41: Đăng nhập TK "Quản lý". Đang ở màn Danh mục. | G41: 1. Gõ "khongtontai123" vào ô tìm nhanh 2. Bấm Tìm kiếm | H41: khongtontai123 | I41: - Bảng hiện thông báo không có dữ liệu phù hợp, tổng dưới bảng là 0 | J41: - Bảng hiện thông báo không có dữ liệu phù hợp, tổng dưới bảng là 0 | K41: Passed
C42: TC_01.010 | D42: Màn hình mở nhanh với 308 bản ghi | E42: P1 | F42: Đăng nhập TK "Quản lý". Đang ở màn hình khác. | G42: 1. Mở màn hình và bấm giờ đến khi bảng hiện xong | I42: - Bảng hiện trong vòng vài giây, không treo trang - Danh sách chỉ tải MỘT lượt, không chớp tải hai lần | J42: - Bảng hiện trong vòng vài giây, không treo trang - Danh sách chỉ tải MỘT lượt, không chớp tải hai lần | K42: Passed
C43: TC_01.011 | D43: Kiểm tra trạng thái mặc định của các cột | E43: P1 | F43: Đã mở popup Cấu hình cột hiển thị | G43: 1. Quan sát danh sách các cột trong popup. | I43: Các cột mặc định được chọn đúng theo cấu hình mặc định của màn Danh mục tài khoản. Các cột không mặc định được bỏ chọn. | J43: Các cột mặc định được chọn đúng theo cấu hình mặc định của màn Danh mục tài khoản. Các cột không mặc định được bỏ chọn. | K43: Passed
C44: TC_01.012 | D44: Bỏ chọn một cột đang hiển thị | E44: P1 | F44: Popup Cấu hình cột hiển thị đang mở; cột đang được chọn | G44: 1. Bỏ chọn một cột đang hiển thị, ví dụ Tên tài khoản. 2. Bấm Lưu. 3. Quan sát bảng dữ liệu. | I44: Cột Tên tài khoản không còn hiển thị trên bảng. Các cột còn lại vẫn hiển thị bình thường. | J44: Cột Tên tài khoản không còn hiển thị trên bảng. Các cột còn lại vẫn hiển thị bình thường. | K44: Passed
C45: II. BỘ LỌC & TÌM KIẾM
A46: Danh mục tài khoản | B46: BỘ LỌC & TÌM KIẾM | C46: TC_02.001 | D46: Tìm nhanh theo Số tài khoản | E46: P0 | F46: Đăng nhập TK "Quản lý". | G46: 1. Gõ "1311" vào ô tìm nhanh 2. Bấm Tìm kiếm | H46: 1311 | I46: - Kết quả gồm các tài khoản có số chứa 1311 Gợi ý trong ô ghi rõ: "Tìm theo số hoặc tên tài khoản..." | J46: - Kết quả gồm các tài khoản có số chứa 1311 Gợi ý trong ô ghi rõ: "Tìm theo số hoặc tên tài khoản..." | K46: Passed
C47: TC_02.002 | D47: Tìm nhanh theo Tên tài khoản | E47: P0 | F47: Đăng nhập TK "Quản lý". | G47: 1. Gõ "phải thu" vào ô tìm nhanh 2. Bấm Tìm kiếm | H47: phải thu | I47: - Kết quả gồm mọi tài khoản có chuỗi "phải thu" trong tên | J47: - Kết quả gồm mọi tài khoản có chuỗi "phải thu" trong tên | K47: Passed
C48: TC_02.003 | D48: Tìm nhanh khớp phần GIỮA của tên | E48: P0 | F48: Đăng nhập TK "Quản lý". | G48: 1. Gõ một cụm nằm ở GIỮA tên tài khoản (ví dụ "khách hàng") 2. Bấm Tìm kiếm | H48: khách hàng | I48: - Tài khoản "Phải thu của khách hàng ngắn hạn" vẫn ra kết quả Đây là lỗi cũ của hệ thống trước đây: chỉ tìm được khi gõ đúng phần ĐUÔI của tên. Bắt buộc phải kiểm TH này | J48: - Tài khoản "Phải thu của khách hàng ngắn hạn" vẫn ra kết quả Đây là lỗi cũ của hệ thống trước đây: chỉ tìm được khi gõ đúng phần ĐUÔI của tên. Bắt buộc phải kiểm TH này | K48: Passed
C49: TC_02.004 | D49: Tìm nhanh không phân biệt hoa thường | E49: P1 | F49: Đăng nhập TK "Quản lý". | G49: 1. Gõ "PHẢI THU" bằng chữ hoa 2. Bấm Tìm kiếm | H49: PHẢI THU | I49: - Kết quả giống hệt khi gõ chữ thường | J49: - Kết quả giống hệt khi gõ chữ thường | K49: Passed
C50: TC_02.005 | D50: Gõ ô tìm nhanh mà chưa bấm Tìm kiếm | E50: P1 | F50: Đăng nhập TK "Quản lý". | G50: 1. Gõ từ khóa 2. Chờ 5 giây, không bấm gì | H50: 1311 | I50: - Bảng vẫn giữ nguyên, chưa lọc | J50: - Bảng vẫn giữ nguyên, chưa lọc | K50: Passed
C51: TC_02.006 | D51: Lọc theo Bậc tài khoản | E51: P0 | F51: Đăng nhập TK "Quản lý". | G51: 1. Mở bộ lọc nâng cao 2. Chọn Bậc tài khoản = 1 3. Bấm Tìm kiếm | H51: Bậc: 1 | I51: - Kết quả chỉ còn tài khoản bậc 1 - Mọi dòng chỉ điền cột Cấp 1, hai cột Cấp 2 và Cấp 3 đều trống | J51: - Kết quả chỉ còn tài khoản bậc 1 - Mọi dòng chỉ điền cột Cấp 1, hai cột Cấp 2 và Cấp 3 đều trống | K51: Passed
C52: TC_02.007 | D52: Lọc theo Bậc tài khoản bậc 3 | E52: P1 | F52: Đăng nhập TK "Quản lý". | G52: 1. Chọn Bậc tài khoản = 3 2. Bấm Tìm kiếm | H52: Bậc: 3 | I52: - Kết quả chỉ còn tài khoản bậc 3, mọi dòng chỉ điền cột Cấp 3 | J52: - Kết quả chỉ còn tài khoản bậc 3, mọi dòng chỉ điền cột Cấp 3 | K52: Passed
C53: TC_02.008 | D53: Lọc theo Loại tài khoản | E53: P0 | F53: Đăng nhập TK "Quản lý". | G53: 1. Chọn một giá trị trong ô Loại tài khoản 2. Bấm Tìm kiếm | H53: Loại: Tài khoản tài sản | I53: - Kết quả chỉ còn tài khoản thuộc loại đã chọn - Cột Loại tài khoản của mọi dòng đều hiện đúng loại vừa chọn | J53: - Kết quả chỉ còn tài khoản thuộc loại đã chọn - Cột Loại tài khoản của mọi dòng đều hiện đúng loại vừa chọn | K53: Passed
C54: TC_02.009 | D54: Lọc theo Theo dõi công nợ | E54: P0 | F54: Đăng nhập TK "Quản lý". | G54: 1. Chọn Theo dõi công nợ = Có 2. Bấm Tìm kiếm | H54: Theo dõi công nợ: Có | I54: - Kết quả chỉ còn các tài khoản có dấu đánh dấu ở cột Theo dõi công nợ | J54: - Kết quả chỉ còn các tài khoản có dấu đánh dấu ở cột Theo dõi công nợ | K54: Passed
C55: TC_02.010 | D55: Lọc theo Theo dõi công nợ = Không | E55: P1 | F55: Đăng nhập TK "Quản lý". | G55: 1. Chọn Theo dõi công nợ = Không 2. Bấm Tìm kiếm | H55: Theo dõi công nợ: Không | I55: - Kết quả chỉ còn các tài khoản để trống cột Theo dõi công nợ | J55: - Kết quả chỉ còn các tài khoản để trống cột Theo dõi công nợ | K55: Passed
C56: TC_02.011 | D56: Lọc theo Trạng thái | E56: P0 | F56: Đăng nhập TK "Quản lý". | G56: 1. Chọn Trạng thái = Khóa 2. Bấm Tìm kiếm 3. Chọn lại Trạng thái = Hoạt động | H56: Trạng thái: Khóa rồi Hoạt động | I56: - Mỗi lần lọc, mọi dòng đều mang đúng nhãn trạng thái đã chọn | J56: - Mỗi lần lọc, mọi dòng đều mang đúng nhãn trạng thái đã chọn | K56: Passed
C57: TC_02.012 | D57: Lọc theo Người tạo | E57: P0 | F57: Đăng nhập TK "Quản lý". | G57: 1. Chọn một người trong ô Người tạo 2. Bấm Tìm kiếm | H57: Người tạo: một nhân viên | I57: - Kết quả chỉ còn tài khoản do người đó tạo - Danh sách chọn chỉ liệt kê người thực sự đã tạo bản ghi, không liệt kê toàn bộ nhân viên | J57: - Kết quả chỉ còn tài khoản do người đó tạo - Danh sách chọn chỉ liệt kê người thực sự đã tạo bản ghi, không liệt kê toàn bộ nhân viên | K57: Passed
C58: TC_02.013 | D58: Lọc theo Người cập nhật | E58: P0 | F58: Đăng nhập TK "Quản lý". | G58: 1. Chọn một người trong ô Người cập nhật 2. Bấm Tìm kiếm | H58: Người cập nhật: một nhân viên | I58: - Kết quả chỉ còn tài khoản do người đó cập nhật gần nhất | J58: - Kết quả chỉ còn tài khoản do người đó cập nhật gần nhất | K58: Passed
C59: TC_02.014 | D59: Kết hợp nhiều điều kiện lọc | E59: P0 | F59: Đăng nhập TK "Quản lý". | G59: 1. Chọn Bậc = 2, Trạng thái = Hoạt động, Theo dõi công nợ = Có 2. Bấm Tìm kiếm | H59: Bậc 2 + Hoạt động + Có theo dõi công nợ | I59: - Kết quả phải thỏa mãn cả ba điều kiện | J59: - Kết quả phải thỏa ĐỒNG THỜI cả ba điều kiện | K59: Passed
C60: TC_02.015 | D60: Nút Làm mới xóa hết điều kiện và nạp lại | E60: P0 | F60: Đăng nhập TK "Quản lý". | G60: 1. Đặt nhiều điều kiện lọc và bấm Tìm kiếm 2. Bấm nút Làm mới | I60: - Mọi ô lọc trở về trống - Danh sách tự nạp lại đủ 308 dòng không cần bấm Tìm kiếm lần nữa | J60: - Mọi ô lọc trở về trống - Danh sách tự nạp lại đủ 308 dòng NGAY, không cần bấm Tìm kiếm lần nữa | K60: Passed
C61: TC_02.016 | D61: Bộ lọc được nhớ khi quay lại màn trong 10 phút | E61: P1 | F61: Đăng nhập TK "Quản lý". | G61: 1. Chọn Bậc = 1, bấm Tìm kiếm 2. Sang màn khác 3. Quay lại trong 10 phút | H61: Bậc: 1 | I61: - Ô lọc và kết quả vẫn giữ nguyên | J61: - Ô lọc và kết quả vẫn giữ nguyên | K61: Passed
C62: TC_02.017 | D62: Lọc xong tự về trang 1 | E62: P1 | F62: Đăng nhập TK "Quản lý". Đang ở trang 5. | G62: 1. Chuyển sang trang 5 2. Đặt điều kiện lọc 3. Bấm Tìm kiếm | I62: - Kết quả hiển thị từ trang 1, không hiện bảng trống | J62: - Kết quả hiển thị từ trang 1, không hiện bảng trống | K62: Passed
C63: TC_02.018 | D63: Bỏ chọn nhiều cột | E63: P1 | F63: Popup Cấu hình cột hiển thị đang mở | G63: 1. Bỏ chọn 2 hoặc nhiều cột đang hiển thị. 2. Bấm Lưu. | I63: Các cột đã bỏ chọn đều được ẩn khỏi bảng. Các cột chưa bỏ chọn vẫn hiển thị. | J63: Các cột đã bỏ chọn đều được ẩn khỏi bảng. Các cột chưa bỏ chọn vẫn hiển thị. | K63: Passed
C64: TC_02.019 | D64: Chọn nhiều cột đang bị ẩn | E64: P1 | F64: Có nhiều cột đang bị ẩn | G64: 1. Mở Cấu hình cột hiển thị. 2. Chọn lại các cột cần hiển thị. 3. Bấm Lưu. | I64: Các cột được chọn hiển thị lại đúng trên bảng. | J64: Các cột được chọn hiển thị lại đúng trên bảng. | K64: Passed
C65: III. DANH SÁCH & PHÂN TRANG
A66: Danh mục tài khoản | B66: DANH SÁCH & PHÂN TRANG | C66: TC_03.001 | D66: Thứ tự mặc định theo cây tài khoản | E66: P0 | F66: Đăng nhập TK "Quản lý". Vừa mở màn hình, chưa lọc/sắp xếp. | G66: 1. Mở màn hình khi chưa lọc, chưa sắp xếp 2. Đọc thứ tự các dòng | I66: - Tài khoản con nằm ngay dưới tài khoản mẹ của nó (131 rồi 1311 rồi 13111) | J66: - Tài khoản con nằm ngay dưới tài khoản mẹ của nó (131 rồi 1311 rồi 13111) | K66: Passed
C67: TC_03.002 | D67: Chuyển trang bằng nút số trang | E67: P0 | F67: Đăng nhập TK "Quản lý". Cỡ trang 10 (tổng > 10). | G67: 1. Bấm số trang 2 | I67: - Bảng hiện dữ liệu trang 2 - Cột STT bắt đầu từ 11 - Dòng Hiển thị dưới bảng cập nhật đúng | J67: - Bảng hiện dữ liệu trang 2 - Cột STT bắt đầu từ 11 - Dòng Hiển thị dưới bảng cập nhật đúng | K67: Passed
C68: TC_03.003 | D68: Chuyển tới trang cuối | E68: P1 | F68: Đăng nhập TK "Quản lý". Cỡ trang 10 (tổng > 10). | G68: 1. Bấm nút chuyển tới trang cuối | I68: - Bảng hiện các dòng cuối cùng, không lỗi, không trống | J68: - Bảng hiện các dòng cuối cùng, không lỗi, không trống | K68: Passed
C69: TC_03.004 | D69: Đổi cỡ trang | E69: P0 | F69: Đăng nhập TK "Quản lý". Cỡ trang đang 10. | G69: 1. Đổi cỡ trang từ 10 sang 100 | H69: Cỡ trang: 100 | I69: - Bảng hiện 100 dòng - Danh sách chỉ nạp lại đúng một lần | J69: - Bảng hiện 100 dòng - Danh sách chỉ nạp lại đúng một lần | K69: Passed
C70: TC_03.005 | D70: Đổi cỡ trang khi đang ở trang cuối | E70: P1 | F70: Đăng nhập TK "Quản lý". Đang ở trang cuối. | G70: 1. Đổi cỡ trang sang 100 | H70: Cỡ trang: 100 | I70: - Bảng hiện dữ liệu, KHÔNG hiện bảng trống | J70: - Bảng hiện dữ liệu, KHÔNG hiện bảng trống | K70: Passed
C71: TC_03.006 | D71: Giữ nguyên trang khi thao tác trên dòng | E71: P1 | F71: Đăng nhập TK "Quản lý". Đang ở trang3. | G71: 1. Chuyển sang trang 3 2. Bấm Xem một dòng rồi Đóng | I71: - Vẫn đang ở trang 3, không bị nhảy về trang 1 | J71: - Vẫn đang ở trang 3, không bị nhảy về trang 1 | K71: Passed
C72: TC_03.007 | D72: Kiểm tra thay đổi thứ tự cột | E72: P1 | F72: Chức năng cho phép thay đổi thứ tự cột | G72: 1. Mở Cấu hình cột hiển thị. 2. Kéo cột Mã tài khoản lên vị trí khác. 3. Bấm Lưu. | I72: Thứ tự cột trên bảng thay đổi đúng theo thứ tự đã cấu hình. | J72: Thứ tự cột trên bảng thay đổi đúng theo thứ tự đã cấu hình. | K72: Passed
C73: TC_03.008 | D73: Kiểm tra thay đổi thứ tự nhiều cột | E73: P1 | F73: Popup Cấu hình cột hiển thị đang mở | G73: 1. Thay đổi vị trí của nhiều cột. 2. Bấm Lưu. | I73: Các cột trên bảng hiển thị đúng thứ tự đã cấu hình. | J73: Các cột trên bảng hiển thị đúng thứ tự đã cấu hình. | K73: Passed
C74: TC_03.009 | D74: Hủy thay đổi cấu hình cột | E74: P1 | F74: Đang có cấu hình hiện tại | G74: 1. Mở Cấu hình cột hiển thị. 2. Bỏ chọn một cột đang hiển thị. 3. Thay đổi thứ tự một cột. 4. Bấm Hủy/Đóng. | I74: Các thay đổi chưa được lưu. Bảng vẫn giữ nguyên cấu hình trước đó. | J74: Các thay đổi chưa được lưu. Bảng vẫn giữ nguyên cấu hình trước đó. | K74: Passed
C75: TC_03.010 | D75: Kiểm tra lưu cấu hình sau khi đóng và mở lại màn hình | E75: P1 | F75: Đã thay đổi và lưu cấu hình cột | G75: 1. Thay đổi cấu hình cột. 2. Bấm Lưu. 3. Đóng/rời khỏi màn Danh mục tài khoản. 4. Vào lại màn Danh mục tài khoản. | I75: Cấu hình cột đã lưu vẫn được giữ nguyên. | J75: Cấu hình cột đã lưu vẫn được giữ nguyên. | K75: Passed
C76: TC_03.011 | D76: Kiểm tra cấu hình sau khi refresh trang | E76: P1 | F76: Đã lưu cấu hình cột | G76: 1. Thay đổi cấu hình cột. 2. Bấm Lưu. 3. Refresh trang. | I76: Các cột vẫn hiển thị theo cấu hình đã lưu. | J76: Các cột vẫn hiển thị theo cấu hình đã lưu. | K76: Passed
C77: IV. THÊM / SỬA / XEM TÀI KHOẢN
A78: Danh mục tài khoản | B78: THÊM / SỬA / XEM TÀI KHOẢN | C78: TC_04.001 | D78: Mở trang Thêm tài khoản | E78: P0 | F78: Đăng nhập TK "Quản lý". | G78: 1. Bấm nút Tạo mới | I78: - Chuyển sang trang riêng để thêm tài khoản - Có các ô: Số tài khoản (bắt buộc), Bậc tài khoản (bắt buộc), Tài khoản mẹ, Tên tài khoản (bắt buộc), Loại tài khoản (bắt buộc), Trạng thái, và ô đánh dấu "Tài khoản theo dõi công nợ" - Các ô bắt buộc có dấu sao đỏ bên cạnh nhãn - Trang chia làm 2 khối: "Vị trí trong hệ thống tài khoản" (Số tài khoản, Bậc tài khoản, Tài khoản mẹ) và "Thông tin tài khoản" (Tên tài khoản, Loại tài khoản, Trạng thái, ô đánh dấu Tài khoản theo dõi công nợ) - Dưới ô Số tài khoản có dòng nhắc: chỉ nhập số, tối đa 15 chữ số; 3 chữ số là cấp 1, 4 số cấp 2, từ 5 số cấp 3 - Góc trên bên phải có 3 nút: Lưu, Lưu & Thêm tiếp, Quay lại | J78: - Chuyển sang trang riêng để thêm tài khoản - Có các ô: Số tài khoản (bắt buộc), Bậc tài khoản (bắt buộc), Tài khoản mẹ, Tên tài khoản (bắt buộc), Loại tài khoản (bắt buộc), Trạng thái, và ô đánh dấu "Tài khoản theo dõi công nợ" - Các ô bắt buộc có dấu sao đỏ bên cạnh nhãn - Trang chia làm 2 khối: "Vị trí trong hệ thống tài khoản" (Số tài khoản, Bậc tài khoản, Tài khoản mẹ) và "Thông tin tài khoản" (Tên tài khoản, Loại tài khoản, Trạng thái, ô đánh dấu Tài khoản theo dõi công nợ) - Dưới ô Số tài khoản có dòng nhắc: chỉ nhập số, tối đa 15 chữ số; 3 chữ số là cấp 1, 4 số cấp 2, từ 5 số cấp 3 - Góc trên bên phải có 3 nút: Lưu, Lưu & Thêm tiếp, Quay lại | K78: Passed
C79: TC_04.002 | D79: Thêm mới tài khoản bậc 1 | E79: P0 | F79: Đăng nhập TK "Quản lý". | G79: 1. Bấm Tạo mới 2. Nhập Số tài khoản 3 chữ số 3. Chọn Bậc = 1 4. Nhập Tên và chọn Loại tài khoản 5. Bấm Lưu | H79: Số: 991; Bậc: 1; Tên: Tài khoản kiểm thử; Loại: Tài khoản tài sản | I79: - Ô Tài khoản mẹ KHÔNG bắt buộc (không có dấu sao) khi Bậc = 1 - Lưu thành công, quay về danh sách và có dòng 991 - Số 991 nằm ở cột Cấp 1 | J79: - Ô Tài khoản mẹ KHÔNG bắt buộc (không có dấu sao) khi Bậc = 1 - Lưu thành công, quay về danh sách và có dòng 991 - Số 991 nằm ở cột Cấp 1 | K79: Passed
C80: TC_04.003 | D80: Thêm mới tài khoản bậc 2 | E80: P0 | F80: Đăng nhập TK "Quản lý". | G80: 1. Bấm Tạo mới 2. Chọn Bậc = 2 3. Chọn Tài khoản mẹ = 991 4. Nhập Số tài khoản = 9911 5. Nhập Tên, chọn Loại 6. Bấm Lưu | H80: Số: 9911; Bậc: 2; Mẹ: 991 | I80: - Ô Tài khoản mẹ chuyển thành bắt buộc (có dấu sao) khi chọn Bậc 2 - Lưu thành công, số 9911 nằm ở cột Cấp 2 - Dòng 9911 nằm ngay dưới dòng 991 trong danh sách | J80: - Ô Tài khoản mẹ chuyển thành bắt buộc (có dấu sao) khi chọn Bậc 2 - Lưu thành công, số 9911 nằm ở cột Cấp 2 - Dòng 9911 nằm ngay dưới dòng 991 trong danh sách | K80: Passed
C81: TC_04.004 | D81: Thêm mới tài khoản bậc 3 | E81: P0 | F81: Đăng nhập TK "Quản lý". | G81: 1. Bấm Tạo mới 2. Chọn Bậc = 3 3. Chọn Tài khoản mẹ = 9911 4. Nhập Số tài khoản = 99111 5. Nhập Tên, chọn Loại 6. Bấm Lưu | H81: Số: 99111; Bậc: 3; Mẹ: 9911 | I81: - Lưu thành công, số 99111 nằm ở cột Cấp 3 | J81: - Lưu thành công, số 99111 nằm ở cột Cấp 3 | K81: Passed
C82: TC_04.005 | D82: Danh sách Tài khoản mẹ lọc theo bậc đang chọn | E82: P0 | F82: Đăng nhập TK "Quản lý". | G82: 1. Bấm Tạo mới 2. Chọn Bậc = 2, mở danh sách Tài khoản mẹ và quan sát 3. Đổi Bậc = 3, mở lại danh sách Tài khoản mẹ | H82: Bậc 2 rồi Bậc 3 | I82: - Ở Bậc 2: danh sách chỉ liệt kê tài khoản BẬC 1 - Ở Bậc 3: danh sách chỉ liệt kê tài khoản BẬC 2 | J82: - Ở Bậc 2: danh sách chỉ liệt kê tài khoản BẬC 1 - Ở Bậc 3: danh sách chỉ liệt kê tài khoản BẬC 2 | K82: Passed
C83: TC_04.006 | D83: Bật ô đánh dấu Tài khoản theo dõi công nợ | E83: P0 | F83: Đăng nhập TK "Quản lý". | G83: 1. Bấm Tạo mới, nhập đủ thông tin 2. Bấm vào ô đánh dấu "Tài khoản theo dõi công nợ" 3. Bấm Lưu | H83: Số: 992; bật theo dõi công nợ | I83: - Ô đánh dấu bấm được và đổi trạng thái ngay khi bấm - Bên dưới có dòng giải thích khi nào nên bật - Sau khi lưu, dòng 992 có dấu đánh dấu ở cột Theo dõi công nợ | J83: - Ô đánh dấu bấm được và đổi trạng thái ngay khi bấm - Bên dưới có dòng giải thích khi nào nên bật - Sau khi lưu, dòng 992 có dấu đánh dấu ở cột Theo dõi công nợ | K83: Passed
C84: TC_04.007 | D84: Mở trang Sửa nạp đúng dữ liệu cũ | E84: P0 | F84: Đăng nhập TK "Quản lý". | G84: 1. Bấm nút Sửa trên dòng 991 | H84: — | I84: - Chuyển sang trang sửa, mọi ô điền sẵn đúng dữ liệu đang có - Ô đánh dấu Theo dõi công nợ đúng trạng thái đang lưu | J84: - Chuyển sang trang sửa, mọi ô điền sẵn đúng dữ liệu đang có - Ô đánh dấu Theo dõi công nợ đúng trạng thái đang lưu | K84: Passed
C85: TC_04.008 | D85: Sửa Tên tài khoản | E85: P0 | F85: Đăng nhập TK "Quản lý". | G85: 1. Bấm Sửa dòng 991 2. Đổi Tên 3. Bấm Lưu | H85: Tên: Tài khoản kiểm thử (đã sửa) | I85: - Lưu thành công, quay về danh sách hiện tên mới - Cột Cập nhật đổi sang thời điểm và người vừa sửa | J85: - Lưu thành công, quay về danh sách hiện tên mới - Cột Cập nhật đổi sang thời điểm và người vừa sửa | K85: Passed
C86: TC_04.009 | D86: Sửa Loại tài khoản | E86: P1 | F86: Đăng nhập TK "Quản lý". | G86: 1. Bấm Sửa dòng 991 2. Đổi Loại tài khoản 3. Bấm Lưu | H86: Loại: Tài khoản nguồn vốn | I86: - Lưu thành công, cột Loại tài khoản hiện giá trị mới | J86: - Lưu thành công, cột Loại tài khoản hiện giá trị mới | K86: Passed
C87: TC_04.010 | D87: Bật / tắt Theo dõi công nợ khi sửa | E87: P1 | F87: Đăng nhập TK "Quản lý". Có 1 TK đang bật Theo dõi. | G87: 1. Bấm Sửa dòng đang bật Theo dõi công nợ 2. Bỏ đánh dấu 3. Bấm Lưu | H87: Bỏ đánh dấu | I87: - Lưu thành công, cột Theo dõi công nợ của dòng đó trở về trống | J87: - Lưu thành công, cột Theo dõi công nợ của dòng đó trở về trống | K87: Passed
C88: TC_04.011 | D88: Nút Sửa bị vô hiệu với tài khoản đang Khóa | E88: P0 | F88: Đăng nhập TK "Quản lý". Có 1 TK đang Khóa. | G88: 1. Rê chuột vào nút Sửa của dòng 993 2. Thử bấm | H88: Tài khoản 993 đang Khóa | I88: - Nút Sửa bị mờ, không bấm được - Rê chuột hiện chú thích "Tài khoản đã khóa → không cho sửa" | J88: - Nút Sửa bị mờ, không bấm được - Rê chuột hiện chú thích "Tài khoản đã khóa → không cho sửa" | K88: Passed
C89: TC_04.012 | D89: Xem chi tiết một tài khoản | E89: P0 | F89: Đăng nhập TK "Quản lý". | G89: 1. Bấm nút Sửa trên một dòng bất kỳ để xem chi tiết 2. Bấm Quay lại | H89: — | I89: - Trang sửa hiện đầy đủ thông tin của tài khoản đó - Bấm Quay lại khi chưa đổi gì thì về danh sách ngay, không hỏi lại | J89: - Trang sửa hiện đầy đủ thông tin của tài khoản đó - Bấm Quay lại khi chưa đổi gì thì về danh sách ngay, không hỏi lại | K89: Passed
C90: TC_04.013 | D90: Cảnh báo khi rời trang lúc đang nhập dở | E90: P0 | F90: Đăng nhập TK "Quản lý". | G90: 1. Bấm Tạo mới 2. Nhập vài ô 3. Bấm quay lại danh sách | H90: Số: 995; Tên: nhập dở | I90: - Hệ thống cảnh báo dữ liệu chưa lưu và hỏi xác nhận - Chọn ở lại thì trang vẫn giữ nguyên nội dung đang nhập - Chọn thoát thì không tạo bản ghi nào | J90: - Hệ thống cảnh báo dữ liệu chưa lưu và hỏi xác nhận - Chọn ở lại thì trang vẫn giữ nguyên nội dung đang nhập - Chọn thoát thì không tạo bản ghi nào | K90: Passed
... C93: TC_04.016 | D93: Tài khoản mới dùng được ngay khi hạch toán | E93: P0 | F93: Đăng nhập TK "Quản lý". | G93: 1. Tạo mới tài khoản 991 ở trạng thái Hoạt động 2. Mở một màn hạch toán chứng từ, mở danh sách chọn tài khoản | H93: Số: 991 | I93: - Tài khoản 991 có trong danh sách chọn và chọn được | J93: - Tài khoản 991 có trong danh sách chọn và chọn được | K93: Passed
C94: TC_04.017 | D94: Kiểm tra cấu hình không làm mất dữ liệu trên bảng | E94: P0 | F94: Danh mục tài khoản có nhiều bản ghi | G94: 1. Bỏ chọn một số cột. 2. Bấm Lưu. 3. Kiểm tra dữ liệu các cột còn lại. | I94: Dữ liệu của các cột còn hiển thị không bị thay đổi hoặc mất dữ liệu. | J94: Dữ liệu của các cột còn hiển thị không bị thay đổi hoặc mất dữ liệu. | K94: Passed
C95: TC_04.018 | D95: Kiểm tra cấu hình cột khi tìm kiếm dữ liệu | E95: P0 | F95: Có dữ liệu danh mục tài khoản | G95: 1. Cấu hình ẩn một số cột. 2. Bấm Lưu. 3. Thực hiện tìm kiếm tài khoản. | I95: Kết quả tìm kiếm vẫn đúng. Các cột đã cấu hình ẩn vẫn không hiển thị trong kết quả. | J95: Kết quả tìm kiếm vẫn đúng. Các cột đã cấu hình ẩn vẫn không hiển thị trong kết quả. | K95: Passed
C96: V. RÀNG BUỘC TÀI KHOẢN
A97: Danh mục tài khoản | B97: RÀNG BUỘC CÂY TÀI KHOẢN | C97: TC_05.001 | D97: Bậc 2 bỏ trống Tài khoản mẹ | E97: P0 | F97: Đăng nhập TK "Quản lý". | G97: 1. Bấm Tạo mới 2. Chọn Bậc = 2, để trống Tài khoản mẹ 3. Nhập các ô còn lại 4. Bấm Lưu | H97: Bậc: 2; Tài khoản mẹ: (để trống) | I97: - Ô Tài khoản mẹ báo "Bắt buộc phải chọn tài khoản mẹ với bậc 2 và 3", không lưu | J97: - Ô Tài khoản mẹ báo "Bắt buộc phải chọn tài khoản mẹ với bậc 2 và 3", không lưu | K97: Passed
C98: TC_05.002 | D98: Bậc 3 bỏ trống Tài khoản mẹ | E98: P0 | F98: Đăng nhập TK "Quản lý". | G98: 1. Bấm Tạo mới 2. Chọn Bậc = 3, để trống Tài khoản mẹ 3. Bấm Lưu | H98: Bậc: 3; Tài khoản mẹ: (để trống) | I98: - Báo lỗi bắt buộc chọn tài khoản mẹ, không lưu | J98: - Báo lỗi bắt buộc chọn tài khoản mẹ, không lưu | K98: Passed
C99: TC_05.003 | D99: Bậc 1 không cần Tài khoản mẹ | E99: P0 | F99: Đăng nhập TK "Quản lý". | G99: 1. Bấm Tạo mới 2. Chọn Bậc = 1, để trống Tài khoản mẹ 3. Nhập các ô còn lại 4. Bấm Lưu | H99: Bậc: 1; Tài khoản mẹ: (để trống) | I99: - Lưu thành công, không báo lỗi ở ô Tài khoản mẹ | J99: - Lưu thành công, không báo lỗi ở ô Tài khoản mẹ | K99: Passed
C100: TC_05.004 | D100: Chọn Tài khoản mẹ sai bậc | E100: P0 | F100: Đăng nhập TK "Quản lý". | G100: 1. Dùng công cụ kiểm thử API gọi thẳng chức năng Thêm tài khoản bậc 3 nhưng đưa mẹ là một tài khoản BẬC 1 2. Đọc thông báo trả về | H100: Số: 99911; Bậc: 3; Mẹ: 131 (bậc 1) | I100: - Hệ thống chặn, báo tài khoản mẹ phải là tài khoản bậc 2 và nêu rõ mẹ đang là bậc mấy - Không tạo bản ghi | J100: - Hệ thống chặn, báo tài khoản mẹ phải là tài khoản bậc 2 và nêu rõ mẹ đang là bậc mấy - Không tạo bản ghi | K100: Passed
C101: TC_05.005 | D101: Số tài khoản con không bắt đầu bằng số mẹ | E101: P0 | F101: Đăng nhập TK "Quản lý". Có TK 991. | G101: 1. Bấm Tạo mới 2. Chọn Bậc = 2, Tài khoản mẹ = 991 3. Nhập Số tài khoản = 8888 (không bắt đầu bằng 991) 4. Bấm Lưu | H101: Số: 8888; Mẹ: 991 | I101: - Hệ thống chặn, thông báo nêu rõ số tài khoản con phải bắt đầu bằng số tài khoản mẹ và gợi ý dạng đúng (991 thì con phải là 9911, 9912…) - Không tạo bản ghi | J101: - Hệ thống chặn, thông báo nêu rõ số tài khoản con phải bắt đầu bằng số tài khoản mẹ và gợi ý dạng đúng (991 thì con phải là 9911, 9912…) - Không tạo bản ghi | K101: Passed
C102: TC_05.006 | D102: Số tài khoản con bắt đầu đúng bằng số mẹ | E102: P0 | F102: Đăng nhập TK "Quản lý". Có TK 991. | G102: 1. Bấm Tạo mới 2. Chọn Bậc = 2, Tài khoản mẹ = 991 3. Nhập Số tài khoản = 9912 4. Bấm Lưu | H102: Số: 9912; Mẹ: 991 | I102: - Lưu thành công - Dòng 9912 nằm ngay dưới 991 trong danh sách | J102: - Lưu thành công - Dòng 9912 nằm ngay dưới 991 trong danh sách | K102: Passed
...

Sheet 4. DM loại tài khoản
A1: MÔ TẢ TÍNH NĂNG (đọc trước khi xem testcase)
A2: 1. Mục đích tính năng | B2: Quản lý danh sách các loại tài khoản kế toán (tài khoản tài sản, tài khoản nguồn vốn, tài khoản doanh thu…). Mỗi tài khoản trong Danh mục tài khoản đều được gán về một loại lấy từ danh mục này. Màn hình nằm ở phân hệ Tài chính → nhóm menu Danh mục → Danh mục loại tài khoản. Đây là màn được chuyển từ hệ thống cũ sang, hai cổng dùng CHUNG một danh mục.
A3: 2. Đối tượng được tính / hiển thị | B3: - Toàn bộ loại tài khoản trong danh mục, KHÔNG phân theo công ty / phòng ban. - Hiển thị cả loại tài khoản Hoạt động và loại tài khoản đang Khóa. - Mỗi dòng gồm 7 cột: STT, Mã loại tài khoản, Tên loại tài khoản, Ghi chú, Cập nhật, Trạng thái, Hành động. - Cột Cập nhật hiện thời điểm sửa gần nhất kèm tên người cập nhật.
A4: 3. Đối tượng bị ẩn / không tính | B4: - Không có loại tài khoản nào bị ẩn khỏi màn này. - Loại tài khoản đang Khóa VẪN hiện ở đây nhưng KHÔNG còn được chọn khi tạo tài khoản mới. - Khi lọc theo một điều kiện (trạng thái, người tạo, người cập nhật, khoảng ngày cập nhật) thì các dòng không thỏa bị loại khỏi kết quả.
A5: 4. Bộ lọc thời gian áp dụng cho | B5: Hai ô "Cập nhật từ" và "Cập nhật đến" lọc theo NGÀY CẬP NHẬT gần nhất của loại tài khoản (chính là giá trị hiển thị ở cột Cập nhật), KHÔNG phải ngày tạo. Khoảng lọc tính bao gồm cả ngày đầu và ngày cuối. Được phép chỉ nhập một trong hai ô.
A6: 5. Cấu trúc dữ liệu / cây phân cấp | B6: Danh sách phẳng, không phân cấp cha- con. Quan hệ với màn khác: một loại tài khoản có thể được nhiều tài khoản sử dụng. Đây là căn cứ để hệ thống chặn xóa và chặn khóa.
A7: 6. Quy tắc cộng dồn / deduplicate | B7: Không cộng dồn. Mỗi loại tài khoản là một dòng độc lập. Chống trùng: cả Mã loại tài khoản và Tên loại tài khoản đều phải là duy nhất trong danh mục. Trùng mã báo "Mã loại tài khoản đã tồn tại"; trùng tên báo "Tên loại tài khoản đã tồn tại".
A8: 7. Phân quyền cấp | B8: Hai quyền dành riêng cho màn này: - "Xem danh mục loại tài khoản": vào màn hình, xem danh sách, mở xem chi tiết, xem lịch sử chỉnh sửa, xuất Excel. - "Quản lý danh mục loại tài khoản": thêm mới, sửa, khóa, mở khóa, xóa, nhập từ Excel. Người có quyền này cũng vào và xem được màn hình. Không có quyền nào trong hai quyền trên thì không vào được màn hình. Danh mục KHÔNG phân quyền theo công ty / phòng ban / bộ phận.
A9: 8. Cách tính các ô thống kê | B9: - Dòng "Hiển thị a- b / N" dưới bảng: a là dòng đầu của trang đang xem, b là dòng cuối, N là tổng số loại tài khoản khớp bộ lọc hiện tại. - Cột STT đánh theo trang: trang 2 với cỡ trang 10 thì bắt đầu từ 11. - Bảng nhập từ Excel: số dòng hợp lệ và số dòng lỗi được đếm riêng; chỉ dòng hợp lệ mới được ghi vào.
A10: 9. Ghi chú đọc bảng | B10: - Nút Khóa / Mở khóa nằm NGAY TRONG cột Trạng thái, không nằm ở cột Hành động. - Loại tài khoản đang được tài khoản nào đó sử dụng thì KHÔNG xóa được VÀ cũng KHÔNG khóa được — khác với Danh mục tiền tệ (ở đó khóa vẫn được). Rê chuột vào nút để đọc lý do. - Loại tài khoản đang ở trạng thái Khóa thì nút Sửa bị vô hiệu; muốn sửa phải Mở khóa trước. - Cột Ghi chú có thể rất dài, được xuống dòng trong ô, không cắt cụt. - Bộ lọc được hệ thống ghi nhớ trong 10 phút. Kiểm thử bộ lọc nên bấm Làm mới trước mỗi kịch bản. - Nút Import Excel chỉ hiện với người có quyền Quản lý; nút Xuất Excel hiện với mọi người vào được màn. - Mọi thay đổi đều được ghi lại và xem được qua nút Lịch sử chỉnh sửa trên từng dòng.
A11: Testcase _ Danh mục loại tài khoản- Cập nhật ngày 13/08/2026 | F11: TEST SUMMARY | I11: Số TH DNS kiểm thử đạt (P): | K11: =COUNTIF(K18:M1001,"Passed") | M11: Số trường hợp TP kiểm thử đạt (P): | P11: =COUNTIF(O18:Q200,"Passed")
I12: Số TH DNS kiểm thử không đạt (F) | K12: =COUNTIF(K18:M1001,"Failed") | M12: Số trường hợp TP kiểm thử không đạt (F) | P12: =COUNTIF(O19:Q201,"Fail")
I13: Số TH DNS kiểm thử đang xem xét (PE) | K13: =COUNTIF(K18:M1001,"Pending") | M13: Số trường hợp TP kiểm thử đang xem xét (PE) | P13: =COUNTIF(O20:Q202,"Pending")
I14: Số TH DNS kiểm thử chưa thực hiện | K14: =COUNTIF(K18:K1001,"Not Executed") | M14: Số trường hợp TP kiểm thử chưa thực hiện | P14: =K16-P15
I15: Tổng số TH DNS đã kiểm thử | K15: =sum(K11:K14) | M15: Tổng số trường hợp TP kiểm thử | P15: =sum(P11:Q13)
I16: Tổng số testcase | K16: =COUNTIF(I18:I1000,"*")
A17: Module | B17: Nhóm chức năng | C17: TC ID | D17: Chức năng | E17: Priority | F17: Tiền điều kiện | G17: Bước thực hiện | H17: Test Data | I17: Expected Result (chi tiết) | J17: KQ thực tế | K17: DNS check lần 1 | L17: DNS check lần 2 | M17: DNS check lần 3 | N17: Ghi chú | O17: TP check lần 1 | P17: TP check lần 2 | Q17: TP check lần 3
C18: Phân quyền & truy cập
A19: Danh mục loại tài khoản | B19: Phân quyền & truy cập | C19: TC-ROLE-01 | D19: Vào màn hình khi chỉ có quyền Xem | E19: P0 | F19: Có sẵn 2 tài khoản: tài khoản A chỉ được cấp quyền "Xem danh mục loại tài khoản"; tài khoản B được cấp quyền "Quản lý danh mục loại tài khoản". Danh mục đang có 7 loại tài khoản, trong đó loại "Tài khoản tài sản" đang được nhiều tài khoản sử dụng, loại "LTK thử" mới tạo chưa có tài khoản nào dùng. | G19: 1. Đăng nhập bằng tài khoản A 2. Vào phân hệ Tài chính → Danh mục → Danh mục loại tài khoản hoặc đường link chứa /finance/type-accounts | H19: Tài khoản A (chỉ có quyền Xem) | I19: - Vào được màn hình, bảng hiển thị đủ 7 loại tài khoản - KHÔNG có nút Tạo mới, KHÔNG có nút Import Excel - Trên mỗi dòng chỉ có nút Xem và nút Lịch sử chỉnh sửa; KHÔNG có nút Sửa, nút Xóa - Cột Trạng thái không có nút Khóa / Mở khóa - Vẫn có nút Xuất Excel | J19: - Vào được màn hình, bảng hiển thị đủ 7 loại tài khoản - KHÔNG có nút Tạo mới, KHÔNG có nút Import Excel - Trên mỗi dòng chỉ có nút Xem và nút Lịch sử chỉnh sửa; KHÔNG có nút Sửa, nút Xóa - Cột Trạng thái không có nút Khóa / Mở khóa - Vẫn có nút Xuất Excel | K19: Passed
C20: TC-ROLE-02 | D20: Vào màn hình khi có quyền Quản lý | E20: P0 | F20: Có sẵn 2 tài khoản: tài khoản A chỉ được cấp quyền "Xem danh mục loại tài khoản"; tài khoản B được cấp quyền "Quản lý danh mục loại tài khoản". Danh mục đang có 7 loại tài khoản, trong đó loại "Tài khoản tài sản" đang được nhiều tài khoản sử dụng, loại "LTK thử" mới tạo chưa có tài khoản nào dùng. | G20: 1. Đăng nhập bằng tài khoản B 2. Vào Danh mục loại tài khoản | H20: Tài khoản B | I20: - Có đủ 3 nút dưới bảng: Tạo mới, Xuất Excel, Import Excel - Mỗi dòng có đủ 4 nút: Xem, Sửa, Lịch sử chỉnh sửa, Xóa - Cột Trạng thái có nút Khóa hoặc Mở khóa | J20: - Có đủ 3 nút dưới bảng: Tạo mới, Xuất Excel, Import Excel - Mỗi dòng có đủ 4 nút: Xem, Sửa, Lịch sử chỉnh sửa, Xóa - Cột Trạng thái có nút Khóa hoặc Mở khóa | K20: Passed
C21: TC-ROLE-03 | D21: Chặn vào màn hình khi không có quyền nào | E21: P0 | F21: Tài khoản C không có cả hai quyền của màn này. | G21: 1. Đăng nhập bằng tài khoản C 2. Tìm mục Danh mục loại tài khoản trong phân hệ Tài chính 3. Dán thẳng đường dẫn màn hình vào thanh địa chỉ | H21: Tài khoản C | I21: - Mục menu KHÔNG hiện - Dán thẳng đường dẫn thì hệ thống chuyển sang trang báo không tìm thấy, không lộ dữ liệu nào | J21: - Mục menu KHÔNG hiện - Dán thẳng đường dẫn thì hệ thống chuyển sang trang báo không tìm thấy, không lộ dữ liệu nào | K21: Passed
C22: TC-ROLE-04 | D22: Chặn Thêm mới khi bỏ qua giao diện | E22: P0 | F22: Có sẵn 2 tài khoản: tài khoản A chỉ được cấp quyền "Xem danh mục loại tài khoản"; tài khoản B được cấp quyền "Quản lý danh mục loại tài khoản". Danh mục đang có 7 loại tài khoản, trong đó loại "Tài khoản tài sản" đang được nhiều tài khoản sử dụng, loại "LTK thử" mới tạo chưa có tài khoản nào dùng. | G22: 1. Đăng nhập bằng tài khoản A, lấy mã đăng nhập 2. Dùng công cụ kiểm thử API gọi thẳng chức năng Thêm loại tài khoản, bỏ qua giao diện 3. Mở lại màn hình kiểm tra | H22: Mã: ZZZ; Tên: Loại thử | I22: - Hệ thống từ chối, báo không có quyền - Danh sách vẫn 7 dòng, không có ZZZ | J22: - Hệ thống từ chối, báo không có quyền - Danh sách vẫn 7 dòng, không có ZZZ | K22: Passed
C23: TC-ROLE-05 | D23: Chặn Sửa khi bỏ qua giao diện | E23: P0 | F23: Có sẵn 2 tài khoản: tài khoản A chỉ được cấp quyền "Xem danh mục loại tài khoản"; tài khoản B được cấp quyền "Quản lý danh mục loại tài khoản". Danh mục đang có 7 loại tài khoản, trong đó loại "Tài khoản tài sản" đang được nhiều tài khoản sử dụng, loại "LTK thử" mới tạo chưa có tài khoản nào dùng. | G23: 1. Đăng nhập bằng tài khoản A 2. Dùng công cụ kiểm thử API gọi thẳng chức năng Sửa loại "Tài khoản tài sản" 3. Mở lại màn hình | H23: Đổi tên thành "Bị sửa trộm" | I23: - Hệ thống từ chối, báo không có quyền - Tên cũ giữ nguyên | J23: - Hệ thống từ chối, báo không có quyền - Tên cũ giữ nguyên | K23: Passed
C24: TC-ROLE-06 | D24: Chặn Xóa khi bỏ qua giao diện | E24: P0 | F24: Có sẵn 2 tài khoản: tài khoản A chỉ được cấp quyền "Xem danh mục loại tài khoản"; tài khoản B được cấp quyền "Quản lý danh mục loại tài khoản". Danh mục đang có 7 loại tài khoản, trong đó loại "Tài khoản tài sản" đang được nhiều tài khoản sử dụng, loại "LTK thử" mới tạo chưa có tài khoản nào dùng. | G24: 1. Đăng nhập bằng tài khoản A 2. Dùng công cụ kiểm thử API gọi thẳng chức năng Xóa loại "LTK thử" 3. Mở lại màn hình | H24: Loại LTK thử (về nghiệp vụ là xóa được) | I24: - Hệ thống từ chối, báo không có quyền - LTK thử vẫn còn trong danh sách | J24: - Hệ thống từ chối, báo không có quyền - LTK thử vẫn còn trong danh sách | K24: Passed
C25: TC-ROLE-07 | D25: Chặn Khóa / Mở khóa khi bỏ qua giao diện | E25: P1 | F25: Có sẵn 2 tài khoản: tài khoản A chỉ được cấp quyền "Xem danh mục loại tài khoản"; tài khoản B được cấp quyền "Quản lý danh mục loại tài khoản". Danh mục đang có 7 loại tài khoản, trong đó loại "Tài khoản tài sản" đang được nhiều tài khoản sử dụng, loại "LTK thử" mới tạo chưa có tài khoản nào dùng. | G25: 1. Đăng nhập bằng tài khoản A 2. Dùng công cụ kiểm thử API gọi thẳng chức năng Khóa loại "LTK thử" 3. Mở lại màn hình | H25: Loại LTK thử đang Hoạt động | I25: - Hệ thống từ chối, báo không có quyền - LTK thử vẫn Hoạt động | J25: - Hệ thống từ chối, báo không có quyền - LTK thử vẫn Hoạt động | K25: Passed
C26: TC-ROLE-08 | D26: Chặn Import Excel khi bỏ qua giao diện | E26: P1 | F26: Có sẵn 2 tài khoản: tài khoản A chỉ được cấp quyền "Xem danh mục loại tài khoản"; tài khoản B được cấp quyền "Quản lý danh mục loại tài khoản". Danh mục đang có 7 loại tài khoản, trong đó loại "Tài khoản tài sản" đang được nhiều tài khoản sử dụng, loại "LTK thử" mới tạo chưa có tài khoản nào dùng. | G26: 1. Đăng nhập bằng tài khoản A 2. Dùng công cụ kiểm thử API gọi thẳng chức năng Nhập loại tài khoản từ Excel 3. Mở lại màn hình | H26: File Excel 3 dòng hợp lệ | I26: - Hệ thống từ chối, báo không có quyền - Danh sách vẫn 7 dòng | J26: - Hệ thống từ chối, báo không có quyền - Danh sách vẫn 7 dòng | K26: Passed
C27: TC-ROLE-09 | D27: Người có quyền Xem vẫn xem được lịch sử chỉnh sửa | E27: P1 | F27: Có sẵn 2 tài khoản: tài khoản A chỉ được cấp quyền "Xem danh mục loại tài khoản"; tài khoản B được cấp quyền "Quản lý danh mục loại tài khoản". Danh mục đang có 7 loại tài khoản, trong đó loại "Tài khoản tài sản" đang được nhiều tài khoản sử dụng, loại "LTK thử" mới tạo chưa có tài khoản nào dùng. | G27: 1. Đăng nhập bằng tài khoản A 2. Bấm nút Lịch sử chỉnh sửa trên một dòng | H27: — | I27: - Cửa sổ "Lịch sử chỉnh sửa loại tài khoản" mở bình thường và hiện dữ liệu | J27: - Cửa sổ "Lịch sử chỉnh sửa loại tài khoản" mở bình thường và hiện dữ liệu | K27: Passed
C28: I. HIỂN THỊ TRANG & TRUY CẬP
A29: Danh mục loại tài khoản | B29: HIỂN THỊ TRANG & TRUY CẬP | C29: TC_01.001 | D29: Mở màn hình lần đầu | E29: P0 | F29: Đăng nhập bằng tài khoản có quyền "Quản lý danh mục loại tài khoản". Danh mục có 7 loại tài khoản: 6 loại Hoạt động và 1 loại đang Khóa. Loại "Tài khoản tài sản" đang được nhiều tài khoản sử dụng; loại "LTK thử" chưa có tài khoản nào dùng; có ít nhất 1 loại đã nhập Ghi chú dài trên 100 ký tự. | G29: 1. Vào phân hệ Tài chính → Danh mục → Danh mục loại tài khoản 2. Quan sát toàn màn hình | H29: — | I29: - Tiêu đề trang và tiêu đề bảng đều là "Danh mục loại tài khoản" - Khối lọc có tiêu đề "Bộ lọc danh mục loại tài khoản", mặc định thu gọn - Bảng có đủ 7 cột đúng thứ tự: STT, Mã loại tài khoản, Tên loại tài khoản, Ghi chú, Cập nhật, Trạng thái, Hành động - Dưới bảng có 3 nút: Tạo mới, Xuất Excel, Import Excel | J29: - Tiêu đề trang và tiêu đề bảng đều là "Danh mục loại tài khoản" - Khối lọc có tiêu đề "Bộ lọc danh mục loại tài khoản", mặc định thu gọn - Bảng có đủ 7 cột đúng thứ tự: STT, Mã loại tài khoản, Tên loại tài khoản, Ghi chú, Cập nhật, Trạng thái, Hành động - Dưới bảng có 3 nút: Tạo mới, Xuất Excel, Import Excel | K29: Passed
C30: TC_01.002 | D30: Hiển thị đủ số bản ghi khi chưa lọc | E30: P0 | F30: Đăng nhập bằng tài khoản có quyền "Quản lý danh mục loại tài khoản". Danh mục có 7 loại tài khoản: 6 loại Hoạt động và 1 loại đang Khóa. Loại "Tài khoản tài sản" đang được nhiều tài khoản sử dụng; loại "LTK thử" chưa có tài khoản nào dùng; có ít nhất 1 loại đã nhập Ghi chú dài trên 100 ký tự. | G30: 1. Mở màn hình 2. Đọc dòng Hiển thị dưới bảng | H30: — | I30: - Tổng là 7, gồm cả loại đang Khóa | J30: - Tổng là 7, gồm cả loại đang Khóa | K30: Passed
C31: TC_01.003 | D31: Cột Ghi chú xuống dòng khi nội dung dài | E31: P1 | F31: Đăng nhập bằng tài khoản có quyền "Quản lý danh mục loại tài khoản". Danh mục có 7 loại tài khoản: 6 loại Hoạt động và 1 loại đang Khóa. Loại "Tài khoản tài sản" đang được nhiều tài khoản sử dụng; loại "LTK thử" chưa có tài khoản nào dùng; có ít nhất 1 loại đã nhập Ghi chú dài trên 100 ký tự. | G31: 1. Mở màn hình 2. Nhìn dòng có Ghi chú dài trên 100 ký tự | H31: — | I31: - Nội dung ghi chú được xuống dòng trong ô, hiện đầy đủ - Không bị cắt cụt bằng dấu ba chấm, không tràn ra ngoài bảng | J31: - Nội dung ghi chú được xuống dòng trong ô, hiện đầy đủ - Không bị cắt cụt bằng dấu ba chấm, không tràn ra ngoài bảng | K31: Passed
C32: TC_01.004 | D32: Cột Cập nhật hiện thời điểm và người cập nhật | E32: P1 | F32: Đăng nhập bằng tài khoản có quyền "Quản lý danh mục loại tài khoản". Danh mục có 7 loại tài khoản: 6 loại Hoạt động và 1 loại đang Khóa. Loại "Tài khoản tài sản" đang được nhiều tài khoản sử dụng; loại "LTK thử" chưa có tài khoản nào dùng; có ít nhất 1 loại đã nhập Ghi chú dài trên 100 ký tự. | G32: 1. Mở màn hình 2. Nhìn cột Cập nhật | H32: — | I32: - Hiện ngày giờ cập nhật gần nhất kèm tên người cập nhật - Dòng chưa từng sửa vẫn hiện thông tin của lần tạo, không để trắng trơn | J32: - Hiện ngày giờ cập nhật gần nhất kèm tên người cập nhật - Dòng chưa từng sửa vẫn hiện thông tin của lần tạo, không để trắng trơn | K32: Passed
C33: TC_01.005 | D33: Cột Trạng thái hiển thị đúng nhãn | E33: P0 | F33: Đăng nhập bằng tài khoản có quyền "Quản lý danh mục loại tài khoản". Danh mục có 7 loại tài khoản: 6 loại Hoạt động và 1 loại đang Khóa. Loại "Tài khoản tài sản" đang được nhiều tài khoản sử dụng; loại "LTK thử" chưa có tài khoản nào dùng; có ít nhất 1 loại đã nhập Ghi chú dài trên 100 ký tự. | G33: 1. Mở màn hình 2. Đối chiếu cột Trạng thái | H33: — | I33: - Loại đang dùng hiện nhãn "Hoạt động" - Loại bị khóa hiện nhãn "Khóa" | J33: - Loại đang dùng hiện nhãn "Hoạt động" - Loại bị khóa hiện nhãn "Khóa" | K33: Passed
C34: TC_01.006 | D34: Vị trí nút Khóa / Mở khóa | E34: P1 | F34: Đăng nhập bằng tài khoản có quyền "Quản lý danh mục loại tài khoản". Danh mục có 7 loại tài khoản: 6 loại Hoạt động và 1 loại đang Khóa. Loại "Tài khoản tài sản" đang được nhiều tài khoản sử dụng; loại "LTK thử" chưa có tài khoản nào dùng; có ít nhất 1 loại đã nhập Ghi chú dài trên 100 ký tự. | G34: 1. Mở màn hình 2. Nhìn cột Trạng thái và cột Hành động | H34: — | I34: - Nút Khóa / Mở khóa nằm ngay cạnh nhãn trạng thái, TRONG cột Trạng thái - Cột Hành động có 4 nút: Xem, Sửa, Lịch sử chỉnh sửa, Xóa | J34: - Nút Khóa / Mở khóa nằm ngay cạnh nhãn trạng thái, TRONG cột Trạng thái - Cột Hành động có 4 nút: Xem, Sửa, Lịch sử chỉnh sửa, Xóa | K34: Passed
C35: TC_01.007 | D35: Bảng trống khi bộ lọc không khớp gì | E35: P1 | F35: Đăng nhập bằng tài khoản có quyền "Quản lý danh mục loại tài khoản". Danh mục có 7 loại tài khoản: 6 loại Hoạt động và 1 loại đang Khóa. Loại "Tài khoản tài sản" đang được nhiều tài khoản sử dụng; loại "LTK thử" chưa có tài khoản nào dùng; có ít nhất 1 loại đã nhập Ghi chú dài trên 100 ký tự. | G35: 1. Gõ "khongtontai123" vào ô tìm nhanh 2. Bấm Tìm kiếm | H35: khongtontai123 | I35: - Bảng hiện thông báo không có dữ liệu phù hợp - Tổng dưới bảng là 0 | J35: - Bảng hiện thông báo không có dữ liệu phù hợp - Tổng dưới bảng là 0 | K35: Passed
C36: II. BỘ LỌC & TÌM KIẾM
A37: Danh mục loại tài khoản | B37: BỘ LỌC & TÌM KIẾM | C37: TC_02.001 | D37: Tìm nhanh theo Mã loại tài khoản | E37: P0 | F37: Đăng nhập bằng tài khoản có quyền "Quản lý danh mục loại tài khoản". Danh mục có 7 loại tài khoản: 6 loại Hoạt động và 1 loại đang Khóa. Loại "Tài khoản tài sản" đang được nhiều tài khoản sử dụng; loại "LTK thử" chưa có tài khoản nào dùng; có ít nhất 1 loại đã nhập Ghi chú dài trên 100 ký tự. | G37: 1. Gõ mã của một loại tài khoản vào ô tìm nhanh 2. Bấm Tìm kiếm | H37: TKTS | I37: - Kết quả chỉ còn dòng có mã tương ứng | J37: - Kết quả chỉ còn dòng có mã tương ứng | K37: Passed
C38: TC_02.002 | D38: Tìm nhanh theo Tên loại tài khoản | E38: P0 | F38: Đăng nhập bằng tài khoản có quyền "Quản lý danh mục loại tài khoản". Danh mục có 7 loại tài khoản: 6 loại Hoạt động và 1 loại đang Khóa. Loại "Tài khoản tài sản" đang được nhiều tài khoản sử dụng; loại "LTK thử" chưa có tài khoản nào dùng; có ít nhất 1 loại đã nhập Ghi chú dài trên 100 ký tự. | G38: 1. Gõ "tài sản" vào ô tìm nhanh 2. Bấm Tìm kiếm | H38: tài sản | I38: - Kết quả gồm mọi loại có chuỗi "tài sản" trong tên Gợi ý trong ô ghi rõ: "Tìm theo mã hoặc tên loại tài khoản..." | J38: - Kết quả gồm mọi loại có chuỗi "tài sản" trong tên Gợi ý trong ô ghi rõ: "Tìm theo mã hoặc tên loại tài khoản..." | K38: Passed
C39: TC_02.003 | D39: Tìm nhanh khớp một phần chuỗi | E39: P1 | F39: Đăng nhập bằng tài khoản có quyền "Quản lý danh mục loại tài khoản". Danh mục có 7 loại tài khoản: 6 loại Hoạt động và 1 loại đang Khóa. Loại "Tài khoản tài sản" đang được nhiều tài khoản sử dụng; loại "LTK thử" chưa có tài khoản nào dùng; có ít nhất 1 loại đã nhập Ghi chú dài trên 100 ký tự. | G39: 1. Gõ 2 ký tự đầu của một mã 2. Bấm Tìm kiếm | H39: TK | I39: - Mọi mã bắt đầu bằng TK đều ra kết quả, không cần gõ đủ mã | J39: - Mọi mã bắt đầu bằng TK đều ra kết quả, không cần gõ đủ mã | K39: Passed
C40: TC_02.004 | D40: Tìm nhanh không phân biệt hoa thường | E40: P1 | F40: Đăng nhập bằng tài khoản có quyền "Quản lý danh mục loại tài khoản". Danh mục có 7 loại tài khoản: 6 loại Hoạt động và 1 loại đang Khóa. Loại "Tài khoản tài sản" đang được nhiều tài khoản sử dụng; loại "LTK thử" chưa có tài khoản nào dùng; có ít nhất 1 loại đã nhập Ghi chú dài trên 100 ký tự. | G40: 1. Gõ mã bằng chữ thường 2. Bấm Tìm kiếm | H40: tkts | I40: - Kết quả giống hệt khi gõ chữ hoa | J40: - Kết quả giống hệt khi gõ chữ hoa | K40: Passed
C41: TC_02.005 | D41: Gõ ô tìm nhanh mà chưa bấm Tìm kiếm | E41: P1 | F41: Đăng nhập bằng tài khoản có quyền "Quản lý danh mục loại tài khoản". Danh mục có 7 loại tài khoản: 6 loại Hoạt động và 1 loại đang Khóa. Loại "Tài khoản tài sản" đang được nhiều tài khoản sử dụng; loại "LTK thử" chưa có tài khoản nào dùng; có ít nhất 1 loại đã nhập Ghi chú dài trên 100 ký tự. | G41: 1. Gõ từ khóa 2. Chờ 5 giây, không bấm gì | H41: TKTS | I41: - Bảng vẫn giữ nguyên, chưa lọc | J41: - Bảng vẫn giữ nguyên, chưa lọc | K41: Passed
C42: TC_02.006 | D42: Lọc theo Trạng thái = Hoạt động | E42: P0 | F42: Đăng nhập bằng tài khoản có quyền "Quản lý danh mục loại tài khoản". Danh mục có 7 loại tài khoản: 6 loại Hoạt động và 1 loại đang Khóa. Loại "Tài khoản tài sản" đang được nhiều tài khoản sử dụng; loại "LTK thử" chưa có tài khoản nào dùng; có ít nhất 1 loại đã nhập Ghi chú dài trên 100 ký tự. | G42: 1. Mở bộ lọc nâng cao 2. Chọn Trạng thái = Hoạt động 3. Bấm Tìm kiếm | H42: Trạng thái: Hoạt động | I42: - Kết quả 6 dòng, tất cả mang nhãn Hoạt động | J42: - Kết quả 6 dòng, tất cả mang nhãn Hoạt động | K42: Passed
C43: TC_02.007 | D43: Lọc theo Trạng thái = Khóa | E43: P0 | F43: Đăng nhập bằng tài khoản có quyền "Quản lý danh mục loại tài khoản". Danh mục có 7 loại tài khoản: 6 loại Hoạt động và 1 loại đang Khóa. Loại "Tài khoản tài sản" đang được nhiều tài khoản sử dụng; loại "LTK thử" chưa có tài khoản nào dùng; có ít nhất 1 loại đã nhập Ghi chú dài trên 100 ký tự. | G43: 1. Chọn Trạng thái = Khóa 2. Bấm Tìm kiếm | H43: Trạng thái: Khóa | I43: - Kết quả 1 dòng mang nhãn Khóa | J43: - Kết quả 1 dòng mang nhãn Khóa | K43: Passed
C44: TC_02.008 | D44: Lọc theo Người tạo | E44: P0 | F44: Đăng nhập bằng tài khoản có quyền "Quản lý danh mục loại tài khoản". Danh mục có 7 loại tài khoản: 6 loại Hoạt động và 1 loại đang Khóa. Loại "Tài khoản tài sản" đang được nhiều tài khoản sử dụng; loại "LTK thử" chưa có tài khoản nào dùng; có ít nhất 1 loại đã nhập Ghi chú dài trên 100 ký tự. | G44: 1. Mở bộ lọc nâng cao 2. Chọn một người trong ô Người tạo 3. Bấm Tìm kiếm | H44: Người tạo: một nhân viên có trong danh sách | I44: - Kết quả chỉ còn các loại tài khoản do người đó tạo - Danh sách chọn Người tạo chỉ liệt kê những người thực sự đã tạo bản ghi, không liệt kê toàn bộ nhân viên | J44: - Kết quả chỉ còn các loại tài khoản do người đó tạo - Danh sách chọn Người tạo chỉ liệt kê những người thực sự đã tạo bản ghi, không liệt kê toàn bộ nhân viên | K44: Passed
C45: TC_02.009 | D45: Lọc theo Người cập nhật | E45: P0 | F45: Đăng nhập bằng tài khoản có quyền "Quản lý danh mục loại tài khoản". Danh mục có 7 loại tài khoản: 6 loại Hoạt động và 1 loại đang Khóa. Loại "Tài khoản tài sản" đang được nhiều tài khoản sử dụng; loại "LTK thử" chưa có tài khoản nào dùng; có ít nhất 1 loại đã nhập Ghi chú dài trên 100 ký tự. | G45: 1. Chọn một người trong ô Người cập nhật 2. Bấm Tìm kiếm | H45: Người cập nhật: một nhân viên có trong danh sách | I45: - Kết quả chỉ còn các loại tài khoản do người đó cập nhật gần nhất - Cột Cập nhật của mọi dòng đều hiện tên người vừa chọn | J45: - Kết quả chỉ còn các loại tài khoản do người đó cập nhật gần nhất - Cột Cập nhật của mọi dòng đều hiện tên người vừa chọn | K45: Passed
C46: TC_02.010 | D46: Lọc theo Cập nhật từ | E46: P0 | F46: Đăng nhập bằng tài khoản có quyền "Quản lý danh mục loại tài khoản". Danh mục có 7 loại tài khoản: 6 loại Hoạt động và 1 loại đang Khóa. Loại "Tài khoản tài sản" đang được nhiều tài khoản sử dụng; loại "LTK thử" chưa có tài khoản nào dùng; có ít nhất 1 loại đã nhập Ghi chú dài trên 100 ký tự. | G46: 1. Nhập Cập nhật từ = ngày hôm nay 2. Bấm Tìm kiếm | H46: Cập nhật từ: hôm nay | I46: - Chỉ còn các dòng có ngày cập nhật từ hôm nay trở đi - Dòng cập nhật đúng hôm nay VẪN nằm trong kết quả (tính cả ngày đầu) | J46: - Chỉ còn các dòng có ngày cập nhật từ hôm nay trở đi - Dòng cập nhật đúng hôm nay VẪN nằm trong kết quả (tính cả ngày đầu) | K46: Passed
C47: TC_02.011 | D47: Lọc theo Cập nhật đến | E47: P0 | F47: Đăng nhập bằng tài khoản có quyền "Quản lý danh mục loại tài khoản". Danh mục có 7 loại tài khoản: 6 loại Hoạt động và 1 loại đang Khóa. Loại "Tài khoản tài sản" đang được nhiều tài khoản sử dụng; loại "LTK thử" chưa có tài khoản nào dùng; có ít nhất 1 loại đã nhập Ghi chú dài trên 100 ký tự. | G47: 1. Nhập Cập nhật đến = ngày hôm nay 2. Bấm Tìm kiếm | H47: Cập nhật đến: hôm nay | I47: - Chỉ còn các dòng có ngày cập nhật đến hết hôm nay - Dòng cập nhật đúng hôm nay VẪN nằm trong kết quả (tính cả ngày cuối) Bẫy hay gặp: dòng cập nhật lúc 15h hôm nay bị loại vì hệ thống cắt mốc từ 0h | J47: - Chỉ còn các dòng có ngày cập nhật đến hết hôm nay - Dòng cập nhật đúng hôm nay VẪN nằm trong kết quả (tính cả ngày cuối) Bẫy hay gặp: dòng cập nhật lúc 15h hôm nay bị loại vì hệ thống cắt mốc từ 0h | K47: Passed
C48: TC_02.012 | D48: Lọc khoảng ngày cập nhật đầy đủ | E48: P0 | F48: Đăng nhập bằng tài khoản có quyền "Quản lý danh mục loại tài khoản". Danh mục có 7 loại tài khoản: 6 loại Hoạt động và 1 loại đang Khóa. Loại "Tài khoản tài sản" đang được nhiều tài khoản sử dụng; loại "LTK thử" chưa có tài khoản nào dùng; có ít nhất 1 loại đã nhập Ghi chú dài trên 100 ký tự. | G48: 1. Nhập Cập nhật từ = đầu tháng, Cập nhật đến = cuối tháng 2. Bấm Tìm kiếm | H48: Cập nhật từ: 01 tháng này; đến: ngày cuối tháng này | I48: - Chỉ còn các dòng có ngày cập nhật nằm trong khoảng, tính cả 2 mốc | J48: - Chỉ còn các dòng có ngày cập nhật nằm trong khoảng, tính cả 2 mốc | K48: Passed
C49: TC_02.013 | D49: Nhập Cập nhật từ lớn hơn Cập nhật đến | E49: P1 | F49: Đăng nhập bằng tài khoản có quyền "Quản lý danh mục loại tài khoản". Danh mục có 7 loại tài khoản: 6 loại Hoạt động và 1 loại đang Khóa. Loại "Tài khoản tài sản" đang được nhiều tài khoản sử dụng; loại "LTK thử" chưa có tài khoản nào dùng; có ít nhất 1 loại đã nhập Ghi chú dài trên 100 ký tự. | G49: 1. Nhập Cập nhật từ = hôm nay, Cập nhật đến = hôm qua 2. Bấm Tìm kiếm | H49: Từ: hôm nay; Đến: hôm qua | I49: - Hệ thống hoặc báo khoảng ngày không hợp lệ, hoặc trả về kết quả rỗng - Không được lỗi trắng trang | J49: - Hệ thống hoặc báo khoảng ngày không hợp lệ, hoặc trả về kết quả rỗng - Không được lỗi trắng trang | K49: Passed
... C53: TC_02.017 | D53: Lọc xong tự về trang 1 | E53: P1 | F53: Đăng nhập bằng tài khoản có quyền "Quản lý danh mục loại tài khoản". Danh mục có 7 loại tài khoản: 6 loại Hoạt động và 1 loại đang Khóa. Loại "Tài khoản tài sản" đang được nhiều tài khoản sử dụng; loại "LTK thử" chưa có tài khoản nào dùng; có ít nhất 1 loại đã nhập Ghi chú dài trên 100 ký tự. Đang đứng ở trang2. | G53: 1. Chuyển sang trang 2 2. Đặt điều kiện lọc 3. Bấm Tìm kiếm | H53: — | I53: - Kết quả hiển thị từ trang 1, không hiện bảng trống | J53: - Kết quả hiển thị từ trang 1, không hiện bảng trống | K53: Passed
C54: III. DANH SÁCH, SẮP XẾP & PHÂN TRANG
A55: Danh mục loại tài khoản | B55: DANH SÁCH, SẮP XẾP & PHÂN TRANG | C55: TC_03.001 | D55: Sắp xếp theo Mã loại tài khoản | E55: P0 | F55: Đăng nhập bằng tài khoản có quyền "Quản lý danh mục loại tài khoản". Danh mục có 7 loại tài khoản: 6 loại Hoạt động và 1 loại đang Khóa. Loại "Tài khoản tài sản" đang được nhiều tài khoản sử dụng; loại "LTK thử" chưa có tài khoản nào dùng; có ít nhất 1 loại đã nhập Ghi chú dài trên 100 ký tự. | G55: 1. Bấm tiêu đề cột Mã loại tài khoản 1 lần rồi 2 lần | H55: — | I55: - Lần 1 xếp tăng dần A→Z, lần 2 xếp giảm dần Z→A - Mũi tên trên tiêu đề đổi chiều tương ứng | J55: - Lần 1 xếp tăng dần A→Z, lần 2 xếp giảm dần Z→A - Mũi tên trên tiêu đề đổi chiều tương ứng | K55: Passed
C56: TC_03.002 | D56: Sắp xếp theo Tên loại tài khoản | E56: P0 | F56: Đăng nhập bằng tài khoản có quyền "Quản lý danh mục loại tài khoản". Danh mục có 7 loại tài khoản: 6 loại Hoạt động và 1 loại đang Khóa. Loại "Tài khoản tài sản" đang được nhiều tài khoản sử dụng; loại "LTK thử" chưa có tài khoản nào dùng; có ít nhất 1 loại đã nhập Ghi chú dài trên 100 ký tự. | G56: 1. Bấm tiêu đề cột Tên loại tài khoản | H56: — | I56: - Thứ tự các dòng thực sự thay đổi theo tên Bẫy: mũi tên đổi chiều nhưng danh sách đứng yên — đó là lỗi | J56: - Thứ tự các dòng thực sự thay đổi theo tên Bẫy: mũi tên đổi chiều nhưng danh sách đứng yên — đó là lỗi | K56: Passed
C57: TC_03.003 | D57: Cột STT và Hành động không sắp xếp được | E57: P2 | F57: Đăng nhập bằng tài khoản có quyền "Quản lý danh mục loại tài khoản". Danh mục có 7 loại tài khoản: 6 loại Hoạt động và 1 loại đang Khóa. Loại "Tài khoản tài sản" đang được nhiều tài khoản sử dụng; loại "LTK thử" chưa có tài khoản nào dùng; có ít nhất 1 loại đã nhập Ghi chú dài trên 100 ký tự. | G57: 1. Bấm tiêu đề cột STT rồi cột Hành động | H57: — | I57: - Không có mũi tên sắp xếp, bấm vào không đổi thứ tự và không lỗi | J57: - Không có mũi tên sắp xếp, bấm vào không đổi thứ tự và không lỗi | K57: Passed
C58: TC_03.004 | D58: Sắp xếp giữ nguyên khi chuyển trang | E58: P1 | F58: Đăng nhập bằng tài khoản có quyền "Quản lý danh mục loại tài khoản". Danh mục có 7 loại tài khoản: 6 loại Hoạt động và 1 loại đang Khóa. Loại "Tài khoản tài sản" đang được nhiều tài khoản sử dụng; loại "LTK thử" chưa có tài khoản nào dùng; có ít nhất 1 loại đã nhập Ghi chú dài trên 100 ký tự. Đặt cỡ trang 5 để có 2 trang. | G58: 1. Sắp xếp theo Mã giảm dần 2. Chuyển sang trang 2 | H58: Cỡ trang: 5 | I58: - Trang 2 tiếp nối đúng thứ tự đã sắp | J58: - Trang 2 tiếp nối đúng thứ tự đã sắp | K58: Passed
C59: TC_03.005 | D59: Chuyển trang bằng nút số trang | E59: P0 | F59: Đăng nhập bằng tài khoản có quyền "Quản lý danh mục loại tài khoản". Danh mục có 7 loại tài khoản: 6 loại Hoạt động và 1 loại đang Khóa. Loại "Tài khoản tài sản" đang được nhiều tài khoản sử dụng; loại "LTK thử" chưa có tài khoản nào dùng; có ít nhất 1 loại đã nhập Ghi chú dài trên 100 ký tự. Đặt cỡ trang 5, có 2 trang. | G59: 1. Bấm số trang 2 | H59: Cỡ trang: 5 | I59: - Bảng hiện các dòng còn lại - Cột STT bắt đầu từ 6 - Dòng Hiển thị dưới bảng cập nhật đúng | J59: - Bảng hiện các dòng còn lại - Cột STT bắt đầu từ 6 - Dòng Hiển thị dưới bảng cập nhật đúng | K59: Passed
C60: TC_03.006 | D60: Đổi cỡ trang | E60: P0 | F60: Đăng nhập bằng tài khoản có quyền "Quản lý danh mục loại tài khoản". Danh mục có 7 loại tài khoản: 6 loại Hoạt động và 1 loại đang Khóa. Loại "Tài khoản tài sản" đang được nhiều tài khoản sử dụng; loại "LTK thử" chưa có tài khoản nào dùng; có ít nhất 1 loại đã nhập Ghi chú dài trên 100 ký tự. | G60: 1. Đổi cỡ trang từ 10 sang 50 | H60: Cỡ trang: 50 | I60: - Toàn bộ 7 dòng hiện trên 1 trang - Danh sách chỉ nạp lại đúng một lần | J60: - Toàn bộ 7 dòng hiện trên 1 trang - Danh sách chỉ nạp lại đúng một lần | K60: Passed
C61: TC_03.007 | D61: Đổi cỡ trang khi đang ở trang cuối | E61: P1 | F61: Đăng nhập bằng tài khoản có quyền "Quản lý danh mục loại tài khoản". Danh mục có 7 loại tài khoản: 6 loại Hoạt động và 1 loại đang Khóa. Loại "Tài khoản tài sản" đang được nhiều tài khoản sử dụng; loại "LTK thử" chưa có tài khoản nào dùng; có ít nhất 1 loại đã nhập Ghi chú dài trên 100 ký tự. Đang ở trang 2 với cỡ trang 5. | G61: 1. Đổi cỡ trang sang 50 | H61: Cỡ trang: 50 | I61: - Bảng hiện dữ liệu từ trang 1, KHÔNG hiện bảng trống | J61: - Bảng hiện dữ liệu từ trang 1, KHÔNG hiện bảng trống | K61: Passed
C62: TC_03.008 | D62: Vào màn hình chỉ gọi dữ liệu một lần | E62: P1 | F62: Đăng nhập bằng tài khoản có quyền "Quản lý danh mục loại tài khoản". Danh mục có 7 loại tài khoản: 6 loại Hoạt động và 1 loại đang Khóa. Loại "Tài khoản tài sản" đang được nhiều tài khoản sử dụng; loại "LTK thử" chưa có tài khoản nào dùng; có ít nhất 1 loại đã nhập Ghi chú dài trên 100 ký tự. | G62: 1. Mở màn hình từ menu 2. Quan sát hiệu ứng tải của bảng | H62: — | I62: - Bảng chỉ tải một lượt, không chớp tải hai lần | J62: - Bảng chỉ tải một lượt, không chớp tải hai lần | K62: Passed
C63: IV. THÊM / SỬA / XEM LOẠI TÀI KHOẢN
A64: Danh mục loại tài khoản | B64: THÊM / SỬA / XEM LOẠI TÀI KHOẢN | C64: TC_04.001 | D64: Mở cửa sổ Thêm loại tài khoản | E64: P0 | F64: Đăng nhập bằng tài khoản có quyền "Quản lý danh mục loại tài khoản". Danh mục có 7 loại tài khoản: 6 loại Hoạt động và 1 loại đang Khóa. Loại "Tài khoản tài sản" đang được nhiều tài khoản sử dụng; loại "LTK thử" chưa có tài khoản nào dùng; có ít nhất 1 loại đã nhập Ghi chú dài trên 100 ký tự. | G64: 1. Bấm nút Tạo mới | H64: — | I64: - Mở cửa sổ tiêu đề "Thêm loại tài khoản" - Có 4 ô: Mã loại tài khoản (bắt buộc), Trạng thái, Tên loại tài khoản (bắt buộc), Ghi chú - Hai ô bắt buộc có dấu sao đỏ bên cạnh nhãn | J64: - Mở cửa sổ tiêu đề "Thêm loại tài khoản" - Có 4 ô: Mã loại tài khoản (bắt buộc), Trạng thái, Tên loại tài khoản (bắt buộc), Ghi chú - Hai ô bắt buộc có dấu sao đỏ bên cạnh nhãn | K64: Passed
C65: TC_04.002 | D65: Thêm mới đầy đủ thông tin | E65: P0 | F65: Đăng nhập bằng tài khoản có quyền "Quản lý danh mục loại tài khoản". Danh mục có 7 loại tài khoản: 6 loại Hoạt động và 1 loại đang Khóa. Loại "Tài khoản tài sản" đang được nhiều tài khoản sử dụng; loại "LTK thử" chưa có tài khoản nào dùng; có ít nhất 1 loại đã nhập Ghi chú dài trên 100 ký tự. | G65: 1. Bấm Tạo mới 2. Nhập đủ 4 ô 3. Bấm Lưu | H65: Mã: LTK1; Tên: Loại kiểm thử; Ghi chú: Dùng để kiểm thử; Trạng thái: Hoạt động | I65: - Thông báo thêm mới thành công - Cửa sổ đóng, danh sách nạp lại và có dòng LTK1 với đủ thông tin vừa nhập | J65: - Thông báo thêm mới thành công - Cửa sổ đóng, danh sách nạp lại và có dòng LTK1 với đủ thông tin vừa nhập | K65: Passed
C66: TC_04.003 | D66: Thêm mới chỉ nhập các ô bắt buộc | E66: P0 | F66: Đăng nhập bằng tài khoản có quyền "Quản lý danh mục loại tài khoản". Danh mục có 7 loại tài khoản: 6 loại Hoạt động và 1 loại đang Khóa. Loại "Tài khoản tài sản" đang được nhiều tài khoản sử dụng; loại "LTK thử" chưa có tài khoản nào dùng; có ít nhất 1 loại đã nhập Ghi chú dài trên 100 ký tự. | G66: 1. Bấm Tạo mới 2. Chỉ nhập Mã và Tên 3. Bấm Lưu | H66: Mã: LTK2; Tên: Loại kiểm thử 2 | I66: - Lưu thành công - Cột Ghi chú của dòng mới để trống - Trạng thái mặc định là Hoạt động | J66: - Lưu thành công - Cột Ghi chú của dòng mới để trống - Trạng thái mặc định là Hoạt động | K66: Passed
C67: TC_04.004 | D67: Mở cửa sổ Sửa nạp đúng dữ liệu cũ | E67: P0 | F67: Đăng nhập bằng tài khoản có quyền "Quản lý danh mục loại tài khoản". Danh mục có 7 loại tài khoản: 6 loại Hoạt động và 1 loại đang Khóa. Loại "Tài khoản tài sản" đang được nhiều tài khoản sử dụng; loại "LTK thử" chưa có tài khoản nào dùng; có ít nhất 1 loại đã nhập Ghi chú dài trên 100 ký tự. | G67: 1. Bấm nút Sửa trên một dòng đang Hoạt động | H67: — | I67: - Tiêu đề cửa sổ là "Sửa loại tài khoản" - Các ô điền sẵn đúng dữ liệu đang có - Cạnh tiêu đề hiện thông tin lần cập nhật gần nhất | J67: - Tiêu đề cửa sổ là "Sửa loại tài khoản" - Các ô điền sẵn đúng dữ liệu đang có - Cạnh tiêu đề hiện thông tin lần cập nhật gần nhất | K67: Passed
C68: TC_04.005 | D68: Sửa Tên loại tài khoản | E68: P0 | F68: Đăng nhập bằng tài khoản có quyền "Quản lý danh mục loại tài khoản". Danh mục có 7 loại tài khoản: 6 loại Hoạt động và 1 loại đang Khóa. Loại "Tài khoản tài sản" đang được nhiều tài khoản sử dụng; loại "LTK thử" chưa có tài khoản nào dùng; có ít nhất 1 loại đã nhập Ghi chú dài trên 100 ký tự. | G68: 1. Bấm Sửa dòng LTK1 2. Đổi Tên 3. Bấm Lưu | H68: Tên: Loại kiểm thử (đã sửa) | I68: - Thông báo cập nhật thành công - Danh sách hiện tên mới, cột Cập nhật đổi sang thời điểm và người vừa sửa | J68: - Thông báo cập nhật thành công - Danh sách hiện tên mới, cột Cập nhật đổi sang thời điểm và người vừa sửa | K68: Passed
C69: TC_04.006 | D69: Sửa Ghi chú | E69: P1 | F69: Đăng nhập bằng tài khoản có quyền "Quản lý danh mục loại tài khoản". Danh mục có 7 loại tài khoản: 6 loại Hoạt động và 1 loại đang Khóa. Loại "Tài khoản tài sản" đang được nhiều tài khoản sử dụng; loại "LTK thử" chưa có tài khoản nào dùng; có ít nhất 1 loại đã nhập Ghi chú dài trên 100 ký tự. | G69: 1. Bấm Sửa dòng LTK1 2. Đổi Ghi chú 3. Bấm Lưu | H69: Ghi chú: nội dung mới | I69: - Cập nhật thành công, cột Ghi chú hiện nội dung mới | J69: - Cập nhật thành công, cột Ghi chú hiện nội dung mới | K69: Passed
C70: TC_04.007 | D70: Xóa trắng Ghi chú đang có | E70: P1 | F70: Đăng nhập bằng tài khoản có quyền "Quản lý danh mục loại tài khoản". Danh mục có 7 loại tài khoản: 6 loại Hoạt động và 1 loại đang Khóa. Loại "Tài khoản tài sản" đang được nhiều tài khoản sử dụng; loại "LTK thử" chưa có tài khoản nào dùng; có ít nhất 1 loại đã nhập Ghi chú dài trên 100 ký tự. | G70: 1. Bấm Sửa dòng có Ghi chú 2. Xóa trắng ô Ghi chú 3. Bấm Lưu | H70: Ghi chú: (để trống) | I70: - Cập nhật thành công, cột Ghi chú thành trống | J70: - Cập nhật thành công, cột Ghi chú thành trống | K70: Passed
C71: TC_04.008 | D71: Nút Sửa bị vô hiệu với loại tài khoản đang Khóa | E71: P0 | F71: Đăng nhập bằng tài khoản có quyền "Quản lý danh mục loại tài khoản". Danh mục có 7 loại tài khoản: 6 loại Hoạt động và 1 loại đang Khóa. Loại "Tài khoản tài sản" đang được nhiều tài khoản sử dụng; loại "LTK thử" chưa có tài khoản nào dùng; có ít nhất 1 loại đã nhập Ghi chú dài trên 100 ký tự. Loại "LTK khóa" đang ở trạng thái Khóa. | G71: 1. Rê chuột vào nút Sửa của dòng LTK khóa 2. Thử bấm | H71: Loại LTK khóa | I71: - Nút Sửa bị mờ, không bấm được - Rê chuột hiện chú thích "Loại tài khoản đã khóa → không cho sửa" Muốn sửa phải Mở khóa trước | J71: - Nút Sửa bị mờ, không bấm được - Rê chuột hiện chú thích "Loại tài khoản đã khóa → không cho sửa" Muốn sửa phải Mở khóa trước | K71: Passed
C72: TC_04.009 | D72: Nút Xem mở ở chế độ chỉ đọc | E72: P0 | F72: Đăng nhập bằng tài khoản có quyền "Quản lý danh mục loại tài khoản". Danh mục có 7 loại tài khoản: 6 loại Hoạt động và 1 loại đang Khóa. Loại "Tài khoản tài sản" đang được nhiều tài khoản sử dụng; loại "LTK thử" chưa có tài khoản nào dùng; có ít nhất 1 loại đã nhập Ghi chú dài trên 100 ký tự. | G72: 1. Bấm nút Xem trên một dòng bất kỳ | H72: — | I72: - Tiêu đề cửa sổ là "Xem loại tài khoản" - Mọi ô đều mờ, không gõ được - KHÔNG có nút Lưu, chỉ có nút Đóng | J72: - Tiêu đề cửa sổ là "Xem loại tài khoản" - Mọi ô đều mờ, không gõ được - KHÔNG có nút Lưu, chỉ có nút Đóng | K72: Passed
C73: TC_04.010 | D73: Xem được cả loại tài khoản đang Khóa | E73: P1 | F73: Đăng nhập bằng tài khoản có quyền "Quản lý danh mục loại tài khoản". Danh mục có 7 loại tài khoản: 6 loại Hoạt động và 1 loại đang Khóa. Loại "Tài khoản tài sản" đang được nhiều tài khoản sử dụng; loại "LTK thử" chưa có tài khoản nào dùng; có ít nhất 1 loại đã nhập Ghi chú dài trên 100 ký tự. | G73: 1. Bấm nút Xem trên dòng đang Khóa | H73: Loại LTK khóa | I73: - Cửa sổ Xem mở bình thường và hiện đủ thông tin | J73: - Cửa sổ Xem mở bình thường và hiện đủ thông tin | K73: Passed
C74: TC_04.011 | D74: Bấm Đóng khi chưa sửa gì | E74: P1 | F74: Đăng nhập bằng tài khoản có quyền "Quản lý danh mục loại tài khoản". Danh mục có 7 loại tài khoản: 6 loại Hoạt động và 1 loại đang Khóa. Loại "Tài khoản tài sản" đang được nhiều tài khoản sử dụng; loại "LTK thử" chưa có tài khoản nào dùng; có ít nhất 1 loại đã nhập Ghi chú dài trên 100 ký tự. | G74: 1. Bấm Sửa một dòng 2. Không đổi gì 3. Bấm Đóng | H74: — | I74: - Cửa sổ đóng ngay, không hỏi lại | J74: - Cửa sổ đóng ngay, không hỏi lại | K74: Passed
C75: TC_04.012 | D75: Cảnh báo khi đóng lúc đang sửa dở | E75: P0 | F75: Đăng nhập bằng tài khoản có quyền "Quản lý danh mục loại tài khoản". Danh mục có 7 loại tài khoản: 6 loại Hoạt động và 1 loại đang Khóa. Loại "Tài khoản tài sản" đang được nhiều tài khoản sử dụng; loại "LTK thử" chưa có tài khoản nào dùng; có ít nhất 1 loại đã nhập Ghi chú dài trên 100 ký tự. | G75: 1. Bấm Sửa một dòng 2. Đổi Tên nhưng chưa Lưu 3. Bấm Đóng | H75: Tên: sửa dở dang | I75: - Hệ thống cảnh báo dữ liệu chưa lưu và hỏi xác nhận - Chọn ở lại thì cửa sổ vẫn mở và giữ nguyên nội dung đang gõ - Chọn thoát thì dữ liệu cũ không bị đổi | J75: - Hệ thống cảnh báo dữ liệu chưa lưu và hỏi xác nhận - Chọn ở lại thì cửa sổ vẫn mở và giữ nguyên nội dung đang gõ - Chọn thoát thì dữ liệu cũ không bị đổi | K75: Passed
C76: TC_04.013 | D76: Chống bấm Lưu nhiều lần liên tiếp | E76: P1 | F76: Đăng nhập bằng tài khoản có quyền "Quản lý danh mục loại tài khoản". Danh mục có 7 loại tài khoản: 6 loại Hoạt động và 1 loại đang Khóa. Loại "Tài khoản tài sản" đang được nhiều tài khoản sử dụng; loại "LTK thử" chưa có tài khoản nào dùng; có ít nhất 1 loại đã nhập Ghi chú dài trên 100 ký tự. | G76: 1. Bấm Tạo mới, nhập đủ 2. Bấm Lưu liên tiếp 3 lần thật nhanh | H76: Mã: LTK9; Tên: Loại thử 9 | I76: - Chỉ tạo ra ĐÚNG 1 bản ghi LTK9 - Nút Lưu bị vô hiệu trong lúc xử lý | J76: - Chỉ tạo ra ĐÚNG 1 bản ghi LTK9 - Nút Lưu bị vô hiệu trong lúc xử lý | K76: Passed
C77: TC_04.014 | D77: Loại tài khoản mới dùng được ngay ở màn Danh mục tài khoản | E77: P0 | F77: Đăng nhập bằng tài khoản có quyền "Quản lý danh mục loại tài khoản". Danh mục có 7 loại tài khoản: 6 loại Hoạt động và 1 loại đang Khóa. Loại "Tài khoản tài sản" đang được nhiều tài khoản sử dụng; loại "LTK thử" chưa có tài khoản nào dùng; có ít nhất 1 loại đã nhập Ghi chú dài trên 100 ký tự. | G77: 1. Tạo mới loại LTK1 ở trạng thái Hoạt động 2. Sang màn Danh mục tài khoản, bấm Tạo mới 3. Mở danh sách chọn Loại tài khoản | H77: Loại: LTK1 | I77: - LTK1 có trong danh sách chọn và chọn được | J77: - LTK1 có trong danh sách chọn và chọn được | K77: Passed
C78: V. KHÓA & MỞ KHÓA
A79: Danh mục loại tài khoản | B79: KHÓA & MỞ KHÓA | C79: TC_05.001 | D79: Khóa một loại tài khoản chưa ai dùng | E79: P0 | F79: Đăng nhập bằng tài khoản có quyền "Quản lý danh mục loại tài khoản". Danh mục có 7 loại tài khoản: 6 loại Hoạt động và 1 loại đang Khóa. Loại "Tài khoản tài sản" đang được nhiều tài khoản sử dụng; loại "LTK thử" chưa có tài khoản nào dùng; có ít nhất 1 loại đã nhập Ghi chú dài trên 100 ký tự. | G79: 1. Bấm nút Khóa ở cột Trạng thái dòng LTK thử 2. Đọc hộp xác nhận 3. Bấm Khóa | H79: Loại: LTK thử | I79: - Hộp xác nhận tiêu đề "Xác nhận khóa", câu hỏi nêu đúng tên loại tài khoản - Thông báo "Khóa thành công" - Dòng đổi nhãn sang Khóa, nút đổi thành hình ổ khóa mở, nút Sửa chuyển sang mờ | J79: - Hộp xác nhận tiêu đề "Xác nhận khóa", câu hỏi nêu đúng tên loại tài khoản - Thông báo "Khóa thành công" - Dòng đổi nhãn sang Khóa, nút đổi thành hình ổ khóa mở, nút Sửa chuyển sang mờ | K79: Passed
C80: TC_05.002 | D80: Mở khóa một loại tài khoản đang Khóa | E80: P0 | F80: Đăng nhập bằng tài khoản có quyền "Quản lý danh mục loại tài khoản". Danh mục có 7 loại tài khoản: 6 loại Hoạt động và 1 loại đang Khóa. Loại "Tài khoản tài sản" đang được nhiều tài khoản sử dụng; loại "LTK thử" chưa có tài khoản nào dùng; có ít nhất 1 loại đã nhập Ghi chú dài trên 100 ký tự. Loại LTK thử đang ở trạng thái Khóa. | G80: 1. Bấm nút Mở khóa 2. Bấm Mở khóa trong hộp xác nhận | H80: Loại: LTK thử | I80: - Hộp xác nhận tiêu đề "Xác nhận mở khóa" - Thông báo "Mở khóa thành công" - Dòng quay lại nhãn Hoạt động, nút Sửa sáng trở lại | J80: - Hộp xác nhận tiêu đề "Xác nhận mở khóa" - Thông báo "Mở khóa thành công" - Dòng quay lại nhãn Hoạt động, nút Sửa sáng trở lại | K80: Passed
C81: TC_05.003 | D81: Không khóa được loại tài khoản đang được sử dụng | E81: P0 | F81: Đăng nhập bằng tài khoản có quyền "Quản lý danh mục loại tài khoản". Danh mục có 7 loại tài khoản: 6 loại Hoạt động và 1 loại đang Khóa. Loại "Tài khoản tài sản" đang được nhiều tài khoản sử dụng; loại "LTK thử" chưa có tài khoản nào dùng; có ít nhất 1 loại đã nhập Ghi chú dài trên 100 ký tự. Loại "Tài khoản tài sản" đang được nhiều tài khoản dùng. | G81: 1. Rê chuột vào nút Khóa của dòng Tài khoản tài sản 2. Thử bấm | H81: Loại: Tài khoản tài sản | I81: - Nút Khóa bị mờ, không bấm được - Rê chuột hiện chú thích "Đang được sử dụng, không thể khóa" Khác Danh mục tiền tệ: ở màn này đang dùng thì KHÔNG khóa được | J81: - Nút Khóa bị mờ, không bấm được - Rê chuột hiện chú thích "Đang được sử dụng, không thể khóa" Khác Danh mục tiền tệ: ở màn này đang dùng thì KHÔNG khóa được | K81: Passed
C82: TC_05.004 | D82: Hủy hộp xác nhận khóa | E82: P1 | F82: Đăng nhập bằng tài khoản có quyền "Quản lý danh mục loại tài khoản". Danh mục có 7 loại tài khoản: 6 loại Hoạt động và 1 loại đang Khóa. Loại "Tài khoản tài sản" đang được nhiều tài khoản sử dụng; loại "LTK thử" chưa có tài khoản nào dùng; có ít nhất 1 loại đã nhập Ghi chú dài trên 100 ký tự. | G82: 1. Bấm nút Khóa trên dòng LTK thử 2. Bấm Hủy | H82: Loại: LTK thử | I82: - Hộp đóng, trạng thái không đổi, không có thông báo thành công | J82: - Hộp đóng, trạng thái không đổi, không có thông báo thành công | K82: Passed
C83: TC_05.005 | D83: Loại tài khoản đã khóa không còn chọn được khi tạo tài khoản | E83: P0 | F83: Đăng nhập bằng tài khoản có quyền "Quản lý danh mục loại tài khoản". Danh mục có 7 loại tài khoản: 6 loại Hoạt động và 1 loại đang Khóa. Loại "Tài khoản tài sản" đang được nhiều tài khoản sử dụng; loại "LTK thử" chưa có tài khoản nào dùng; có ít nhất 1 loại đã nhập Ghi chú dài trên 100 ký tự. Loại LTK thử đang ở trạng thái Khóa. | G83: 1. Sang màn Danh mục tài khoản, bấm Tạo mới 2. Mở danh sách chọn Loại tài khoản | H83: Loại: LTK thử (đang Khóa) | I83: - LTK thử KHÔNG có trong danh sách chọn | J83: - LTK thử KHÔNG có trong danh sách chọn | K83: Passed
C84: TC_05.006 | D84: Tài khoản cũ vẫn hiện đúng loại đã bị khóa | E84: P0 | F84: Có sẵn 1 tài khoản đang gán loại "Tài khoản tài sản"; sau đó loại này bị chuyển sang Khóa. | G84: 1. Khóa loại Tài khoản tài sản (sau khi đã gỡ hết ràng buộc nếu cần) 2. Mở lại tài khoản cũ ở chế độ Sửa | H84: Loại: Tài khoản tài sản (đang Khóa) | I84: - Ô Loại tài khoản vẫn hiện đúng tên, không trống, không tự nhảy sang giá trị khác - Lưu lại tài khoản không làm mất giá trị loại Quy tắc chung toàn hệ thống: danh mục bị khóa vẫn phải hiện ở bản ghi đang dùng nó | J84: - Ô Loại tài khoản vẫn hiện đúng tên, không trống, không tự nhảy sang giá trị khác - Lưu lại tài khoản không làm mất giá trị loại Quy tắc chung toàn hệ thống: danh mục bị khóa vẫn phải hiện ở bản ghi đang dùng nó | K84: Passed
C85: TC_05.007 | D85: Người chỉ có quyền Xem không thấy nút Khóa | E85: P0 | F85: Đăng nhập bằng tài khoản chỉ có quyền "Xem danh mục loại tài khoản". | G85: 1. Mở màn hình 2. Nhìn cột Trạng thái | H85: — | I85: - Cột Trạng thái chỉ có nhãn, không có nút Khóa / Mở khóa | J85: - Cột Trạng thái chỉ có nhãn, không có nút Khóa / Mở khóa | K85: Passed
C86: VI. XÓA
A87: Danh mục loại tài khoản | B87: XÓA | C87: TC_06.001 | D87: Xóa loại tài khoản chưa ai dùng | E87: P0 | F87: Đăng nhập bằng tài khoản có quyền "Quản lý danh mục loại tài khoản". Danh mục có 7 loại tài khoản: 6 loại Hoạt động và 1 loại đang Khóa. Loại "Tài khoản tài sản" đang được nhiều tài khoản sử dụng; loại "LTK thử" chưa có tài khoản nào dùng; có ít nhất 1 loại đã nhập Ghi chú dài trên 100 ký tự. | G87: 1. Bấm nút Xóa trên dòng LTK thử 2. Đọc hộp xác nhận 3. Bấm Xóa | H87: Loại: LTK thử | I87: - Hộp xác nhận tiêu đề "Xác nhận xóa", câu hỏi nêu đúng tên loại tài khoản - Thông báo "Xóa thành công" - Dòng biến mất, tổng dưới bảng giảm 1 | J87: - Hộp xác nhận tiêu đề "Xác nhận xóa", câu hỏi nêu đúng tên loại tài khoản - Thông báo "Xóa thành công" - Dòng biến mất, tổng dưới bảng giảm 1 | K87: Passed
C88: TC_06.002 | D88: Hủy hộp xác nhận xóa | E88: P0 | F88: Đăng nhập bằng tài khoản có quyền "Quản lý danh mục loại tài khoản". Danh mục có 7 loại tài khoản: 6 loại Hoạt động và 1 loại đang Khóa. Loại "Tài khoản tài sản" đang được nhiều tài khoản sử dụng; loại "LTK thử" chưa có tài khoản nào dùng; có ít nhất 1 loại đã nhập Ghi chú dài trên 100 ký tự. | G88: 1. Bấm nút Xóa trên dòng LTK thử 2. Bấm Hủy | H88: Loại: LTK thử | I88: - Hộp đóng, dòng vẫn còn nguyên | J88: - Hộp đóng, dòng vẫn còn nguyên | K88: Passed
C89: TC_06.003 | D89: Nút Xóa bị vô hiệu với loại đang được sử dụng | E89: P0 | F89: Đăng nhập bằng tài khoản có quyền "Quản lý danh mục loại tài khoản". Danh mục có 7 loại tài khoản: 6 loại Hoạt động và 1 loại đang Khóa. Loại "Tài khoản tài sản" đang được nhiều tài khoản sử dụng; loại "LTK thử" chưa có tài khoản nào dùng; có ít nhất 1 loại đã nhập Ghi chú dài trên 100 ký tự. Loại "Tài khoản tài sản" đang được nhiều tài khoản dùng. | G89: 1. Rê chuột vào nút Xóa của dòng Tài khoản tài sản 2. Thử bấm | H89: Loại: Tài khoản tài sản | I89: - Nút Xóa bị mờ, không bấm được - Rê chuột hiện chú thích "Loại tài khoản đang được sử dụng, không thể xóa" | J89: - Nút Xóa bị mờ, không bấm được - Rê chuột hiện chú thích "Loại tài khoản đang được sử dụng, không thể xóa" | K89: Passed
C90: TC_06.004 | D90: Chặn xóa khi bỏ qua giao diện | E90: P0 | F90: Đăng nhập bằng tài khoản có quyền "Quản lý danh mục loại tài khoản". Danh mục có 7 loại tài khoản: 6 loại Hoạt động và 1 loại đang Khóa. Loại "Tài khoản tài sản" đang được nhiều tài khoản sử dụng; loại "LTK thử" chưa có tài khoản nào dùng; có ít nhất 1 loại đã nhập Ghi chú dài trên 100 ký tự. Loại "Tài khoản tài sản" đang được sử dụng. | G90: 1. Dùng công cụ kiểm thử API gọi thẳng chức năng Xóa loại Tài khoản tài sản 2. Mở lại màn hình | H90: Loại: Tài khoản tài sản | I90: - Hệ thống chặn, báo loại tài khoản đang được sử dụng - Dòng vẫn còn Không được dựa vào việc nút bị mờ ở giao diện để bảo vệ dữ liệu | J90: - Hệ thống chặn, báo loại tài khoản đang được sử dụng - Dòng vẫn còn Không được dựa vào việc nút bị mờ ở giao diện để bảo vệ dữ liệu | K90: Passed
C91: TC_06.005 | D91: Xóa loại tài khoản vừa bị người khác gán cho tài khoản | E91: P1 | F91: Hai tài khoản cùng thao tác. Loại LTK thử ban đầu chưa ai dùng. | G91: 1. Người 1 mở màn hình (nút Xóa của LTK thử đang sáng) 2. Người 2 tạo một tài khoản gán loại LTK thử 3. Người 1 bấm Xóa và xác nhận | H91: Loại: LTK thử | I91: - Hệ thống chặn lại, báo loại tài khoản đang được sử dụng - Dòng vẫn còn | J91: - Hệ thống chặn lại, báo loại tài khoản đang được sử dụng - Dòng vẫn còn | K91: Passed
C92: TC_06.006 | D92: Xóa dòng cuối cùng của trang | E92: P1 | F92: Đăng nhập bằng tài khoản có quyền "Quản lý danh mục loại tài khoản". Danh mục có 7 loại tài khoản: 6 loại Hoạt động và 1 loại đang Khóa. Loại "Tài khoản tài sản" đang được nhiều tài khoản sử dụng; loại "LTK thử" chưa có tài khoản nào dùng; có ít nhất 1 loại đã nhập Ghi chú dài trên 100 ký tự. Đang ở trang 2, trang 2 chỉ còn 1 dòng và dòng đó xóa được. | G92: 1. Xóa dòng duy nhất của trang 2 | H92: — | I92: - Xóa thành công - Màn tự lùi về trang 1, KHÔNG hiện bảng trống | J92: - Xóa thành công - Màn tự lùi về trang 1, KHÔNG hiện bảng trống | K92: Passed
C93: TC_06.007 | D93: Xóa loại tài khoản đang ở trạng thái Khóa | E93: P2 | F93: Đăng nhập bằng tài khoản có quyền "Quản lý danh mục loại tài khoản". Danh mục có 7 loại tài khoản: 6 loại Hoạt động và 1 loại đang Khóa. Loại "Tài khoản tài sản" đang được nhiều tài khoản sử dụng; loại "LTK thử" chưa có tài khoản nào dùng; có ít nhất 1 loại đã nhập Ghi chú dài trên 100 ký tự. Loại LTK thử đang Khóa và chưa ai dùng. | G93: 1. Bấm Xóa và xác nhận | H93: Loại: LTK thử | I93: - Xóa được bình thường; trạng thái Khóa không cản việc xóa | J93: - Xóa được bình thường; trạng thái Khóa không cản việc xóa | K93: Passed
C94: TC_06.008 | D94: Người chỉ có quyền Xem không thấy nút Xóa | E94: P0 | F94: Đăng nhập bằng tài khoản chỉ có quyền "Xem danh mục loại tài khoản". | G94: 1. Mở màn hình, nhìn cột Hành động | H94: — | I94: - Chỉ có nút Xem và nút Lịch sử chỉnh sửa, không có nút Xóa | J94: - Chỉ có nút Xem và nút Lịch sử chỉnh sửa, không có nút Xóa | K94: Passed
C95: VII. LỊCH SỬ CHỈNH SỬA
A96: Danh mục loại tài khoản | B96: LỊCH SỬ CHỈNH SỬA | C96: TC_07.001 | D96: Mở cửa sổ lịch sử chỉnh sửa | E96: P0 | F96: Đăng nhập bằng tài khoản có quyền "Quản lý danh mục loại tài khoản". Danh mục có 7 loại tài khoản: 6 loại Hoạt động và 1 loại đang Khóa. Loại "Tài khoản tài sản" đang được nhiều tài khoản sử dụng; loại "LTK thử" chưa có tài khoản nào dùng; có ít nhất 1 loại đã nhập Ghi chú dài trên 100 ký tự. | G96: 1. Bấm nút Lịch sử chỉnh sửa trên một dòng đã từng bị sửa | H96: — | I96: - Mở cửa sổ tiêu đề "Lịch sử chỉnh sửa loại tài khoản" - Có danh sách các lần thay đổi kèm thời điểm và người thực hiện | J96: - Mở cửa sổ tiêu đề "Lịch sử chỉnh sửa loại tài khoản" - Có danh sách các lần thay đổi kèm thời điểm và người thực hiện | K96: Passed
C97: TC_07.002 | D97: Lịch sử ghi nhận lần sửa vừa thực hiện | E97: P0 | F97: Đăng nhập bằng tài khoản có quyền "Quản lý danh mục loại tài khoản". Danh mục có 7 loại tài khoản: 6 loại Hoạt động và 1 loại đang Khóa. Loại "Tài khoản tài sản" đang được nhiều tài khoản sử dụng; loại "LTK thử" chưa có tài khoản nào dùng; có ít nhất 1 loại đã nhập Ghi chú dài trên 100 ký tự. | G97: 1. Sửa Tên của dòng LTK1 và Lưu 2. Bấm nút Lịch sử chỉnh sửa của dòng đó | H97: Tên cũ: Loại kiểm thử → Tên mới: Loại kiểm thử A | I97: - Lịch sử có bản ghi mới nhất, nêu rõ trường Tên loại tài khoản đổi từ giá trị cũ sang giá trị mới - Ghi đúng người thực hiện và thời điểm | J97: - Lịch sử có bản ghi mới nhất, nêu rõ trường Tên loại tài khoản đổi từ giá trị cũ sang giá trị mới - Ghi đúng người thực hiện và thời điểm | K97: Passed
C98: TC_07.003 | D98: Lịch sử sắp xếp mới nhất lên đầu | E98: P0 | F98: Đăng nhập bằng tài khoản có quyền "Quản lý danh mục loại tài khoản". Danh mục có 7 loại tài khoản: 6 loại Hoạt động và 1 loại đang Khóa. Loại "Tài khoản tài sản" đang được nhiều tài khoản sử dụng; loại "LTK thử" chưa có tài khoản nào dùng; có ít nhất 1 loại đã nhập Ghi chú dài trên 100 ký tự. Dòng LTK1 đã bị sửa ít nhất 3 lần vào các thời điểm khác nhau. | G98: 1. Mở cửa sổ lịch sử của LTK1 2. Đọc thứ tự các dòng | H98: — | I98: - Lần sửa gần nhất nằm ở TRÊN CÙNG, các lần cũ xếp xuống dưới Bẫy hay gặp: lịch sử xếp ngược, lần đầu tiên lại nằm trên cùng | J98: - Lần sửa gần nhất nằm ở TRÊN CÙNG, các lần cũ xếp xuống dưới Bẫy hay gặp: lịch sử xếp ngược, lần đầu tiên lại nằm trên cùng | K98: Passed
C99: TC_07.004 | D99: Lịch sử ghi nhận thay đổi trạng thái | E99: P1 | F99: Đăng nhập bằng tài khoản có quyền "Quản lý danh mục loại tài khoản". Danh mục có 7 loại tài khoản: 6 loại Hoạt động và 1 loại đang Khóa. Loại "Tài khoản tài sản" đang được nhiều tài khoản sử dụng; loại "LTK thử" chưa có tài khoản nào dùng; có ít nhất 1 loại đã nhập Ghi chú dài trên 100 ký tự. | G99: 1. Khóa dòng LTK1 2. Mở cửa sổ lịch sử của dòng đó | H99: — | I99: - Có bản ghi cho biết Trạng thái đổi từ "Hoạt động" sang "Khóa" - Giá trị hiển thị bằng nhãn tiếng Việt, không phải con số | J99: - Có bản ghi cho biết Trạng thái đổi từ "Hoạt động" sang "Khóa" - Giá trị hiển thị bằng nhãn tiếng Việt, không phải con số | K99: Passed
C100: TC_07.005 | D100: Lịch sử của bản ghi chưa từng bị sửa | E100: P2 | F100: Đăng nhập bằng tài khoản có quyền "Quản lý danh mục loại tài khoản". Danh mục có 7 loại tài khoản: 6 loại Hoạt động và 1 loại đang Khóa. Loại "Tài khoản tài sản" đang được nhiều tài khoản sử dụng; loại "LTK thử" chưa có tài khoản nào dùng; có ít nhất 1 loại đã nhập Ghi chú dài trên 100 ký tự. | G100: 1. Tạo mới một loại tài khoản 2. Bấm nút Lịch sử chỉnh sửa ngay | H100: Mã: LTK5 | I100: - Cửa sổ mở bình thường - Chỉ có bản ghi của lần tạo, hoặc thông báo chưa có thay đổi nào; không lỗi | J100: - Cửa sổ mở bình thường - Chỉ có bản ghi của lần tạo, hoặc thông báo chưa có thay đổi nào; không lỗi | K100: Passed
C101: TC_07.006 | D101: Đóng cửa sổ lịch sử | E101: P2 | F101: Đăng nhập bằng tài khoản có quyền "Quản lý danh mục loại tài khoản". Danh mục có 7 loại tài khoản: 6 loại Hoạt động và 1 loại đang Khóa. Loại "Tài khoản tài sản" đang được nhiều tài khoản sử dụng; loại "LTK thử" chưa có tài khoản nào dùng; có ít nhất 1 loại đã nhập Ghi chú dài trên 100 ký tự. | G101: 1. Mở cửa sổ lịch sử 2. Bấm Đóng | H101: — | I101: - Cửa sổ đóng, danh sách phía sau giữ nguyên bộ lọc và trang đang xem | J101: - Cửa sổ đóng, danh sách phía sau giữ nguyên bộ lọc và trang đang xem | K101: Passed
C102: VIII. XUẤT EXCEL & NHẬP EXCEL
A103: Danh mục loại tài khoản | B103: XUẤT EXCEL & NHẬP EXCEL | C103: TC_08.001 | D103: Xuất Excel toàn bộ danh mục | E103: P0 | F103: Đăng nhập bằng tài khoản có quyền "Quản lý danh mục loại tài khoản". Danh mục có 7 loại tài khoản: 6 loại Hoạt động và 1 loại đang Khóa. Loại "Tài khoản tài sản" đang được nhiều tài khoản sử dụng; loại "LTK thử" chưa có tài khoản nào dùng; có ít nhất 1 loại đã nhập Ghi chú dài trên 100 ký tự. | G103: 1. Không lọc gì 2. Bấm Xuất Excel 3. Mở file tải về | H103: — | I103: - Thông báo "Xuất Excel thành công" - File mở được và có đủ 7 dòng | J103: - Thông báo "Xuất Excel thành công" - File mở được và có đủ 7 dòng | K103: Passed
...

Sheet 5. Cập nhật nhanh giá dịch vụ
A1: MÔ TẢ TÍNH NĂNG (đọc trước khi xem testcase)
A2: 1. Mục đích tính năng | B2: Đặt HAI thông số chung dùng để tính giá bán dịch vụ bảo dưỡng cho toàn hệ thống: Hệ số giá bán dịch vụ và Định mức đàm phán giá (%). Bấm Lưu là hệ thống áp ngay hai thông số này cho TẤT CẢ gói bảo dưỡng đang có (khoảng 207 gói) và tính lại giá gốc của các cấp dịch vụ (khoảng 242 cấp). Màn hình nằm ở phân hệ Chăm sóc khách hàng → nhóm menu Danh mục- Dịch vụ → Cập nhật nhanh giá dịch vụ. Đây là màn có SỨC ẢNH HƯỞNG LỚN NHẤT trong nhóm danh mục dịch vụ: một lần bấm Lưu là đổi giá hàng trăm gói. Trước khi kiểm thử BẮT BUỘC phải sao lưu dữ liệu giá hiện tại.
A3: 2. Đối tượng được tính / hiển thị | B3: - Màn hình chỉ là MỘT khung nhập với 2 ô: Hệ số giá bán dịch vụ (bắt buộc) và Định mức đàm phán giá (%) (không bắt buộc). Không có bảng danh sách, không có bộ lọc. - Dưới 2 ô có dòng ghi chú nêu rõ SỐ GÓI BẢO DƯỠNG sẽ bị ảnh hưởng, và dòng "Cập nhật gần nhất" cho biết lần thay đổi trước đó. - Khi bấm Lưu: MỌI gói bảo dưỡng đều bị áp lại hệ số và định mức, KỂ CẢ gói đã được chỉnh riêng trước đó.
A4: 3. Đối tượng bị ẩn / không tính | B4: - Gói bảo dưỡng không xác định được đơn giá công của công ty sẽ bị BỎ QUA, không bị ghi giá về 0. Sau khi lưu, hệ thống báo lại số gói đã bỏ qua. Ở hệ thống cũ những gói này bị ghi giá gốc về 0 — tức là mất giá. Bản mới bỏ qua và báo lại. Đây là điểm bắt buộc phải kiểm. - Giá gốc của cấp dịch vụ CHỈ được tính lại khi Hệ số giá bán dịch vụ thực sự thay đổi. Nếu chỉ đổi Định mức đàm phán giá thì giá gốc giữ nguyên.
A5: 4. Bộ lọc thời gian áp dụng cho | B5: Không áp dụng. Màn hình không có bộ lọc nào. Dòng "Cập nhật gần nhất" chỉ để xem, không phải điều kiện lọc.
A6: 5. Cấu trúc dữ liệu / cây phân cấp | B6: Không có cây phân cấp. Toàn hệ thống chỉ có DUY NHẤT một bộ thông số này, dùng chung cho mọi công ty. Quan hệ với màn khác: hai thông số này chảy xuống Danh mục gói bảo dưỡng (mỗi gói có hệ số và định mức riêng, nhưng bị màn này ghi đè) và xuống cấp dịch vụ của từng gói (giá gốc).
A7: 6. Quy tắc cộng dồn / deduplicate | B7: Không cộng dồn, không có bản ghi trùng. Mỗi lần Lưu là GHI ĐÈ lên giá trị cũ, không tạo thêm bản ghi mới. Không có lịch sử thay đổi cho màn này — sai là không lùi lại được bằng giao diện.
A8: 7. Phân quyền cấp | B8: Chỉ MỘT quyền duy nhất: "Cập nhật nhanh giá dịch vụ". Có quyền thì vào được màn hình và bấm Lưu được. Không có quyền thì không vào được màn hình. Quyền này tồn tại ở CẢ hai cổng dưới cùng một tên. Người được cấp quyền ở cổng cũ HOẶC ở cổng mới đều dùng được màn này. Khi kiểm thử phân quyền, hãy kiểm đủ cả hai đường cấp quyền. Màn hình KHÔNG phân quyền theo công ty / phòng ban / bộ phận.
A9: 8. Cách tính các ô thống kê | B9: - Con số gói bảo dưỡng trong dòng ghi chú và trong hộp xác nhận = tổng số gói bảo dưỡng hiện có trong hệ thống, lấy trực tiếp từ dữ liệu chứ không phải số cố định. - Con số cấp dịch vụ trong hộp xác nhận = tổng số cấp dịch vụ sẽ được tính lại giá gốc. - Thông báo sau khi lưu nêu số gói đã cập nhật, số cấp đã tính lại giá và số gói bị bỏ qua.
A10: 9. Ghi chú đọc bảng | B10: - BẮT BUỘC sao lưu giá của các gói bảo dưỡng và cấp dịch vụ TRƯỚC lần bấm Lưu đầu tiên. Sao lưu sau khi đã lưu là mất dữ liệu gốc, không lấy lại được vì màn này không có lịch sử. - Hệ số giá bán dịch vụ: bắt buộc, phải lớn hơn 0, tối đa 999,99. - Định mức đàm phán giá (%): không bắt buộc, từ 0 đến 99. - Luôn có hộp xác nhận trước khi ghi, nêu rõ số gói và số cấp bị ảnh hưởng. Hệ thống cũ bấm Lưu là chạy luôn, không hỏi. - Sau khi lưu, muốn kiểm chứng phải sang màn Danh mục gói bảo dưỡng xem giá của gói cụ thể — màn này không hiện danh sách gói. - Lỗi nhập liệu chỉ hiện SAU lần bấm Lưu đầu tiên, không hiện ngay khi vừa gõ.
A11: Testcase _ Cập nhật nhanh giá dịch vụ- Cập nhật ngày 13/08/2026 | F11: TEST SUMMARY | I11: Số TH DNS kiểm thử đạt (P): | K11: =COUNTIF(K18:M1001,"Passed") | M11: Số trường hợp TP kiểm thử đạt (P): | P11: =COUNTIF(O18:Q200,"Passed")
I12: Số TH DNS kiểm thử không đạt (F) | K12: =COUNTIF(K18:M1001,"Failed") | M12: Số trường hợp TP kiểm thử không đạt (F) | P12: =COUNTIF(O19:Q201,"Fail")
I13: Số TH DNS kiểm thử đang xem xét (PE) | K13: =COUNTIF(K18:M1001,"Pending") | M13: Số trường hợp TP kiểm thử đang xem xét (PE) | P13: =COUNTIF(O20:Q202,"Pending")
I14: Số TH DNS kiểm thử chưa thực hiện | K14: =COUNTIF(K18:K1001,"Not Executed") | M14: Số trường hợp TP kiểm thử chưa thực hiện | P14: =K16-P15
I15: Tổng số TH DNS đã kiểm thử | K15: =sum(K11:K14) | M15: Tổng số trường hợp TP kiểm thử | P15: =sum(P11:Q13)
I16: Tổng số testcase | K16: =COUNTIF(I18:I1000,"*")
A17: Module | B17: Nhóm chức năng | C17: TC ID | D17: Chức năng | E17: Priority | F17: Tiền điều kiện | G17: Bước thực hiện | H17: Test Data | I17: Expected Result (chi tiết) | J17: KQ thực tế | K17: DNS check lần 1 | L17: DNS check lần 2 | M17: DNS check lần 3 | N17: Ghi chú | O17: TP check lần 1 | P17: TP check lần 2 | Q17: TP check lần 3
C18: Phân quyền & truy cập
A19: Cập nhật nhanh giá DV | B19: Phân quyền & truy cập | C19: TC-ROLE-01 | D19: Vào màn hình khi có quyền cấp ở cổng mới | E19: P0 | F19: Có sẵn 3 tài khoản: A được cấp quyền "Cập nhật nhanh giá dịch vụ" ở cổng mới; B được cấp quyền cùng tên ở cổng cũ; C không được cấp quyền này ở cả hai cổng. Hệ thống có khoảng 207 gói bảo dưỡng và 242 cấp dịch vụ. ĐÃ SAO LƯU toàn bộ giá của gói bảo dưỡng và cấp dịch vụ trước khi kiểm thử. | G19: 1. Đăng nhập bằng tài khoản A 2. Vào phân hệ Chăm sóc khách hàng → Danh mục- Dịch vụ → Cập nhật nhanh giá dịch vụ hoặc đường link chứa /customer-care/service-price-config | H19: Tài khoản A | I19: - Vào được màn hình - Hai ô nhập hiện giá trị đang lưu - Có nút Lưu | J19: - Vào được màn hình - Hai ô nhập hiện giá trị đang lưu - Có nút Lưu | K19: Passed
C20: TC-ROLE-02 | D20: Vào màn hình khi quyền chỉ được cấp ở cổng cũ | E20: P0 | F20: Có sẵn 3 tài khoản: A được cấp quyền "Cập nhật nhanh giá dịch vụ" ở cổng mới; B được cấp quyền cùng tên ở cổng cũ; C không được cấp quyền này ở cả hai cổng. Hệ thống có khoảng 207 gói bảo dưỡng và 242 cấp dịch vụ. ĐÃ SAO LƯU toàn bộ giá của gói bảo dưỡng và cấp dịch vụ trước khi kiểm thử. | G20: 1. Đăng nhập bằng tài khoản B (chỉ được cấp quyền ở cổng cũ) 2. Mở phân hệ Chăm sóc khách hàng, tìm mục Cập nhật nhanh giá dịch vụ | H20: Tài khoản B | I20: - Mục menu HIỆN và vào được màn hình - Nút Lưu dùng được bình thường Nếu người được cấp quyền ở cổng cũ mà bị đá về trang không tìm thấy thì là lỗi phân quyền, phải báo ngay | J20: - Mục menu HIỆN và vào được màn hình - Nút Lưu dùng được bình thường | K20: Passed
C21: TC-ROLE-03 | D21: Chặn vào màn hình khi không có quyền | E21: P0 | F21: Có sẵn 3 tài khoản: A được cấp quyền "Cập nhật nhanh giá dịch vụ" ở cổng mới; B được cấp quyền cùng tên ở cổng cũ; C không được cấp quyền này ở cả hai cổng. Hệ thống có khoảng 207 gói bảo dưỡng và 242 cấp dịch vụ. ĐÃ SAO LƯU toàn bộ giá của gói bảo dưỡng và cấp dịch vụ trước khi kiểm thử. | G21: 1. Đăng nhập bằng tài khoản C 2. Tìm mục Cập nhật nhanh giá dịch vụ trong phân hệ Chăm sóc khách hàng 3. Dán thẳng đường dẫn màn hình vào thanh địa chỉ | H21: Tài khoản C | I21: - Mục menu KHÔNG hiện - Dán thẳng đường dẫn thì chuyển sang trang báo không tìm thấy, không hiện giá trị thông số nào | J21: - Mục menu KHÔNG hiện - Dán thẳng đường dẫn thì chuyển sang trang báo không tìm thấy, không hiện giá trị thông số nào | K21: Passed
